Workbook
Name liste_évaluation: #REF!
Name valeurs: #REF!
Name valeurs: #REF!
Name valeurs: #REF!
Name valeurs: #REF!
Name valeurs: #REF!
Name valeurs: #REF!
Name valeurs: #REF!

Sheet Accueil

Sheet Méthodologie

Sheet Contexte
B2: Étapes préalables et description du contexte de priorisation
B4: Organisation pour laquelle la priorisation est effectuée
B5: Niveau d'avancement dans la mise en œuvre des ONR
B6: Documents politiques et stratégiques existants ou en préparation qui peuvent faciliter l'identification des cibles et ONR prioritaires
B7: Sources d'information pertinentes sur la situation relativement à l'atteinte des cibles des ONR
B8: Service responsable de la priorisation
B10: Noms et titres des analystes
B11: Personne responsable de l'analyse et du suivi
B12: Date de l'analyse

Sheet ONR 1
L1: 0 | M1: 1 | N1: 2 | O1: 3 | P1: 4 | Q1: 5
B2: ONR 1 : Sobriété · Utiliser les outils numériques pour consommer moins de ressources et réduire leurs effets sur l’environnement
B4: Cibles à évaluer | D4: Importance de la cible | F4: Performance actuelle | H4: Compétences internes et externes | J4: Priorité | V4: Mise en œuvre
D5: Avantages possibles et risques | E5: Importance | F5: Niveau actuel | G5: Ce qui est déjà fait et ce qui justifie la note | H5: Compétences nécessaires | I5: Points forts et points faibles | J5: Niveau de priorité | K5: Clé de priorisation | L5: Intervention urgente | M5: Intervention prioritaire | N5: Intervention à moyen terme | O5: Intervention à long terme | P5: Intervention de consolidation | Q5: Intervention non prioritaire | R5: Intervention non pertinente | S5: Libellé de priorité | T5: Score de priorité | U5: Code priorité et compétences | V5: Actions proposées pour atteindre la cible
B6: Renseigner les cellules jaunes pour les notes, puis les textes utiles. La priorité se calcule automatiquement. Faire défiler vers la droite pour proposer des actions.
B7: 1.1 | C7: Prendre en compte toutes les étapes de la vie des équipements et des logiciels, de leur création à leur fin de vie, pour contribuer à la transition énergétique. | D7: Avantages possibles : réduire les émissions de gaz à effet de serre de l’organisation et se préparer aux futures règles environnementales. Risque : payer plus cher à l’achat certains équipements conçus pour limiter leurs effets sur l’environnement. | E7: 3 | F7: 1 | G7: L’équipe Achats retient le prix d’achat comme seul critère de choix. Elle ne demande pas d’analyse du cycle de vie (ACV) aux fournisseurs dans les appels d’offres. | H7: 3 | I7: Point fort : la direction des achats souhaite adopter des pratiques plus durables. Point faible : l’équipe connaît peu les labels environnementaux des équipements informatiques. | J7: =S7 -> Intervention urgente | K7: =IF(IF(ISNUMBER(E7),AND(E7>=0,E7<=3,MOD(E7,1)=0),FALSE),IF(E7=0,0,IF(IF(ISNUMBER(F7),AND(F7>=1,F7<=4,MOD(F7,1)=0),FALSE),E7*10+F7,"")),"") -> 31 | L7: =IF(ISNUMBER(K7),K7=31,FALSE) -> TRUE | M7: =IF(ISNUMBER(K7),OR(K7=21,K7=32),FALSE) -> FALSE | N7: =IF(ISNUMBER(K7),OR(K7=22,K7=33),FALSE) -> FALSE | O7: =IF(ISNUMBER(K7),OR(K7=11,K7=12),FALSE) -> FALSE | P7: =IF(ISNUMBER(K7),OR(K7=23,K7=34),FALSE) -> FALSE | Q7: =IF(ISNUMBER(K7),OR(K7=13,K7=14,K7=24),FALSE) -> FALSE | R7: =IF(ISNUMBER(K7),K7=0,FALSE) -> FALSE | S7: =IF(ISNUMBER(T7),INDEX($L$5:$R$5,1,7-T7),"") -> Intervention urgente | T7: =IF(ISNUMBER(K7),IF(L7,6,IF(M7,5,IF(N7,4,IF(O7,3,IF(P7,2,IF(Q7,1,0)))))),"") -> 6 | U7: =IF(AND(ISNUMBER(T7),ISNUMBER(H7)),IF(AND(H7>=1,H7<=4,MOD(H7,1)=0),T7*10+H7,""),"") -> 63 | V7: Former l’équipe Achats aux critères du numérique responsable et aux labels TCO et EPEAT. Dans les prochains appels d’offres pour remplacer les serveurs, faire compter les critères environnementaux pour 15 % de la note.
B8: 1.2 | C8: Utiliser les équipements plus longtemps, même après la fin de leur amortissement, c’est-à-dire la période sur laquelle leur coût est réparti dans les comptes. | D8: Avantages possibles : réduire les dépenses d’achat de matériel et les déchets d’équipements électriques et électroniques (DEEE). | E8: 3 | F8: 3 | G8: L’organisation a porté la durée de renouvellement des ordinateurs portables de trois à quatre ans l’année dernière. Elle dispose d’un contrat de maintenance. | H8: 2 | I8: Point fort : l’équipe technique peut réparer les équipements en interne. Point faible : certains utilisateurs demandent du matériel neuf pour son apparence. | J8: =S8 -> Intervention à moyen terme | K8: =IF(IF(ISNUMBER(E8),AND(E8>=0,E8<=3,MOD(E8,1)=0),FALSE),IF(E8=0,0,IF(IF(ISNUMBER(F8),AND(F8>=1,F8<=4,MOD(F8,1)=0),FALSE),E8*10+F8,"")),"") -> 33 | L8: =IF(ISNUMBER(K8),K8=31,FALSE) -> FALSE | M8: =IF(ISNUMBER(K8),OR(K8=21,K8=32),FALSE) -> FALSE | N8: =IF(ISNUMBER(K8),OR(K8=22,K8=33),FALSE) -> TRUE | O8: =IF(ISNUMBER(K8),OR(K8=11,K8=12),FALSE) -> FALSE | P8: =IF(ISNUMBER(K8),OR(K8=23,K8=34),FALSE) -> FALSE | Q8: =IF(ISNUMBER(K8),OR(K8=13,K8=14,K8=24),FALSE) -> FALSE | R8: =IF(ISNUMBER(K8),K8=0,FALSE) -> FALSE | S8: =IF(ISNUMBER(T8),INDEX($L$5:$R$5,1,7-T8),"") -> Intervention à moyen terme | T8: =IF(ISNUMBER(K8),IF(L8,6,IF(M8,5,IF(N8,4,IF(O8,3,IF(P8,2,IF(Q8,1,0)))))),"") -> 4 | U8: =IF(AND(ISNUMBER(T8),ISNUMBER(H8)),IF(AND(H8>=1,H8<=4,MOD(H8,1)=0),T8*10+H8,""),"") -> 42 | V8: Répartir le coût des équipements dans les comptes sur cinq ans au minimum : c’est la durée d’amortissement. Prévoir un stock de pièces détachées pour faciliter les réparations. Expliquer aux équipes comment garder leur ordinateur plus longtemps permet d’éviter des émissions de gaz à effet de serre.
B9: 1.3 | C9: Concevoir des services numériques qui limitent leurs effets sur l’environnement. Choisir des technologies qui contribuent aux Objectifs de développement durable (ODD). | D9: Avantages possibles : réduire les effets des services sur l’environnement dès leur conception, faciliter leur utilisation et contribuer aux Objectifs de développement durable (ODD). Risques : accumuler des problèmes techniques non résolus ou créer des logiciels trop gourmands en ressources, qui obligent à remplacer le matériel plus tôt. | E9: 3 | F9: 2 | G9: Les équipes valident les nouveaux services et sites web selon des critères fonctionnels, graphiques et financiers. Elles ne mesurent ni le poids des pages ni l’impact environnemental du code. | H9: 2 | I9: Point fort : les développeurs et les chefs de produit s’intéressent aux effets de leurs activités sur la société et l’environnement. Points faibles : ils connaissent peu les guides pour concevoir des services numériques moins polluants, comme le RGESN. Ils savent peu comment relier leurs projets aux ODD. | J9: =S9 -> Intervention prioritaire | K9: =IF(IF(ISNUMBER(E9),AND(E9>=0,E9<=3,MOD(E9,1)=0),FALSE),IF(E9=0,0,IF(IF(ISNUMBER(F9),AND(F9>=1,F9<=4,MOD(F9,1)=0),FALSE),E9*10+F9,"")),"") -> 32 | L9: =IF(ISNUMBER(K9),K9=31,FALSE) -> FALSE | M9: =IF(ISNUMBER(K9),OR(K9=21,K9=32),FALSE) -> TRUE | N9: =IF(ISNUMBER(K9),OR(K9=22,K9=33),FALSE) -> FALSE | O9: =IF(ISNUMBER(K9),OR(K9=11,K9=12),FALSE) -> FALSE | P9: =IF(ISNUMBER(K9),OR(K9=23,K9=34),FALSE) -> FALSE | Q9: =IF(ISNUMBER(K9),OR(K9=13,K9=14,K9=24),FALSE) -> FALSE | R9: =IF(ISNUMBER(K9),K9=0,FALSE) -> FALSE | S9: =IF(ISNUMBER(T9),INDEX($L$5:$R$5,1,7-T9),"") -> Intervention prioritaire | T9: =IF(ISNUMBER(K9),IF(L9,6,IF(M9,5,IF(N9,4,IF(O9,3,IF(P9,2,IF(Q9,1,0)))))),"") -> 5 | U9: =IF(AND(ISNUMBER(T9),ISNUMBER(H9)),IF(AND(H9>=1,H9<=4,MOD(H9,1)=0),T9*10+H9,""),"") -> 52 | V9: 1. Former les équipes de conception, de développement et de gestion de projet à créer des services numériques qui limitent leurs effets sur l’environnement. 2. Ajouter des exigences environnementales aux cahiers des charges, comme limiter le poids des images et réduire les demandes envoyées aux serveurs. 3. Pour chaque nouveau projet, préciser à quels Objectifs de développement durable il contribue.
B10: 1.4 | C10: Adopter des pratiques qui consomment moins de matériel, de ressources, d’énergie et de consommables, comme le papier ou l’encre. | J10: =S10 | K10: =IF(IF(ISNUMBER(E10),AND(E10>=0,E10<=3,MOD(E10,1)=0),FALSE),IF(E10=0,0,IF(IF(ISNUMBER(F10),AND(F10>=1,F10<=4,MOD(F10,1)=0),FALSE),E10*10+F10,"")),"") | L10: =IF(ISNUMBER(K10),K10=31,FALSE) -> FALSE | M10: =IF(ISNUMBER(K10),OR(K10=21,K10=32),FALSE) -> FALSE | N10: =IF(ISNUMBER(K10),OR(K10=22,K10=33),FALSE) -> FALSE | O10: =IF(ISNUMBER(K10),OR(K10=11,K10=12),FALSE) -> FALSE | P10: =IF(ISNUMBER(K10),OR(K10=23,K10=34),FALSE) -> FALSE | Q10: =IF(ISNUMBER(K10),OR(K10=13,K10=14,K10=24),FALSE) -> FALSE | R10: =IF(ISNUMBER(K10),K10=0,FALSE) -> FALSE | S10: =IF(ISNUMBER(T10),INDEX($L$5:$R$5,1,7-T10),"") | T10: =IF(ISNUMBER(K10),IF(L10,6,IF(M10,5,IF(N10,4,IF(O10,3,IF(P10,2,IF(Q10,1,0)))))),"") | U10: =IF(AND(ISNUMBER(T10),ISNUMBER(H10)),IF(AND(H10>=1,H10<=4,MOD(H10,1)=0),T10*10+H10,""),"")
B11: 1.5 | C11: Réutiliser ou recycler les déchets pour en faire de nouvelles ressources. Soutenir les emplois liés à leur traitement et à l’économie circulaire. | J11: =S11 | K11: =IF(IF(ISNUMBER(E11),AND(E11>=0,E11<=3,MOD(E11,1)=0),FALSE),IF(E11=0,0,IF(IF(ISNUMBER(F11),AND(F11>=1,F11<=4,MOD(F11,1)=0),FALSE),E11*10+F11,"")),"") | L11: =IF(ISNUMBER(K11),K11=31,FALSE) -> FALSE | M11: =IF(ISNUMBER(K11),OR(K11=21,K11=32),FALSE) -> FALSE | N11: =IF(ISNUMBER(K11),OR(K11=22,K11=33),FALSE) -> FALSE | O11: =IF(ISNUMBER(K11),OR(K11=11,K11=12),FALSE) -> FALSE | P11: =IF(ISNUMBER(K11),OR(K11=23,K11=34),FALSE) -> FALSE | Q11: =IF(ISNUMBER(K11),OR(K11=13,K11=14,K11=24),FALSE) -> FALSE | R11: =IF(ISNUMBER(K11),K11=0,FALSE) -> FALSE | S11: =IF(ISNUMBER(T11),INDEX($L$5:$R$5,1,7-T11),"") | T11: =IF(ISNUMBER(K11),IF(L11,6,IF(M11,5,IF(N11,4,IF(O11,3,IF(P11,2,IF(Q11,1,0)))))),"") | U11: =IF(AND(ISNUMBER(T11),ISNUMBER(H11)),IF(AND(H11>=1,H11<=4,MOD(H11,1)=0),T11*10+H11,""),"")
B12: 1.6 | C12: Choisir des énergies renouvelables et encourager leur utilisation. | J12: =S12 | K12: =IF(IF(ISNUMBER(E12),AND(E12>=0,E12<=3,MOD(E12,1)=0),FALSE),IF(E12=0,0,IF(IF(ISNUMBER(F12),AND(F12>=1,F12<=4,MOD(F12,1)=0),FALSE),E12*10+F12,"")),"") | L12: =IF(ISNUMBER(K12),K12=31,FALSE) -> FALSE | M12: =IF(ISNUMBER(K12),OR(K12=21,K12=32),FALSE) -> FALSE | N12: =IF(ISNUMBER(K12),OR(K12=22,K12=33),FALSE) -> FALSE | O12: =IF(ISNUMBER(K12),OR(K12=11,K12=12),FALSE) -> FALSE | P12: =IF(ISNUMBER(K12),OR(K12=23,K12=34),FALSE) -> FALSE | Q12: =IF(ISNUMBER(K12),OR(K12=13,K12=14,K12=24),FALSE) -> FALSE | R12: =IF(ISNUMBER(K12),K12=0,FALSE) -> FALSE | S12: =IF(ISNUMBER(T12),INDEX($L$5:$R$5,1,7-T12),"") | T12: =IF(ISNUMBER(K12),IF(L12,6,IF(M12,5,IF(N12,4,IF(O12,3,IF(P12,2,IF(Q12,1,0)))))),"") | U12: =IF(AND(ISNUMBER(T12),ISNUMBER(H12)),IF(AND(H12>=1,H12<=4,MOD(H12,1)=0),T12*10+H12,""),"")
B13: 1.7 | C13: Réserver l’intelligence artificielle aux besoins qui la justifient et privilégier des solutions sobres en ressources. | D13: Avantages possibles : maîtriser les coûts du matériel et des services d’IA, et réduire les émissions de gaz à effet de serre liées à leur entraînement et à leur utilisation. Risque : utiliser l’IA par effet de mode, sans besoin réel, et consommer davantage de ressources. | E13: 3 | F13: 1 | G13: Les équipes métiers expérimentent plusieurs projets d’IA générative, dont des usages de ChatGPT. Elles ne mesurent pas leur impact énergétique et ne disposent pas de charte pour encadrer les besoins et les usages. | H13: 2 | I13: Point fort : l’équipe chargée des données et de l’informatique dispose de compétences techniques et souhaite explorer ces outils. Points faibles : elle connaît peu les méthodes pour mesurer et réduire la consommation de l’IA. Elle manque aussi de recul pour savoir quand l’IA est utile. | J13: =S13 -> Intervention urgente | K13: =IF(IF(ISNUMBER(E13),AND(E13>=0,E13<=3,MOD(E13,1)=0),FALSE),IF(E13=0,0,IF(IF(ISNUMBER(F13),AND(F13>=1,F13<=4,MOD(F13,1)=0),FALSE),E13*10+F13,"")),"") -> 31 | L13: =IF(ISNUMBER(K13),K13=31,FALSE) -> TRUE | M13: =IF(ISNUMBER(K13),OR(K13=21,K13=32),FALSE) -> FALSE | N13: =IF(ISNUMBER(K13),OR(K13=22,K13=33),FALSE) -> FALSE | O13: =IF(ISNUMBER(K13),OR(K13=11,K13=12),FALSE) -> FALSE | P13: =IF(ISNUMBER(K13),OR(K13=23,K13=34),FALSE) -> FALSE | Q13: =IF(ISNUMBER(K13),OR(K13=13,K13=14,K13=24),FALSE) -> FALSE | R13: =IF(ISNUMBER(K13),K13=0,FALSE) -> FALSE | S13: =IF(ISNUMBER(T13),INDEX($L$5:$R$5,1,7-T13),"") -> Intervention urgente | T13: =IF(ISNUMBER(K13),IF(L13,6,IF(M13,5,IF(N13,4,IF(O13,3,IF(P13,2,IF(Q13,1,0)))))),"") -> 6 | U13: =IF(AND(ISNUMBER(T13),ISNUMBER(H13)),IF(AND(H13>=1,H13<=4,MOD(H13,1)=0),T13*10+H13,""),"") -> 62 | V13: 1. Vérifier le besoin avant chaque projet : faut-il de l’IA ou un outil informatique classique suffit-il ? 2. Choisir de petits modèles spécialisés quand ils répondent au besoin. 3. Former les développeurs et les spécialistes des données à réduire la consommation de l’IA, en améliorant le code et en évitant les calculs répétés.
B14: 1.8 | C14: Mesurer et réduire ce que consomme l’intelligence artificielle, pendant son entraînement comme pendant son utilisation. | D14: Avantages possibles : maîtriser les coûts du matériel et des services d’IA, et réduire les émissions de gaz à effet de serre liées à leur entraînement et à leur utilisation. Risque : utiliser l’IA par effet de mode, sans besoin réel, et consommer davantage de ressources. | E14: 3 | F14: 1 | G14: Les équipes métiers expérimentent plusieurs projets d’IA générative, dont des usages de ChatGPT. Elles ne mesurent pas leur impact énergétique et ne disposent pas de charte pour encadrer les besoins et les usages. | H14: 2 | I14: Point fort : l’équipe chargée des données et de l’informatique dispose de compétences techniques et souhaite explorer ces outils. Points faibles : elle connaît peu les méthodes pour mesurer et réduire la consommation de l’IA. Elle manque aussi de recul pour savoir quand l’IA est utile. | J14: =S14 -> Intervention urgente | K14: =IF(IF(ISNUMBER(E14),AND(E14>=0,E14<=3,MOD(E14,1)=0),FALSE),IF(E14=0,0,IF(IF(ISNUMBER(F14),AND(F14>=1,F14<=4,MOD(F14,1)=0),FALSE),E14*10+F14,"")),"") -> 31 | L14: =IF(ISNUMBER(K14),K14=31,FALSE) -> TRUE | M14: =IF(ISNUMBER(K14),OR(K14=21,K14=32),FALSE) -> FALSE | N14: =IF(ISNUMBER(K14),OR(K14=22,K14=33),FALSE) -> FALSE | O14: =IF(ISNUMBER(K14),OR(K14=11,K14=12),FALSE) -> FALSE | P14: =IF(ISNUMBER(K14),OR(K14=23,K14=34),FALSE) -> FALSE | Q14: =IF(ISNUMBER(K14),OR(K14=13,K14=14,K14=24),FALSE) -> FALSE | R14: =IF(ISNUMBER(K14),K14=0,FALSE) -> FALSE | S14: =IF(ISNUMBER(T14),INDEX($L$5:$R$5,1,7-T14),"") -> Intervention urgente | T14: =IF(ISNUMBER(K14),IF(L14,6,IF(M14,5,IF(N14,4,IF(O14,3,IF(P14,2,IF(Q14,1,0)))))),"") -> 6 | U14: =IF(AND(ISNUMBER(T14),ISNUMBER(H14)),IF(AND(H14>=1,H14<=4,MOD(H14,1)=0),T14*10+H14,""),"") -> 62 | V14: 1. Vérifier le besoin avant chaque projet : faut-il de l’IA ou un outil informatique classique suffit-il ? 2. Choisir de petits modèles spécialisés quand ils répondent au besoin. 3. Former les développeurs et les spécialistes des données à réduire la consommation de l’IA, en améliorant le code et en évitant les calculs répétés.

Sheet ONR 2
L1: 0 | M1: 1 | N1: 2 | O1: 3 | P1: 4 | Q1: 5
B2: ONR 2 : Inclusion · Développer des services numériques durables que toutes et tous peuvent utiliser
B4: Cibles à évaluer | D4: Importance de la cible | F4: Performance actuelle | H4: Compétences internes et externes | J4: Priorité | V4: Mise en œuvre
D5: Avantages possibles et risques | E5: Importance | F5: Niveau actuel | G5: Ce qui est déjà fait et ce qui justifie la note | H5: Compétences nécessaires | I5: Points forts et points faibles | J5: Niveau de priorité | K5: Clé de priorisation | L5: Intervention urgente | M5: Intervention prioritaire | N5: Intervention à moyen terme | O5: Intervention à long terme | P5: Intervention de consolidation | Q5: Intervention non prioritaire | R5: Intervention non pertinente | S5: Libellé de priorité | T5: Score de priorité | U5: Code priorité et compétences | V5: Actions proposées pour atteindre la cible | W5: Adhérence
B6: Renseigner les cellules jaunes pour les notes, puis les textes utiles. La priorité se calcule automatiquement. Faire défiler vers la droite pour proposer des actions.
B7: 2.1 | C7: Intégrer dans tous les achats des exigences qui tiennent compte de leurs effets sur la société et l’environnement. | J7: =S7 | K7: =IF(IF(ISNUMBER(E7),AND(E7>=0,E7<=3,MOD(E7,1)=0),FALSE),IF(E7=0,0,IF(IF(ISNUMBER(F7),AND(F7>=1,F7<=4,MOD(F7,1)=0),FALSE),E7*10+F7,"")),"") | L7: =IF(ISNUMBER(K7),K7=31,FALSE) -> FALSE | M7: =IF(ISNUMBER(K7),OR(K7=21,K7=32),FALSE) -> FALSE | N7: =IF(ISNUMBER(K7),OR(K7=22,K7=33),FALSE) -> FALSE | O7: =IF(ISNUMBER(K7),OR(K7=11,K7=12),FALSE) -> FALSE | P7: =IF(ISNUMBER(K7),OR(K7=23,K7=34),FALSE) -> FALSE | Q7: =IF(ISNUMBER(K7),OR(K7=13,K7=14,K7=24),FALSE) -> FALSE | R7: =IF(ISNUMBER(K7),K7=0,FALSE) -> FALSE | S7: =IF(ISNUMBER(T7),INDEX($L$5:$R$5,1,7-T7),"") | T7: =IF(ISNUMBER(K7),IF(L7,6,IF(M7,5,IF(N7,4,IF(O7,3,IF(P7,2,IF(Q7,1,0)))))),"") | U7: =IF(AND(ISNUMBER(T7),ISNUMBER(H7)),IF(AND(H7>=1,H7<=4,MOD(H7,1)=0),T7*10+H7,""),"")
B8: 2.2 | C8: Rendre les services numériques accessibles à toutes et tous. Mesurer leur respect du RGAA, le référentiel français sur l’accessibilité numérique. | J8: =S8 | K8: =IF(IF(ISNUMBER(E8),AND(E8>=0,E8<=3,MOD(E8,1)=0),FALSE),IF(E8=0,0,IF(IF(ISNUMBER(F8),AND(F8>=1,F8<=4,MOD(F8,1)=0),FALSE),E8*10+F8,"")),"") | L8: =IF(ISNUMBER(K8),K8=31,FALSE) -> FALSE | M8: =IF(ISNUMBER(K8),OR(K8=21,K8=32),FALSE) -> FALSE | N8: =IF(ISNUMBER(K8),OR(K8=22,K8=33),FALSE) -> FALSE | O8: =IF(ISNUMBER(K8),OR(K8=11,K8=12),FALSE) -> FALSE | P8: =IF(ISNUMBER(K8),OR(K8=23,K8=34),FALSE) -> FALSE | Q8: =IF(ISNUMBER(K8),OR(K8=13,K8=14,K8=24),FALSE) -> FALSE | R8: =IF(ISNUMBER(K8),K8=0,FALSE) -> FALSE | S8: =IF(ISNUMBER(T8),INDEX($L$5:$R$5,1,7-T8),"") | T8: =IF(ISNUMBER(K8),IF(L8,6,IF(M8,5,IF(N8,4,IF(O8,3,IF(P8,2,IF(Q8,1,0)))))),"") | U8: =IF(AND(ISNUMBER(T8),ISNUMBER(H8)),IF(AND(H8>=1,H8<=4,MOD(H8,1)=0),T8*10+H8,""),"")
B9: 2.3 | C9: Créer des applications utiles, faciles à utiliser et réellement utilisées : les « 3 U ». Les rendre accessibles pour permettre à chacun d’utiliser le numérique. | J9: =S9 | K9: =IF(IF(ISNUMBER(E9),AND(E9>=0,E9<=3,MOD(E9,1)=0),FALSE),IF(E9=0,0,IF(IF(ISNUMBER(F9),AND(F9>=1,F9<=4,MOD(F9,1)=0),FALSE),E9*10+F9,"")),"") | L9: =IF(ISNUMBER(K9),K9=31,FALSE) -> FALSE | M9: =IF(ISNUMBER(K9),OR(K9=21,K9=32),FALSE) -> FALSE | N9: =IF(ISNUMBER(K9),OR(K9=22,K9=33),FALSE) -> FALSE | O9: =IF(ISNUMBER(K9),OR(K9=11,K9=12),FALSE) -> FALSE | P9: =IF(ISNUMBER(K9),OR(K9=23,K9=34),FALSE) -> FALSE | Q9: =IF(ISNUMBER(K9),OR(K9=13,K9=14,K9=24),FALSE) -> FALSE | R9: =IF(ISNUMBER(K9),K9=0,FALSE) -> FALSE | S9: =IF(ISNUMBER(T9),INDEX($L$5:$R$5,1,7-T9),"") | T9: =IF(ISNUMBER(K9),IF(L9,6,IF(M9,5,IF(N9,4,IF(O9,3,IF(P9,2,IF(Q9,1,0)))))),"") | U9: =IF(AND(ISNUMBER(T9),ISNUMBER(H9)),IF(AND(H9>=1,H9<=4,MOD(H9,1)=0),T9*10+H9,""),"")
B10: 2.4 | C10: Concevoir les services avec leurs utilisateurs et utilisatrices, en se concentrant sur leurs besoins réels. | J10: =S10 | K10: =IF(IF(ISNUMBER(E10),AND(E10>=0,E10<=3,MOD(E10,1)=0),FALSE),IF(E10=0,0,IF(IF(ISNUMBER(F10),AND(F10>=1,F10<=4,MOD(F10,1)=0),FALSE),E10*10+F10,"")),"") | L10: =IF(ISNUMBER(K10),K10=31,FALSE) -> FALSE | M10: =IF(ISNUMBER(K10),OR(K10=21,K10=32),FALSE) -> FALSE | N10: =IF(ISNUMBER(K10),OR(K10=22,K10=33),FALSE) -> FALSE | O10: =IF(ISNUMBER(K10),OR(K10=11,K10=12),FALSE) -> FALSE | P10: =IF(ISNUMBER(K10),OR(K10=23,K10=34),FALSE) -> FALSE | Q10: =IF(ISNUMBER(K10),OR(K10=13,K10=14,K10=24),FALSE) -> FALSE | R10: =IF(ISNUMBER(K10),K10=0,FALSE) -> FALSE | S10: =IF(ISNUMBER(T10),INDEX($L$5:$R$5,1,7-T10),"") | T10: =IF(ISNUMBER(K10),IF(L10,6,IF(M10,5,IF(N10,4,IF(O10,3,IF(P10,2,IF(Q10,1,0)))))),"") | U10: =IF(AND(ISNUMBER(T10),ISNUMBER(H10)),IF(AND(H10>=1,H10<=4,MOD(H10,1)=0),T10*10+H10,""),"")
B11: 2.5 | C11: Vérifier que l’intelligence artificielle ne discrimine personne et que ses services peuvent être utilisés par toutes et tous. | J11: =S11 -> 0 | K11: =IF(IF(ISNUMBER(E11),AND(E11>=0,E11<=3,MOD(E11,1)=0),FALSE),IF(E11=0,0,IF(IF(ISNUMBER(F11),AND(F11>=1,F11<=4,MOD(F11,1)=0),FALSE),E11*10+F11,"")),"") | L11: =IF(ISNUMBER(K11),K11=31,FALSE) -> FALSE | M11: =IF(ISNUMBER(K11),OR(K11=21,K11=32),FALSE) -> FALSE | N11: =IF(ISNUMBER(K11),OR(K11=22,K11=33),FALSE) -> FALSE | O11: =IF(ISNUMBER(K11),OR(K11=11,K11=12),FALSE) -> FALSE | P11: =IF(ISNUMBER(K11),OR(K11=23,K11=34),FALSE) -> FALSE | Q11: =IF(ISNUMBER(K11),OR(K11=13,K11=14,K11=24),FALSE) -> FALSE | R11: =IF(ISNUMBER(K11),K11=0,FALSE) -> FALSE | S11: =IF(ISNUMBER(T11),INDEX($L$5:$R$5,1,7-T11),"") | T11: =IF(ISNUMBER(K11),IF(L11,6,IF(M11,5,IF(N11,4,IF(O11,3,IF(P11,2,IF(Q11,1,0)))))),"") | U11: =IF(AND(ISNUMBER(T11),ISNUMBER(H11)),IF(AND(H11>=1,H11<=4,MOD(H11,1)=0),T11*10+H11,""),"")

Sheet ONR 3
L1: 0 | M1: 1 | N1: 2 | O1: 3 | P1: 4 | Q1: 5
B2: ONR 3 : RSE · Utiliser le numérique de façon éthique et responsable
B4: Cibles à évaluer | D4: Importance de la cible | F4: Performance actuelle | H4: Compétences internes et externes | J4: Priorité | V4: Mise en œuvre
D5: Avantages possibles et risques | E5: Importance | F5: Niveau actuel | G5: Ce qui est déjà fait et ce qui justifie la note | H5: Compétences nécessaires | I5: Points forts et points faibles | J5: Niveau de priorité | K5: Clé de priorisation | L5: Intervention urgente | M5: Intervention prioritaire | N5: Intervention à moyen terme | O5: Intervention à long terme | P5: Intervention de consolidation | Q5: Intervention non prioritaire | R5: Intervention non pertinente | S5: Libellé de priorité | T5: Score de priorité | U5: Code priorité et compétences | V5: Actions proposées pour atteindre la cible
B6: Renseigner les cellules jaunes pour les notes, puis les textes utiles. La priorité se calcule automatiquement. Faire défiler vers la droite pour proposer des actions.
B7: 3.1 | C7: Utiliser les données et les services numériques avec mesure, en respectant les personnes et l’environnement. | J7: =S7 | K7: =IF(IF(ISNUMBER(E7),AND(E7>=0,E7<=3,MOD(E7,1)=0),FALSE),IF(E7=0,0,IF(IF(ISNUMBER(F7),AND(F7>=1,F7<=4,MOD(F7,1)=0),FALSE),E7*10+F7,"")),"") | L7: =IF(ISNUMBER(K7),K7=31,FALSE) -> FALSE | M7: =IF(ISNUMBER(K7),OR(K7=21,K7=32),FALSE) -> FALSE | N7: =IF(ISNUMBER(K7),OR(K7=22,K7=33),FALSE) -> FALSE | O7: =IF(ISNUMBER(K7),OR(K7=11,K7=12),FALSE) -> FALSE | P7: =IF(ISNUMBER(K7),OR(K7=23,K7=34),FALSE) -> FALSE | Q7: =IF(ISNUMBER(K7),OR(K7=13,K7=14,K7=24),FALSE) -> FALSE | R7: =IF(ISNUMBER(K7),K7=0,FALSE) -> FALSE | S7: =IF(ISNUMBER(T7),INDEX($L$5:$R$5,1,7-T7),"") | T7: =IF(ISNUMBER(K7),IF(L7,6,IF(M7,5,IF(N7,4,IF(O7,3,IF(P7,2,IF(Q7,1,0)))))),"") | U7: =IF(AND(ISNUMBER(T7),ISNUMBER(H7)),IF(AND(H7>=1,H7<=4,MOD(H7,1)=0),T7*10+H7,""),"")
B8: 3.2 | C8: Supprimer les pratiques et les interfaces qui trompent les utilisateurs sur les sites web, aussi appelées « dark patterns ». Respecter la réglementation. | J8: =S8 | K8: =IF(IF(ISNUMBER(E8),AND(E8>=0,E8<=3,MOD(E8,1)=0),FALSE),IF(E8=0,0,IF(IF(ISNUMBER(F8),AND(F8>=1,F8<=4,MOD(F8,1)=0),FALSE),E8*10+F8,"")),"") | L8: =IF(ISNUMBER(K8),K8=31,FALSE) -> FALSE | M8: =IF(ISNUMBER(K8),OR(K8=21,K8=32),FALSE) -> FALSE | N8: =IF(ISNUMBER(K8),OR(K8=22,K8=33),FALSE) -> FALSE | O8: =IF(ISNUMBER(K8),OR(K8=11,K8=12),FALSE) -> FALSE | P8: =IF(ISNUMBER(K8),OR(K8=23,K8=34),FALSE) -> FALSE | Q8: =IF(ISNUMBER(K8),OR(K8=13,K8=14,K8=24),FALSE) -> FALSE | R8: =IF(ISNUMBER(K8),K8=0,FALSE) -> FALSE | S8: =IF(ISNUMBER(T8),INDEX($L$5:$R$5,1,7-T8),"") | T8: =IF(ISNUMBER(K8),IF(L8,6,IF(M8,5,IF(N8,4,IF(O8,3,IF(P8,2,IF(Q8,1,0)))))),"") | U8: =IF(AND(ISNUMBER(T8),ISNUMBER(H8)),IF(AND(H8>=1,H8<=4,MOD(H8,1)=0),T8*10+H8,""),"")
B9: 3.3 | C9: Collecter seulement les données nécessaires au service rendu. Protéger la vie privée, réduire les effets sur l’environnement et respecter le RGPD, le règlement sur la protection des données personnelles. | J9: =S9 | K9: =IF(IF(ISNUMBER(E9),AND(E9>=0,E9<=3,MOD(E9,1)=0),FALSE),IF(E9=0,0,IF(IF(ISNUMBER(F9),AND(F9>=1,F9<=4,MOD(F9,1)=0),FALSE),E9*10+F9,"")),"") | L9: =IF(ISNUMBER(K9),K9=31,FALSE) -> FALSE | M9: =IF(ISNUMBER(K9),OR(K9=21,K9=32),FALSE) -> FALSE | N9: =IF(ISNUMBER(K9),OR(K9=22,K9=33),FALSE) -> FALSE | O9: =IF(ISNUMBER(K9),OR(K9=11,K9=12),FALSE) -> FALSE | P9: =IF(ISNUMBER(K9),OR(K9=23,K9=34),FALSE) -> FALSE | Q9: =IF(ISNUMBER(K9),OR(K9=13,K9=14,K9=24),FALSE) -> FALSE | R9: =IF(ISNUMBER(K9),K9=0,FALSE) -> FALSE | S9: =IF(ISNUMBER(T9),INDEX($L$5:$R$5,1,7-T9),"") | T9: =IF(ISNUMBER(K9),IF(L9,6,IF(M9,5,IF(N9,4,IF(O9,3,IF(P9,2,IF(Q9,1,0)))))),"") | U9: =IF(AND(ISNUMBER(T9),ISNUMBER(H9)),IF(AND(H9>=1,H9<=4,MOD(H9,1)=0),T9*10+H9,""),"")
B10: 3.4 | C10: Recruter des personnes aux profils variés dans les métiers du numérique. | J10: =S10 | K10: =IF(IF(ISNUMBER(E10),AND(E10>=0,E10<=3,MOD(E10,1)=0),FALSE),IF(E10=0,0,IF(IF(ISNUMBER(F10),AND(F10>=1,F10<=4,MOD(F10,1)=0),FALSE),E10*10+F10,"")),"") | L10: =IF(ISNUMBER(K10),K10=31,FALSE) -> FALSE | M10: =IF(ISNUMBER(K10),OR(K10=21,K10=32),FALSE) -> FALSE | N10: =IF(ISNUMBER(K10),OR(K10=22,K10=33),FALSE) -> FALSE | O10: =IF(ISNUMBER(K10),OR(K10=11,K10=12),FALSE) -> FALSE | P10: =IF(ISNUMBER(K10),OR(K10=23,K10=34),FALSE) -> FALSE | Q10: =IF(ISNUMBER(K10),OR(K10=13,K10=14,K10=24),FALSE) -> FALSE | R10: =IF(ISNUMBER(K10),K10=0,FALSE) -> FALSE | S10: =IF(ISNUMBER(T10),INDEX($L$5:$R$5,1,7-T10),"") | T10: =IF(ISNUMBER(K10),IF(L10,6,IF(M10,5,IF(N10,4,IF(O10,3,IF(P10,2,IF(Q10,1,0)))))),"") | U10: =IF(AND(ISNUMBER(T10),ISNUMBER(H10)),IF(AND(H10>=1,H10<=4,MOD(H10,1)=0),T10*10+H10,""),"")
B11: 3.5 | C11: Améliorer les conditions de travail des personnes qui travaillent dans le numérique. | J11: =S11 | K11: =IF(IF(ISNUMBER(E11),AND(E11>=0,E11<=3,MOD(E11,1)=0),FALSE),IF(E11=0,0,IF(IF(ISNUMBER(F11),AND(F11>=1,F11<=4,MOD(F11,1)=0),FALSE),E11*10+F11,"")),"") | L11: =IF(ISNUMBER(K11),K11=31,FALSE) -> FALSE | M11: =IF(ISNUMBER(K11),OR(K11=21,K11=32),FALSE) -> FALSE | N11: =IF(ISNUMBER(K11),OR(K11=22,K11=33),FALSE) -> FALSE | O11: =IF(ISNUMBER(K11),OR(K11=11,K11=12),FALSE) -> FALSE | P11: =IF(ISNUMBER(K11),OR(K11=23,K11=34),FALSE) -> FALSE | Q11: =IF(ISNUMBER(K11),OR(K11=13,K11=14,K11=24),FALSE) -> FALSE | R11: =IF(ISNUMBER(K11),K11=0,FALSE) -> FALSE | S11: =IF(ISNUMBER(T11),INDEX($L$5:$R$5,1,7-T11),"") | T11: =IF(ISNUMBER(K11),IF(L11,6,IF(M11,5,IF(N11,4,IF(O11,3,IF(P11,2,IF(Q11,1,0)))))),"") | U11: =IF(AND(ISNUMBER(T11),ISNUMBER(H11)),IF(AND(H11>=1,H11<=4,MOD(H11,1)=0),T11*10+H11,""),"")
B12: 3.6 | C12: Fixer et appliquer des règles éthiques pour utiliser les algorithmes, en particulier l’intelligence artificielle. Encadrer l’utilisation des données et assurer leur protection. | J12: =S12 | K12: =IF(IF(ISNUMBER(E12),AND(E12>=0,E12<=3,MOD(E12,1)=0),FALSE),IF(E12=0,0,IF(IF(ISNUMBER(F12),AND(F12>=1,F12<=4,MOD(F12,1)=0),FALSE),E12*10+F12,"")),"") | L12: =IF(ISNUMBER(K12),K12=31,FALSE) -> FALSE | M12: =IF(ISNUMBER(K12),OR(K12=21,K12=32),FALSE) -> FALSE | N12: =IF(ISNUMBER(K12),OR(K12=22,K12=33),FALSE) -> FALSE | O12: =IF(ISNUMBER(K12),OR(K12=11,K12=12),FALSE) -> FALSE | P12: =IF(ISNUMBER(K12),OR(K12=23,K12=34),FALSE) -> FALSE | Q12: =IF(ISNUMBER(K12),OR(K12=13,K12=14,K12=24),FALSE) -> FALSE | R12: =IF(ISNUMBER(K12),K12=0,FALSE) -> FALSE | S12: =IF(ISNUMBER(T12),INDEX($L$5:$R$5,1,7-T12),"") | T12: =IF(ISNUMBER(K12),IF(L12,6,IF(M12,5,IF(N12,4,IF(O12,3,IF(P12,2,IF(Q12,1,0)))))),"") | U12: =IF(AND(ISNUMBER(T12),ISNUMBER(H12)),IF(AND(H12>=1,H12<=4,MOD(H12,1)=0),T12*10+H12,""),"")
B13: 3.7 | C13: Mettre en place et faire connaître les actions de responsabilité sociétale (RSE), qui prennent en compte les effets de l’organisation sur la société et l’environnement. | J13: =S13 | K13: =IF(IF(ISNUMBER(E13),AND(E13>=0,E13<=3,MOD(E13,1)=0),FALSE),IF(E13=0,0,IF(IF(ISNUMBER(F13),AND(F13>=1,F13<=4,MOD(F13,1)=0),FALSE),E13*10+F13,"")),"") | L13: =IF(ISNUMBER(K13),K13=31,FALSE) -> FALSE | M13: =IF(ISNUMBER(K13),OR(K13=21,K13=32),FALSE) -> FALSE | N13: =IF(ISNUMBER(K13),OR(K13=22,K13=33),FALSE) -> FALSE | O13: =IF(ISNUMBER(K13),OR(K13=11,K13=12),FALSE) -> FALSE | P13: =IF(ISNUMBER(K13),OR(K13=23,K13=34),FALSE) -> FALSE | Q13: =IF(ISNUMBER(K13),OR(K13=13,K13=14,K13=24),FALSE) -> FALSE | R13: =IF(ISNUMBER(K13),K13=0,FALSE) -> FALSE | S13: =IF(ISNUMBER(T13),INDEX($L$5:$R$5,1,7-T13),"") | T13: =IF(ISNUMBER(K13),IF(L13,6,IF(M13,5,IF(N13,4,IF(O13,3,IF(P13,2,IF(Q13,1,0)))))),"") | U13: =IF(AND(ISNUMBER(T13),ISNUMBER(H13)),IF(AND(H13>=1,H13<=4,MOD(H13,1)=0),T13*10+H13,""),"")
B14: 3.8 | C14: Indiquer quand une intelligence artificielle répond et expliquer comment elle prend ses décisions. Garder un contrôle humain sur les sujets sensibles. | J14: =S14 -> 0 | K14: =IF(IF(ISNUMBER(E14),AND(E14>=0,E14<=3,MOD(E14,1)=0),FALSE),IF(E14=0,0,IF(IF(ISNUMBER(F14),AND(F14>=1,F14<=4,MOD(F14,1)=0),FALSE),E14*10+F14,"")),"") | L14: =IF(ISNUMBER(K14),K14=31,FALSE) -> FALSE | M14: =IF(ISNUMBER(K14),OR(K14=21,K14=32),FALSE) -> FALSE | N14: =IF(ISNUMBER(K14),OR(K14=22,K14=33),FALSE) -> FALSE | O14: =IF(ISNUMBER(K14),OR(K14=11,K14=12),FALSE) -> FALSE | P14: =IF(ISNUMBER(K14),OR(K14=23,K14=34),FALSE) -> FALSE | Q14: =IF(ISNUMBER(K14),OR(K14=13,K14=14,K14=24),FALSE) -> FALSE | R14: =IF(ISNUMBER(K14),K14=0,FALSE) -> FALSE | S14: =IF(ISNUMBER(T14),INDEX($L$5:$R$5,1,7-T14),"") | T14: =IF(ISNUMBER(K14),IF(L14,6,IF(M14,5,IF(N14,4,IF(O14,3,IF(P14,2,IF(Q14,1,0)))))),"") | U14: =IF(AND(ISNUMBER(T14),ISNUMBER(H14)),IF(AND(H14>=1,H14<=4,MOD(H14,1)=0),T14*10+H14,""),"")

Sheet ONR 4
L1: 0 | M1: 1 | N1: 2 | O1: 3 | P1: 4 | Q1: 5
B2: ONR 4 : Résilience et stratégie · Utiliser le numérique responsable pour aider l’organisation à faire face aux difficultés et à s’adapter
B4: Cibles à évaluer | D4: Importance de la cible | F4: Performance actuelle | H4: Compétences internes et externes | J4: Priorité | V4: Mise en œuvre
D5: Avantages possibles et risques | E5: Importance | F5: Niveau actuel | G5: Ce qui est déjà fait et ce qui justifie la note | H5: Compétences nécessaires | I5: Points forts et points faibles | J5: Niveau de priorité | K5: Clé de priorisation | L5: Intervention urgente | M5: Intervention prioritaire | N5: Intervention à moyen terme | O5: Intervention à long terme | P5: Intervention de consolidation | Q5: Intervention non prioritaire | R5: Intervention non pertinente | S5: Libellé de priorité | T5: Score de priorité | U5: Code priorité et compétences | V5: Actions proposées pour atteindre la cible
B6: Renseigner les cellules jaunes pour les notes, puis les textes utiles. La priorité se calcule automatiquement. Faire défiler vers la droite pour proposer des actions.
B7: 4.1 | C7: Suivre des normes communes pour recueillir, regrouper, analyser et partager les données sur les effets des technologies de l’information et de la communication (TIC). | J7: =S7 | K7: =IF(IF(ISNUMBER(E7),AND(E7>=0,E7<=3,MOD(E7,1)=0),FALSE),IF(E7=0,0,IF(IF(ISNUMBER(F7),AND(F7>=1,F7<=4,MOD(F7,1)=0),FALSE),E7*10+F7,"")),"") | L7: =IF(ISNUMBER(K7),K7=31,FALSE) -> FALSE | M7: =IF(ISNUMBER(K7),OR(K7=21,K7=32),FALSE) -> FALSE | N7: =IF(ISNUMBER(K7),OR(K7=22,K7=33),FALSE) -> FALSE | O7: =IF(ISNUMBER(K7),OR(K7=11,K7=12),FALSE) -> FALSE | P7: =IF(ISNUMBER(K7),OR(K7=23,K7=34),FALSE) -> FALSE | Q7: =IF(ISNUMBER(K7),OR(K7=13,K7=14,K7=24),FALSE) -> FALSE | R7: =IF(ISNUMBER(K7),K7=0,FALSE) -> FALSE | S7: =IF(ISNUMBER(T7),INDEX($L$5:$R$5,1,7-T7),"") | T7: =IF(ISNUMBER(K7),IF(L7,6,IF(M7,5,IF(N7,4,IF(O7,3,IF(P7,2,IF(Q7,1,0)))))),"") | U7: =IF(AND(ISNUMBER(T7),ISNUMBER(H7)),IF(AND(H7>=1,H7<=4,MOD(H7,1)=0),T7*10+H7,""),"")
B8: 4.2 | C8: Évaluer les services numériques au fil du temps et partager les résultats. | J8: =S8 | K8: =IF(IF(ISNUMBER(E8),AND(E8>=0,E8<=3,MOD(E8,1)=0),FALSE),IF(E8=0,0,IF(IF(ISNUMBER(F8),AND(F8>=1,F8<=4,MOD(F8,1)=0),FALSE),E8*10+F8,"")),"") | L8: =IF(ISNUMBER(K8),K8=31,FALSE) -> FALSE | M8: =IF(ISNUMBER(K8),OR(K8=21,K8=32),FALSE) -> FALSE | N8: =IF(ISNUMBER(K8),OR(K8=22,K8=33),FALSE) -> FALSE | O8: =IF(ISNUMBER(K8),OR(K8=11,K8=12),FALSE) -> FALSE | P8: =IF(ISNUMBER(K8),OR(K8=23,K8=34),FALSE) -> FALSE | Q8: =IF(ISNUMBER(K8),OR(K8=13,K8=14,K8=24),FALSE) -> FALSE | R8: =IF(ISNUMBER(K8),K8=0,FALSE) -> FALSE | S8: =IF(ISNUMBER(T8),INDEX($L$5:$R$5,1,7-T8),"") | T8: =IF(ISNUMBER(K8),IF(L8,6,IF(M8,5,IF(N8,4,IF(O8,3,IF(P8,2,IF(Q8,1,0)))))),"") | U8: =IF(AND(ISNUMBER(T8),ISNUMBER(H8)),IF(AND(H8>=1,H8<=4,MOD(H8,1)=0),T8*10+H8,""),"")
B9: 4.3 | C9: Innover en utilisant de nouveaux outils numériques. Évaluer leurs effets et expliquer les résultats aux personnes qui les utilisent. | J9: =S9 | K9: =IF(IF(ISNUMBER(E9),AND(E9>=0,E9<=3,MOD(E9,1)=0),FALSE),IF(E9=0,0,IF(IF(ISNUMBER(F9),AND(F9>=1,F9<=4,MOD(F9,1)=0),FALSE),E9*10+F9,"")),"") | L9: =IF(ISNUMBER(K9),K9=31,FALSE) -> FALSE | M9: =IF(ISNUMBER(K9),OR(K9=21,K9=32),FALSE) -> FALSE | N9: =IF(ISNUMBER(K9),OR(K9=22,K9=33),FALSE) -> FALSE | O9: =IF(ISNUMBER(K9),OR(K9=11,K9=12),FALSE) -> FALSE | P9: =IF(ISNUMBER(K9),OR(K9=23,K9=34),FALSE) -> FALSE | Q9: =IF(ISNUMBER(K9),OR(K9=13,K9=14,K9=24),FALSE) -> FALSE | R9: =IF(ISNUMBER(K9),K9=0,FALSE) -> FALSE | S9: =IF(ISNUMBER(T9),INDEX($L$5:$R$5,1,7-T9),"") | T9: =IF(ISNUMBER(K9),IF(L9,6,IF(M9,5,IF(N9,4,IF(O9,3,IF(P9,2,IF(Q9,1,0)))))),"") | U9: =IF(AND(ISNUMBER(T9),ISNUMBER(H9)),IF(AND(H9>=1,H9<=4,MOD(H9,1)=0),T9*10+H9,""),"")
B10: 4.4 | C10: Renforcer la souveraineté numérique : garder la maîtrise de nos choix, de nos outils et de nos données. | J10: =S10 -> 0 | K10: =IF(IF(ISNUMBER(E10),AND(E10>=0,E10<=3,MOD(E10,1)=0),FALSE),IF(E10=0,0,IF(IF(ISNUMBER(F10),AND(F10>=1,F10<=4,MOD(F10,1)=0),FALSE),E10*10+F10,"")),"") | L10: =IF(ISNUMBER(K10),K10=31,FALSE) -> FALSE | M10: =IF(ISNUMBER(K10),OR(K10=21,K10=32),FALSE) -> FALSE | N10: =IF(ISNUMBER(K10),OR(K10=22,K10=33),FALSE) -> FALSE | O10: =IF(ISNUMBER(K10),OR(K10=11,K10=12),FALSE) -> FALSE | P10: =IF(ISNUMBER(K10),OR(K10=23,K10=34),FALSE) -> FALSE | Q10: =IF(ISNUMBER(K10),OR(K10=13,K10=14,K10=24),FALSE) -> FALSE | R10: =IF(ISNUMBER(K10),K10=0,FALSE) -> FALSE | S10: =IF(ISNUMBER(T10),INDEX($L$5:$R$5,1,7-T10),"") | T10: =IF(ISNUMBER(K10),IF(L10,6,IF(M10,5,IF(N10,4,IF(O10,3,IF(P10,2,IF(Q10,1,0)))))),"") | U10: =IF(AND(ISNUMBER(T10),ISNUMBER(H10)),IF(AND(H10>=1,H10<=4,MOD(H10,1)=0),T10*10+H10,""),"")

Sheet ONR 5
L1: 0 | M1: 1 | N1: 2 | O1: 3 | P1: 4 | Q1: 5
B2: ONR 5 : Management · Donner du sens au travail et préserver les personnes et les ressources nécessaires à nos activités
B4: Cibles à évaluer | D4: Importance de la cible | F4: Performance actuelle | H4: Compétences internes et externes | J4: Priorité | V4: Mise en œuvre
D5: Avantages possibles et risques | E5: Importance | F5: Niveau actuel | G5: Ce qui est déjà fait et ce qui justifie la note | H5: Compétences nécessaires | I5: Points forts et points faibles | J5: Niveau de priorité | K5: Clé de priorisation | L5: Intervention urgente | M5: Intervention prioritaire | N5: Intervention à moyen terme | O5: Intervention à long terme | P5: Intervention de consolidation | Q5: Intervention non prioritaire | R5: Intervention non pertinente | S5: Libellé de priorité | T5: Score de priorité | U5: Code priorité et compétences | V5: Actions proposées pour atteindre la cible
B6: Renseigner les cellules jaunes pour les notes, puis les textes utiles. La priorité se calcule automatiquement. Faire défiler vers la droite pour proposer des actions.
B7: 5.1 | C7: Concevoir les systèmes et les services numériques en intégrant de nouvelles façons de répondre aux besoins sociaux. | J7: =S7 | K7: =IF(IF(ISNUMBER(E7),AND(E7>=0,E7<=3,MOD(E7,1)=0),FALSE),IF(E7=0,0,IF(IF(ISNUMBER(F7),AND(F7>=1,F7<=4,MOD(F7,1)=0),FALSE),E7*10+F7,"")),"") | L7: =IF(ISNUMBER(K7),K7=31,FALSE) -> FALSE | M7: =IF(ISNUMBER(K7),OR(K7=21,K7=32),FALSE) -> FALSE | N7: =IF(ISNUMBER(K7),OR(K7=22,K7=33),FALSE) -> FALSE | O7: =IF(ISNUMBER(K7),OR(K7=11,K7=12),FALSE) -> FALSE | P7: =IF(ISNUMBER(K7),OR(K7=23,K7=34),FALSE) -> FALSE | Q7: =IF(ISNUMBER(K7),OR(K7=13,K7=14,K7=24),FALSE) -> FALSE | R7: =IF(ISNUMBER(K7),K7=0,FALSE) -> FALSE | S7: =IF(ISNUMBER(T7),INDEX($L$5:$R$5,1,7-T7),"") | T7: =IF(ISNUMBER(K7),IF(L7,6,IF(M7,5,IF(N7,4,IF(O7,3,IF(P7,2,IF(Q7,1,0)))))),"") | U7: =IF(AND(ISNUMBER(T7),ISNUMBER(H7)),IF(AND(H7>=1,H7<=4,MOD(H7,1)=0),T7*10+H7,""),"")
B8: 5.2 | C8: Faire connaître et soutenir les initiatives des équipes qui encouragent l’engagement, la coopération entre services et le bien-être au travail. | J8: =S8 | K8: =IF(IF(ISNUMBER(E8),AND(E8>=0,E8<=3,MOD(E8,1)=0),FALSE),IF(E8=0,0,IF(IF(ISNUMBER(F8),AND(F8>=1,F8<=4,MOD(F8,1)=0),FALSE),E8*10+F8,"")),"") | L8: =IF(ISNUMBER(K8),K8=31,FALSE) -> FALSE | M8: =IF(ISNUMBER(K8),OR(K8=21,K8=32),FALSE) -> FALSE | N8: =IF(ISNUMBER(K8),OR(K8=22,K8=33),FALSE) -> FALSE | O8: =IF(ISNUMBER(K8),OR(K8=11,K8=12),FALSE) -> FALSE | P8: =IF(ISNUMBER(K8),OR(K8=23,K8=34),FALSE) -> FALSE | Q8: =IF(ISNUMBER(K8),OR(K8=13,K8=14,K8=24),FALSE) -> FALSE | R8: =IF(ISNUMBER(K8),K8=0,FALSE) -> FALSE | S8: =IF(ISNUMBER(T8),INDEX($L$5:$R$5,1,7-T8),"") | T8: =IF(ISNUMBER(K8),IF(L8,6,IF(M8,5,IF(N8,4,IF(O8,3,IF(P8,2,IF(Q8,1,0)))))),"") | U8: =IF(AND(ISNUMBER(T8),ISNUMBER(H8)),IF(AND(H8>=1,H8<=4,MOD(H8,1)=0),T8*10+H8,""),"")
B9: 5.3 | C9: Faire participer les personnes et les organisations concernées. S’appuyer sur leurs connaissances des questions d’environnement, de conditions de vie et de société. | J9: =S9 | K9: =IF(IF(ISNUMBER(E9),AND(E9>=0,E9<=3,MOD(E9,1)=0),FALSE),IF(E9=0,0,IF(IF(ISNUMBER(F9),AND(F9>=1,F9<=4,MOD(F9,1)=0),FALSE),E9*10+F9,"")),"") | L9: =IF(ISNUMBER(K9),K9=31,FALSE) -> FALSE | M9: =IF(ISNUMBER(K9),OR(K9=21,K9=32),FALSE) -> FALSE | N9: =IF(ISNUMBER(K9),OR(K9=22,K9=33),FALSE) -> FALSE | O9: =IF(ISNUMBER(K9),OR(K9=11,K9=12),FALSE) -> FALSE | P9: =IF(ISNUMBER(K9),OR(K9=23,K9=34),FALSE) -> FALSE | Q9: =IF(ISNUMBER(K9),OR(K9=13,K9=14,K9=24),FALSE) -> FALSE | R9: =IF(ISNUMBER(K9),K9=0,FALSE) -> FALSE | S9: =IF(ISNUMBER(T9),INDEX($L$5:$R$5,1,7-T9),"") | T9: =IF(ISNUMBER(K9),IF(L9,6,IF(M9,5,IF(N9,4,IF(O9,3,IF(P9,2,IF(Q9,1,0)))))),"") | U9: =IF(AND(ISNUMBER(T9),ISNUMBER(H9)),IF(AND(H9>=1,H9<=4,MOD(H9,1)=0),T9*10+H9,""),"")
B10: 5.4 | C10: Permettre aux générations futures d’innover pour mieux vivre ensemble, s’ouvrir aux autres et préserver l’équilibre de la nature. | J10: =S10 | K10: =IF(IF(ISNUMBER(E10),AND(E10>=0,E10<=3,MOD(E10,1)=0),FALSE),IF(E10=0,0,IF(IF(ISNUMBER(F10),AND(F10>=1,F10<=4,MOD(F10,1)=0),FALSE),E10*10+F10,"")),"") | L10: =IF(ISNUMBER(K10),K10=31,FALSE) -> FALSE | M10: =IF(ISNUMBER(K10),OR(K10=21,K10=32),FALSE) -> FALSE | N10: =IF(ISNUMBER(K10),OR(K10=22,K10=33),FALSE) -> FALSE | O10: =IF(ISNUMBER(K10),OR(K10=11,K10=12),FALSE) -> FALSE | P10: =IF(ISNUMBER(K10),OR(K10=23,K10=34),FALSE) -> FALSE | Q10: =IF(ISNUMBER(K10),OR(K10=13,K10=14,K10=24),FALSE) -> FALSE | R10: =IF(ISNUMBER(K10),K10=0,FALSE) -> FALSE | S10: =IF(ISNUMBER(T10),INDEX($L$5:$R$5,1,7-T10),"") | T10: =IF(ISNUMBER(K10),IF(L10,6,IF(M10,5,IF(N10,4,IF(O10,3,IF(P10,2,IF(Q10,1,0)))))),"") | U10: =IF(AND(ISNUMBER(T10),ISNUMBER(H10)),IF(AND(H10>=1,H10<=4,MOD(H10,1)=0),T10*10+H10,""),"")
B11: 5.5 | C11: Suivre les résultats obtenus et le respect des règles à l’aide d’indicateurs. | J11: =S11 | K11: =IF(IF(ISNUMBER(E11),AND(E11>=0,E11<=3,MOD(E11,1)=0),FALSE),IF(E11=0,0,IF(IF(ISNUMBER(F11),AND(F11>=1,F11<=4,MOD(F11,1)=0),FALSE),E11*10+F11,"")),"") | L11: =IF(ISNUMBER(K11),K11=31,FALSE) -> FALSE | M11: =IF(ISNUMBER(K11),OR(K11=21,K11=32),FALSE) -> FALSE | N11: =IF(ISNUMBER(K11),OR(K11=22,K11=33),FALSE) -> FALSE | O11: =IF(ISNUMBER(K11),OR(K11=11,K11=12),FALSE) -> FALSE | P11: =IF(ISNUMBER(K11),OR(K11=23,K11=34),FALSE) -> FALSE | Q11: =IF(ISNUMBER(K11),OR(K11=13,K11=14,K11=24),FALSE) -> FALSE | R11: =IF(ISNUMBER(K11),K11=0,FALSE) -> FALSE | S11: =IF(ISNUMBER(T11),INDEX($L$5:$R$5,1,7-T11),"") | T11: =IF(ISNUMBER(K11),IF(L11,6,IF(M11,5,IF(N11,4,IF(O11,3,IF(P11,2,IF(Q11,1,0)))))),"") | U11: =IF(AND(ISNUMBER(T11),ISNUMBER(H11)),IF(AND(H11>=1,H11<=4,MOD(H11,1)=0),T11*10+H11,""),"")
B12: 5.6 | C12: Proposer des améliorations et de nouvelles idées pour un numérique responsable, y compris des solutions sans outils numériques. | J12: =S12 | K12: =IF(IF(ISNUMBER(E12),AND(E12>=0,E12<=3,MOD(E12,1)=0),FALSE),IF(E12=0,0,IF(IF(ISNUMBER(F12),AND(F12>=1,F12<=4,MOD(F12,1)=0),FALSE),E12*10+F12,"")),"") | L12: =IF(ISNUMBER(K12),K12=31,FALSE) -> FALSE | M12: =IF(ISNUMBER(K12),OR(K12=21,K12=32),FALSE) -> FALSE | N12: =IF(ISNUMBER(K12),OR(K12=22,K12=33),FALSE) -> FALSE | O12: =IF(ISNUMBER(K12),OR(K12=11,K12=12),FALSE) -> FALSE | P12: =IF(ISNUMBER(K12),OR(K12=23,K12=34),FALSE) -> FALSE | Q12: =IF(ISNUMBER(K12),OR(K12=13,K12=14,K12=24),FALSE) -> FALSE | R12: =IF(ISNUMBER(K12),K12=0,FALSE) -> FALSE | S12: =IF(ISNUMBER(T12),INDEX($L$5:$R$5,1,7-T12),"") | T12: =IF(ISNUMBER(K12),IF(L12,6,IF(M12,5,IF(N12,4,IF(O12,3,IF(P12,2,IF(Q12,1,0)))))),"") | U12: =IF(AND(ISNUMBER(T12),ISNUMBER(H12)),IF(AND(H12>=1,H12<=4,MOD(H12,1)=0),T12*10+H12,""),"")
B13: 5.7 | C13: Décider avec les équipes comment utiliser l’intelligence artificielle. Les former à ses limites et préserver le sens de leur travail. | J13: =S13 -> 0 | K13: =IF(IF(ISNUMBER(E13),AND(E13>=0,E13<=3,MOD(E13,1)=0),FALSE),IF(E13=0,0,IF(IF(ISNUMBER(F13),AND(F13>=1,F13<=4,MOD(F13,1)=0),FALSE),E13*10+F13,"")),"") | L13: =IF(ISNUMBER(K13),K13=31,FALSE) -> FALSE | M13: =IF(ISNUMBER(K13),OR(K13=21,K13=32),FALSE) -> FALSE | N13: =IF(ISNUMBER(K13),OR(K13=22,K13=33),FALSE) -> FALSE | O13: =IF(ISNUMBER(K13),OR(K13=11,K13=12),FALSE) -> FALSE | P13: =IF(ISNUMBER(K13),OR(K13=23,K13=34),FALSE) -> FALSE | Q13: =IF(ISNUMBER(K13),OR(K13=13,K13=14,K13=24),FALSE) -> FALSE | R13: =IF(ISNUMBER(K13),K13=0,FALSE) -> FALSE | S13: =IF(ISNUMBER(T13),INDEX($L$5:$R$5,1,7-T13),"") | T13: =IF(ISNUMBER(K13),IF(L13,6,IF(M13,5,IF(N13,4,IF(O13,3,IF(P13,2,IF(Q13,1,0)))))),"") | U13: =IF(AND(ISNUMBER(T13),ISNUMBER(H13)),IF(AND(H13>=1,H13<=4,MOD(H13,1)=0),T13*10+H13,""),"")

Sheet Priorisation
B2: Tableau de priorisation des cibles
A4: Importance de la cible | B4: 3 | H4: Intervention urgente | I4: Intervention de consolidation
B5: 2 | H5: Intervention prioritaire | I5: Intervention non prioritaire
B6: 1 | H6: Intervention à moyen terme | I6: Intervention non pertinente
B7: 0 | H7: Intervention à long terme
C8: 1 | D8: 2 | E8: 3 | F8: 4
C9: État de la situation actuelle

Sheet Résultats détaillés
L1: 0 | M1: 1 | N1: 2 | O1: 3 | P1: 4 | Q1: 5
B2: Résultats détaillés | V2: Mise en œuvre des actions | Y2: Analyse des Forces, Faiblesses, Opportunités et Menaces (FFOM)
D3: Enjeux locaux associés à la cible | E3: ='ONR 1'!E5 -> Importance | F3: ='ONR 1'!F5 -> Niveau actuel | G3: ='ONR 1'!G5 -> Ce qui est déjà fait et ce qui justifie la note | H3: ='ONR 1'!H5 -> Compétences nécessaires | I3: ='ONR 1'!I5 -> Points forts et points faibles | J3: ='ONR 1'!J5 -> Niveau de priorité | K3: Valeur priorité | L3: Intervention urgente | M3: Intervention prioritaire | N3: Intervention à moyen terme | O3: Intervention à long terme | P3: Intervention de consolidation | Q3: Intervention non prioritaire | R3: Intervention non pertinente | S3: Priorité texte | T3: Priorité valeur | U3: Valeur type d'action | V3: Mesures et actions déjà en place | W3: Stratégies d'action pouvant contribuer à l'atteinte de la cible et proposées lors de l'analyse | X3: Synergies avec les Modules (M3 stratégie, M4 sensibiliser, M5 action) | Y3: Forces et faiblesses en regard de la cible | Z3: Opportunités et menaces en regard de la cible | AB3: ONR | AC3: Nombre de cibles | AD3: Nombre de cibles analysées | AE3: Cibles à évaluer | AF3: Nombre de cibles urgentes | AG3: Nombre de cibles prioritaires | AH3: Nombre de cibles à moyen terme | AI3: Nombre de cibles à long terme | AJ3: Nombre de cibles à consolider | AK3: Nombre de cibles non prioritaires | AL3: Cibles non applicables | AM3: Piste d’action renseignée
B4: ='ONR 1'!B2 -> ONR 1 : Sobriété · Utiliser les outils numériques pour consommer moins de ressources et réduire leurs effets sur l’environnement | AB4: =B4 -> ONR 1 : Sobriété · Utiliser les outils numériques pour consommer moins de ressources et réduire leurs effets sur l’environnement | AC4: =COUNTA('ONR 1'!B7:B14) -> 8 | AD4: =COUNT(T5:T12) -> 5 | AE4: =SUM(AE5:AE12) -> 3 | AF4: =SUM(AF5:AF12) -> 3 | AG4: =SUM(AG5:AG12) -> 1 | AH4: =SUM(AH5:AH12) -> 1 | AI4: =SUM(AI5:AI12) -> 0 | AJ4: =SUM(AJ5:AJ12) -> 0 | AK4: =SUM(AK5:AK12) -> 0 | AL4: =SUM(AL5:AL12) -> 0
B5: =IF(ISBLANK('ONR 1'!B7),"",'ONR 1'!B7) -> 1.1 | C5: =IF(ISBLANK('ONR 1'!C7),"",'ONR 1'!C7) -> Prendre en compte toutes les étapes de la vie des équipements et des logiciels, de leur création à leur fin de vie, pour contribuer à la transition énergétique. | D5: =IF(ISBLANK('ONR 1'!D7),"",'ONR 1'!D7) -> Avantages possibles : réduire les émissions de gaz à effet de serre de l’organisation et se préparer aux futures règles environnementales. Risque : payer plus cher à l’achat certains équipements conçus pour limiter leurs effets sur l’environnement. | E5: =IF(ISBLANK('ONR 1'!E7),"",'ONR 1'!E7) -> 3 | F5: =IF(ISBLANK('ONR 1'!F7),"",'ONR 1'!F7) -> 1 | G5: =IF(ISBLANK('ONR 1'!G7),"",'ONR 1'!G7) -> L’équipe Achats retient le prix d’achat comme seul critère de choix. Elle ne demande pas d’analyse du cycle de vie (ACV) aux fournisseurs dans les appels d’offres. | H5: =IF(ISBLANK('ONR 1'!H7),"",'ONR 1'!H7) -> 3 | I5: =IF(ISBLANK('ONR 1'!I7),"",'ONR 1'!I7) -> Point fort : la direction des achats souhaite adopter des pratiques plus durables. Point faible : l’équipe connaît peu les labels environnementaux des équipements informatiques. | ... U5: =IF(ISBLANK('ONR 1'!U7),"",'ONR 1'!U7) -> 63 | V5: =IF(ISBLANK('ONR 1'!G7),"",'ONR 1'!G7) -> L’équipe Achats retient le prix d’achat comme seul critère de choix. Elle ne demande pas d’analyse du cycle de vie (ACV) aux fournisseurs dans les appels d’offres. | W5: =IF(ISBLANK('ONR 1'!V7),"",'ONR 1'!V7) -> Former l’équipe Achats aux critères du numérique responsable et aux labels TCO et EPEAT. Dans les prochains appels d’offres pour remplacer les serveurs, faire compter les critères environnementaux pour 15 % de la note. | X5: =IF(ISBLANK('ONR 1'!W7),"",'ONR 1'!W7) | Y5: =IF(ISBLANK('ONR 1'!I7),"",'ONR 1'!I7) -> Point fort : la direction des achats souhaite adopter des pratiques plus durables. Point faible : l’équipe connaît peu les labels environnementaux des équipements informatiques. | Z5: =IF(ISBLANK('ONR 1'!D7),"",'ONR 1'!D7) -> Avantages possibles : réduire les émissions de gaz à effet de serre de l’organisation et se préparer aux futures règles environnementales. Risque : payer plus cher à l’achat certains équipements conçus pour limiter leurs effets sur l’environnement. | AE5: =IF(ISNUMBER(T5),0,1) -> 0 | AF5: =IF(L5=TRUE,1,0) -> 1 | AG5: =IF(M5=TRUE,1,0) -> 0 | AH5: =IF(N5=TRUE,1,0) -> 0 | AI5: =IF(O5=TRUE,1,0) -> 0 | AJ5: =IF(P5=TRUE,1,0) -> 0 | AK5: =IF(Q5=TRUE,1,0) -> 0 | AL5: =IF(R5=TRUE,1,0) -> 0 | AM5: =IF(LEN(TRIM(W5))>0,1,0) -> 1
B6: =IF(ISBLANK('ONR 1'!B8),"",'ONR 1'!B8) -> 1.2 | C6: =IF(ISBLANK('ONR 1'!C8),"",'ONR 1'!C8) -> Utiliser les équipements plus longtemps, même après la fin de leur amortissement, c’est-à-dire la période sur laquelle leur coût est réparti dans les comptes. | D6: =IF(ISBLANK('ONR 1'!D8),"",'ONR 1'!D8) -> Avantages possibles : réduire les dépenses d’achat de matériel et les déchets d’équipements électriques et électroniques (DEEE). | E6: =IF(ISBLANK('ONR 1'!E8),"",'ONR 1'!E8) -> 3 | F6: =IF(ISBLANK('ONR 1'!F8),"",'ONR 1'!F8) -> 3 | G6: =IF(ISBLANK('ONR 1'!G8),"",'ONR 1'!G8) -> L’organisation a porté la durée de renouvellement des ordinateurs portables de trois à quatre ans l’année dernière. Elle dispose d’un contrat de maintenance. | H6: =IF(ISBLANK('ONR 1'!H8),"",'ONR 1'!H8) -> 2 | I6: =IF(ISBLANK('ONR 1'!I8),"",'ONR 1'!I8) -> Point fort : l’équipe technique peut réparer les équipements en interne. Point faible : certains utilisateurs demandent du matériel neuf pour son apparence. | ... U6: =IF(ISBLANK('ONR 1'!U8),"",'ONR 1'!U8) -> 42 | V6: =IF(ISBLANK('ONR 1'!G8),"",'ONR 1'!G8) -> L’organisation a porté la durée de renouvellement des ordinateurs portables de trois à quatre ans l’année dernière. Elle dispose d’un contrat de maintenance. | W6: =IF(ISBLANK('ONR 1'!V8),"",'ONR 1'!V8) -> Répartir le coût des équipements dans les comptes sur cinq ans au minimum : c’est la durée d’amortissement. Prévoir un stock de pièces détachées pour faciliter les réparations. Expliquer aux équipes comment garder leur ordinateur plus longtemps permet d’éviter des émissions de gaz à effet de serre. | X6: =IF(ISBLANK('ONR 1'!W8),"",'ONR 1'!W8) | Y6: =IF(ISBLANK('ONR 1'!I8),"",'ONR 1'!I8) -> Point fort : l’équipe technique peut réparer les équipements en interne. Point faible : certains utilisateurs demandent du matériel neuf pour son apparence. | Z6: =IF(ISBLANK('ONR 1'!D8),"",'ONR 1'!D8) -> Avantages possibles : réduire les dépenses d’achat de matériel et les déchets d’équipements électriques et électroniques (DEEE). | AE6: =IF(ISNUMBER(T6),0,1) -> 0 | AF6: =IF(L6=TRUE,1,0) -> 0 | AG6: =IF(M6=TRUE,1,0) -> 0 | AH6: =IF(N6=TRUE,1,0) -> 1 | AI6: =IF(O6=TRUE,1,0) -> 0 | AJ6: =IF(P6=TRUE,1,0) -> 0 | AK6: =IF(Q6=TRUE,1,0) -> 0 | AL6: =IF(R6=TRUE,1,0) -> 0 | AM6: =IF(LEN(TRIM(W6))>0,1,0) -> 1
B7: =IF(ISBLANK('ONR 1'!B9),"",'ONR 1'!B9) -> 1.3 | C7: =IF(ISBLANK('ONR 1'!C9),"",'ONR 1'!C9) -> Concevoir des services numériques qui limitent leurs effets sur l’environnement. Choisir des technologies qui contribuent aux Objectifs de développement durable (ODD). | D7: =IF(ISBLANK('ONR 1'!D9),"",'ONR 1'!D9) -> Avantages possibles : réduire les effets des services sur l’environnement dès leur conception, faciliter leur utilisation et contribuer aux Objectifs de développement durable (ODD). Risques : accumuler des problèmes techniques non résolus ou créer des logiciels trop gourmands en ressources, qui obligent à remplacer le matériel plus tôt. | E7: =IF(ISBLANK('ONR 1'!E9),"",'ONR 1'!E9) -> 3 | F7: =IF(ISBLANK('ONR 1'!F9),"",'ONR 1'!F9) -> 2 | G7: =IF(ISBLANK('ONR 1'!G9),"",'ONR 1'!G9) -> Les équipes valident les nouveaux services et sites web selon des critères fonctionnels, graphiques et financiers. Elles ne mesurent ni le poids des pages ni l’impact environnemental du code. | H7: =IF(ISBLANK('ONR 1'!H9),"",'ONR 1'!H9) -> 2 | I7: =IF(ISBLANK('ONR 1'!I9),"",'ONR 1'!I9) -> Point fort : les développeurs et les chefs de produit s’intéressent aux effets de leurs activités sur la société et l’environnement. Points faibles : ils connaissent peu les guides pour concevoir des services numériques moins polluants, comme le RGESN. Ils savent peu comment relier leurs projets aux ODD. | ... U7: =IF(ISBLANK('ONR 1'!U9),"",'ONR 1'!U9) -> 52 | V7: =IF(ISBLANK('ONR 1'!G9),"",'ONR 1'!G9) -> Les équipes valident les nouveaux services et sites web selon des critères fonctionnels, graphiques et financiers. Elles ne mesurent ni le poids des pages ni l’impact environnemental du code. | W7: =IF(ISBLANK('ONR 1'!V9),"",'ONR 1'!V9) -> 1. Former les équipes de conception, de développement et de gestion de projet à créer des services numériques qui limitent leurs effets sur l’environnement. 2. Ajouter des exigences environnementales aux cahiers des charges, comme limiter le poids des images et réduire les demandes envoyées aux serveurs. 3. Pour chaque nouveau projet, préciser à quels Objectifs de développement durable il contribue. | X7: =IF(ISBLANK('ONR 1'!W9),"",'ONR 1'!W9) | Y7: =IF(ISBLANK('ONR 1'!I9),"",'ONR 1'!I9) -> Point fort : les développeurs et les chefs de produit s’intéressent aux effets de leurs activités sur la société et l’environnement. Points faibles : ils connaissent peu les guides pour concevoir des services numériques moins polluants, comme le RGESN. Ils savent peu comment relier leurs projets aux ODD. | Z7: =IF(ISBLANK('ONR 1'!D9),"",'ONR 1'!D9) -> Avantages possibles : réduire les effets des services sur l’environnement dès leur conception, faciliter leur utilisation et contribuer aux Objectifs de développement durable (ODD). Risques : accumuler des problèmes techniques non résolus ou créer des logiciels trop gourmands en ressources, qui obligent à remplacer le matériel plus tôt. | AE7: =IF(ISNUMBER(T7),0,1) -> 0 | AF7: =IF(L7=TRUE,1,0) -> 0 | AG7: =IF(M7=TRUE,1,0) -> 1 | AH7: =IF(N7=TRUE,1,0) -> 0 | AI7: =IF(O7=TRUE,1,0) -> 0 | AJ7: =IF(P7=TRUE,1,0) -> 0 | AK7: =IF(Q7=TRUE,1,0) -> 0 | AL7: =IF(R7=TRUE,1,0) -> 0 | AM7: =IF(LEN(TRIM(W7))>0,1,0) -> 1
B8: =IF(ISBLANK('ONR 1'!B10),"",'ONR 1'!B10) -> 1.4 | C8: =IF(ISBLANK('ONR 1'!C10),"",'ONR 1'!C10) -> Adopter des pratiques qui consomment moins de matériel, de ressources, d’énergie et de consommables, comme le papier ou l’encre. | D8: =IF(ISBLANK('ONR 1'!D10),"",'ONR 1'!D10) | E8: =IF(ISBLANK('ONR 1'!E10),"",'ONR 1'!E10) | F8: =IF(ISBLANK('ONR 1'!F10),"",'ONR 1'!F10) | G8: =IF(ISBLANK('ONR 1'!G10),"",'ONR 1'!G10) | H8: =IF(ISBLANK('ONR 1'!H10),"",'ONR 1'!H10) | I8: =IF(ISBLANK('ONR 1'!I10),"",'ONR 1'!I10) | ... U8: =IF(ISBLANK('ONR 1'!U10),"",'ONR 1'!U10) | V8: =IF(ISBLANK('ONR 1'!G10),"",'ONR 1'!G10) | W8: =IF(ISBLANK('ONR 1'!V10),"",'ONR 1'!V10) | X8: =IF(ISBLANK('ONR 1'!W10),"",'ONR 1'!W10) | Y8: =IF(ISBLANK('ONR 1'!I10),"",'ONR 1'!I10) | Z8: =IF(ISBLANK('ONR 1'!D10),"",'ONR 1'!D10) | AE8: =IF(ISNUMBER(T8),0,1) -> 1 | AF8: =IF(L8=TRUE,1,0) -> 0 | AG8: =IF(M8=TRUE,1,0) -> 0 | AH8: =IF(N8=TRUE,1,0) -> 0 | AI8: =IF(O8=TRUE,1,0) -> 0 | AJ8: =IF(P8=TRUE,1,0) -> 0 | AK8: =IF(Q8=TRUE,1,0) -> 0 | AL8: =IF(R8=TRUE,1,0) -> 0 | AM8: =IF(LEN(TRIM(W8))>0,1,0) -> 0
B9: =IF(ISBLANK('ONR 1'!B11),"",'ONR 1'!B11) -> 1.5 | C9: =IF(ISBLANK('ONR 1'!C11),"",'ONR 1'!C11) -> Réutiliser ou recycler les déchets pour en faire de nouvelles ressources. Soutenir les emplois liés à leur traitement et à l’économie circulaire. | D9: =IF(ISBLANK('ONR 1'!D11),"",'ONR 1'!D11) | E9: =IF(ISBLANK('ONR 1'!E11),"",'ONR 1'!E11) | F9: =IF(ISBLANK('ONR 1'!F11),"",'ONR 1'!F11) | G9: =IF(ISBLANK('ONR 1'!G11),"",'ONR 1'!G11) | H9: =IF(ISBLANK('ONR 1'!H11),"",'ONR 1'!H11) | I9: =IF(ISBLANK('ONR 1'!I11),"",'ONR 1'!I11) | ... U9: =IF(ISBLANK('ONR 1'!U11),"",'ONR 1'!U11) | V9: =IF(ISBLANK('ONR 1'!G11),"",'ONR 1'!G11) | W9: =IF(ISBLANK('ONR 1'!V11),"",'ONR 1'!V11) | X9: =IF(ISBLANK('ONR 1'!W11),"",'ONR 1'!W11) | Y9: =IF(ISBLANK('ONR 1'!I11),"",'ONR 1'!I11) | Z9: =IF(ISBLANK('ONR 1'!D11),"",'ONR 1'!D11) | AE9: =IF(ISNUMBER(T9),0,1) -> 1 | AF9: =IF(L9=TRUE,1,0) -> 0 | AG9: =IF(M9=TRUE,1,0) -> 0 | AH9: =IF(N9=TRUE,1,0) -> 0 | AI9: =IF(O9=TRUE,1,0) -> 0 | AJ9: =IF(P9=TRUE,1,0) -> 0 | AK9: =IF(Q9=TRUE,1,0) -> 0 | AL9: =IF(R9=TRUE,1,0) -> 0 | AM9: =IF(LEN(TRIM(W9))>0,1,0) -> 0
B10: =IF(ISBLANK('ONR 1'!B12),"",'ONR 1'!B12) -> 1.6 | C10: =IF(ISBLANK('ONR 1'!C12),"",'ONR 1'!C12) -> Choisir des énergies renouvelables et encourager leur utilisation. | D10: =IF(ISBLANK('ONR 1'!D12),"",'ONR 1'!D12) | E10: =IF(ISBLANK('ONR 1'!E12),"",'ONR 1'!E12) | F10: =IF(ISBLANK('ONR 1'!F12),"",'ONR 1'!F12) | G10: =IF(ISBLANK('ONR 1'!G12),"",'ONR 1'!G12) | H10: =IF(ISBLANK('ONR 1'!H12),"",'ONR 1'!H12) | I10: =IF(ISBLANK('ONR 1'!I12),"",'ONR 1'!I12) | ... U10: =IF(ISBLANK('ONR 1'!U12),"",'ONR 1'!U12) | V10: =IF(ISBLANK('ONR 1'!G12),"",'ONR 1'!G12) | W10: =IF(ISBLANK('ONR 1'!V12),"",'ONR 1'!V12) | X10: =IF(ISBLANK('ONR 1'!W12),"",'ONR 1'!W12) | Y10: =IF(ISBLANK('ONR 1'!I12),"",'ONR 1'!I12) | Z10: =IF(ISBLANK('ONR 1'!D12),"",'ONR 1'!D12) | AE10: =IF(ISNUMBER(T10),0,1) -> 1 | AF10: =IF(L10=TRUE,1,0) -> 0 | AG10: =IF(M10=TRUE,1,0) -> 0 | AH10: =IF(N10=TRUE,1,0) -> 0 | AI10: =IF(O10=TRUE,1,0) -> 0 | AJ10: =IF(P10=TRUE,1,0) -> 0 | AK10: =IF(Q10=TRUE,1,0) -> 0 | AL10: =IF(R10=TRUE,1,0) -> 0 | AM10: =IF(LEN(TRIM(W10))>0,1,0) -> 0
B11: =IF(ISBLANK('ONR 1'!B13),"",'ONR 1'!B13) -> 1.7 | C11: =IF(ISBLANK('ONR 1'!C13),"",'ONR 1'!C13) -> Réserver l’intelligence artificielle aux besoins qui la justifient et privilégier des solutions sobres en ressources. | D11: =IF(ISBLANK('ONR 1'!D13),"",'ONR 1'!D13) -> Avantages possibles : maîtriser les coûts du matériel et des services d’IA, et réduire les émissions de gaz à effet de serre liées à leur entraînement et à leur utilisation. Risque : utiliser l’IA par effet de mode, sans besoin réel, et consommer davantage de ressources. | E11: =IF(ISBLANK('ONR 1'!E13),"",'ONR 1'!E13) -> 3 | F11: =IF(ISBLANK('ONR 1'!F13),"",'ONR 1'!F13) -> 1 | G11: =IF(ISBLANK('ONR 1'!G13),"",'ONR 1'!G13) -> Les équipes métiers expérimentent plusieurs projets d’IA générative, dont des usages de ChatGPT. Elles ne mesurent pas leur impact énergétique et ne disposent pas de charte pour encadrer les besoins et les usages. | H11: =IF(ISBLANK('ONR 1'!H13),"",'ONR 1'!H13) -> 2 | I11: =IF(ISBLANK('ONR 1'!I13),"",'ONR 1'!I13) -> Point fort : l’équipe chargée des données et de l’informatique dispose de compétences techniques et souhaite explorer ces outils. Points faibles : elle connaît peu les méthodes pour mesurer et réduire la consommation de l’IA. Elle manque aussi de recul pour savoir quand l’IA est utile. | ... U11: =IF(ISBLANK('ONR 1'!U13),"",'ONR 1'!U13) -> 62 | V11: =IF(ISBLANK('ONR 1'!G13),"",'ONR 1'!G13) -> Les équipes métiers expérimentent plusieurs projets d’IA générative, dont des usages de ChatGPT. Elles ne mesurent pas leur impact énergétique et ne disposent pas de charte pour encadrer les besoins et les usages. | W11: =IF(ISBLANK('ONR 1'!V13),"",'ONR 1'!V13) -> 1. Vérifier le besoin avant chaque projet : faut-il de l’IA ou un outil informatique classique suffit-il ? 2. Choisir de petits modèles spécialisés quand ils répondent au besoin. 3. Former les développeurs et les spécialistes des données à réduire la consommation de l’IA, en améliorant le code et en évitant les calculs répétés. | X11: =IF(ISBLANK('ONR 1'!W13),"",'ONR 1'!W13) | Y11: =IF(ISBLANK('ONR 1'!I13),"",'ONR 1'!I13) -> Point fort : l’équipe chargée des données et de l’informatique dispose de compétences techniques et souhaite explorer ces outils. Points faibles : elle connaît peu les méthodes pour mesurer et réduire la consommation de l’IA. Elle manque aussi de recul pour savoir quand l’IA est utile. | Z11: =IF(ISBLANK('ONR 1'!D13),"",'ONR 1'!D13) -> Avantages possibles : maîtriser les coûts du matériel et des services d’IA, et réduire les émissions de gaz à effet de serre liées à leur entraînement et à leur utilisation. Risque : utiliser l’IA par effet de mode, sans besoin réel, et consommer davantage de ressources. | AE11: =IF(ISNUMBER(T11),0,1) -> 0 | AF11: =IF(L11=TRUE,1,0) -> 1 | AG11: =IF(M11=TRUE,1,0) -> 0 | AH11: =IF(N11=TRUE,1,0) -> 0 | AI11: =IF(O11=TRUE,1,0) -> 0 | AJ11: =IF(P11=TRUE,1,0) -> 0 | AK11: =IF(Q11=TRUE,1,0) -> 0 | AL11: =IF(R11=TRUE,1,0) -> 0 | AM11: =IF(LEN(TRIM(W11))>0,1,0) -> 1
B12: =IF(ISBLANK('ONR 1'!B14),"",'ONR 1'!B14) -> 1.8 | C12: =IF(ISBLANK('ONR 1'!C14),"",'ONR 1'!C14) -> Mesurer et réduire ce que consomme l’intelligence artificielle, pendant son entraînement comme pendant son utilisation. | D12: =IF(ISBLANK('ONR 1'!D14),"",'ONR 1'!D14) -> Avantages possibles : maîtriser les coûts du matériel et des services d’IA, et réduire les émissions de gaz à effet de serre liées à leur entraînement et à leur utilisation. Risque : utiliser l’IA par effet de mode, sans besoin réel, et consommer davantage de ressources. | E12: =IF(ISBLANK('ONR 1'!E14),"",'ONR 1'!E14) -> 3 | F12: =IF(ISBLANK('ONR 1'!F14),"",'ONR 1'!F14) -> 1 | G12: =IF(ISBLANK('ONR 1'!G14),"",'ONR 1'!G14) -> Les équipes métiers expérimentent plusieurs projets d’IA générative, dont des usages de ChatGPT. Elles ne mesurent pas leur impact énergétique et ne disposent pas de charte pour encadrer les besoins et les usages. | H12: =IF(ISBLANK('ONR 1'!H14),"",'ONR 1'!H14) -> 2 | I12: =IF(ISBLANK('ONR 1'!I14),"",'ONR 1'!I14) -> Point fort : l’équipe chargée des données et de l’informatique dispose de compétences techniques et souhaite explorer ces outils. Points faibles : elle connaît peu les méthodes pour mesurer et réduire la consommation de l’IA. Elle manque aussi de recul pour savoir quand l’IA est utile. | ... U12: =IF(ISBLANK('ONR 1'!U14),"",'ONR 1'!U14) -> 62 | V12: =IF(ISBLANK('ONR 1'!G14),"",'ONR 1'!G14) -> Les équipes métiers expérimentent plusieurs projets d’IA générative, dont des usages de ChatGPT. Elles ne mesurent pas leur impact énergétique et ne disposent pas de charte pour encadrer les besoins et les usages. | W12: =IF(ISBLANK('ONR 1'!V14),"",'ONR 1'!V14) -> 1. Vérifier le besoin avant chaque projet : faut-il de l’IA ou un outil informatique classique suffit-il ? 2. Choisir de petits modèles spécialisés quand ils répondent au besoin. 3. Former les développeurs et les spécialistes des données à réduire la consommation de l’IA, en améliorant le code et en évitant les calculs répétés. | X12: =IF(ISBLANK('ONR 1'!W14),"",'ONR 1'!W14) | Y12: =IF(ISBLANK('ONR 1'!I14),"",'ONR 1'!I14) -> Point fort : l’équipe chargée des données et de l’informatique dispose de compétences techniques et souhaite explorer ces outils. Points faibles : elle connaît peu les méthodes pour mesurer et réduire la consommation de l’IA. Elle manque aussi de recul pour savoir quand l’IA est utile. | Z12: =IF(ISBLANK('ONR 1'!D14),"",'ONR 1'!D14) -> Avantages possibles : maîtriser les coûts du matériel et des services d’IA, et réduire les émissions de gaz à effet de serre liées à leur entraînement et à leur utilisation. Risque : utiliser l’IA par effet de mode, sans besoin réel, et consommer davantage de ressources. | AE12: =IF(ISNUMBER(T12),0,1) -> 0 | AF12: =IF(L12=TRUE,1,0) -> 1 | AG12: =IF(M12=TRUE,1,0) -> 0 | AH12: =IF(N12=TRUE,1,0) -> 0 | AI12: =IF(O12=TRUE,1,0) -> 0 | AJ12: =IF(P12=TRUE,1,0) -> 0 | AK12: =IF(Q12=TRUE,1,0) -> 0 | AL12: =IF(R12=TRUE,1,0) -> 0 | AM12: =IF(LEN(TRIM(W12))>0,1,0) -> 1
B13: ='ONR 2'!B2 -> ONR 2 : Inclusion · Développer des services numériques durables que toutes et tous peuvent utiliser | AB13: =B13 -> ONR 2 : Inclusion · Développer des services numériques durables que toutes et tous peuvent utiliser | AC13: =COUNTA('ONR 2'!B7:B11) -> 5 | AD13: =COUNT(T14:T18) -> 0 | AE13: =SUM(AE14:AE18) -> 5 | AF13: =SUM(AF14:AF18) -> 0 | AG13: =SUM(AG14:AG18) -> 0 | AH13: =SUM(AH14:AH18) -> 0 | AI13: =SUM(AI14:AI18) -> 0 | AJ13: =SUM(AJ14:AJ18) -> 0 | AK13: =SUM(AK14:AK18) -> 0 | AL13: =SUM(AL14:AL18) -> 0
B14: =IF(ISBLANK('ONR 2'!B7),"",'ONR 2'!B7) -> 2.1 | C14: =IF(ISBLANK('ONR 2'!C7),"",'ONR 2'!C7) -> Intégrer dans tous les achats des exigences qui tiennent compte de leurs effets sur la société et l’environnement. | D14: =IF(ISBLANK('ONR 2'!D7),"",'ONR 2'!D7) | E14: =IF(ISBLANK('ONR 2'!E7),"",'ONR 2'!E7) | F14: =IF(ISBLANK('ONR 2'!F7),"",'ONR 2'!F7) | G14: =IF(ISBLANK('ONR 2'!G7),"",'ONR 2'!G7) | H14: =IF(ISBLANK('ONR 2'!H7),"",'ONR 2'!H7) | I14: =IF(ISBLANK('ONR 2'!I7),"",'ONR 2'!I7) | ... U14: =IF(ISBLANK('ONR 2'!U7),"",'ONR 2'!U7) | V14: =IF(ISBLANK('ONR 2'!G7),"",'ONR 2'!G7) | W14: =IF(ISBLANK('ONR 2'!V7),"",'ONR 2'!V7) | X14: =IF(ISBLANK('ONR 2'!W7),"",'ONR 2'!W7) | Y14: =IF(ISBLANK('ONR 2'!I7),"",'ONR 2'!I7) | Z14: =IF(ISBLANK('ONR 2'!D7),"",'ONR 2'!D7) | AE14: =IF(ISNUMBER(T14),0,1) -> 1 | AF14: =IF(L14=TRUE,1,0) -> 0 | AG14: =IF(M14=TRUE,1,0) -> 0 | AH14: =IF(N14=TRUE,1,0) -> 0 | AI14: =IF(O14=TRUE,1,0) -> 0 | AJ14: =IF(P14=TRUE,1,0) -> 0 | AK14: =IF(Q14=TRUE,1,0) -> 0 | AL14: =IF(R14=TRUE,1,0) -> 0 | AM14: =IF(LEN(TRIM(W14))>0,1,0) -> 0
B15: =IF(ISBLANK('ONR 2'!B8),"",'ONR 2'!B8) -> 2.2 | C15: =IF(ISBLANK('ONR 2'!C8),"",'ONR 2'!C8) -> Rendre les services numériques accessibles à toutes et tous. Mesurer leur respect du RGAA, le référentiel français sur l’accessibilité numérique. | D15: =IF(ISBLANK('ONR 2'!D8),"",'ONR 2'!D8) | E15: =IF(ISBLANK('ONR 2'!E8),"",'ONR 2'!E8) | F15: =IF(ISBLANK('ONR 2'!F8),"",'ONR 2'!F8) | G15: =IF(ISBLANK('ONR 2'!G8),"",'ONR 2'!G8) | H15: =IF(ISBLANK('ONR 2'!H8),"",'ONR 2'!H8) | I15: =IF(ISBLANK('ONR 2'!I8),"",'ONR 2'!I8) | ... U15: =IF(ISBLANK('ONR 2'!U8),"",'ONR 2'!U8) | V15: =IF(ISBLANK('ONR 2'!G8),"",'ONR 2'!G8) | W15: =IF(ISBLANK('ONR 2'!V8),"",'ONR 2'!V8) | X15: =IF(ISBLANK('ONR 2'!W8),"",'ONR 2'!W8) | Y15: =IF(ISBLANK('ONR 2'!I8),"",'ONR 2'!I8) | Z15: =IF(ISBLANK('ONR 2'!D8),"",'ONR 2'!D8) | AE15: =IF(ISNUMBER(T15),0,1) -> 1 | AF15: =IF(L15=TRUE,1,0) -> 0 | AG15: =IF(M15=TRUE,1,0) -> 0 | AH15: =IF(N15=TRUE,1,0) -> 0 | AI15: =IF(O15=TRUE,1,0) -> 0 | AJ15: =IF(P15=TRUE,1,0) -> 0 | AK15: =IF(Q15=TRUE,1,0) -> 0 | AL15: =IF(R15=TRUE,1,0) -> 0 | AM15: =IF(LEN(TRIM(W15))>0,1,0) -> 0
B16: =IF(ISBLANK('ONR 2'!B9),"",'ONR 2'!B9) -> 2.3 | C16: =IF(ISBLANK('ONR 2'!C9),"",'ONR 2'!C9) -> Créer des applications utiles, faciles à utiliser et réellement utilisées : les « 3 U ». Les rendre accessibles pour permettre à chacun d’utiliser le numérique. | D16: =IF(ISBLANK('ONR 2'!D9),"",'ONR 2'!D9) | E16: =IF(ISBLANK('ONR 2'!E9),"",'ONR 2'!E9) | F16: =IF(ISBLANK('ONR 2'!F9),"",'ONR 2'!F9) | G16: =IF(ISBLANK('ONR 2'!G9),"",'ONR 2'!G9) | H16: =IF(ISBLANK('ONR 2'!H9),"",'ONR 2'!H9) | I16: =IF(ISBLANK('ONR 2'!I9),"",'ONR 2'!I9) | ... K17: =IF(ISBLANK('ONR 2'!K10),"",'ONR 2'!K10) | K16: =IF(ISBLANK('ONR 2'!K9),"",'ONR 2'!K9) | L17: =IF(ISBLANK('ONR 2'!L10),"",'ONR 2'!L10) -> FALSE | L16: =IF(ISBLANK('ONR 2'!L9),"",'ONR 2'!L9) -> FALSE | M17: =IF(ISBLANK('ONR 2'!M10),"",'ONR 2'!M10) -> FALSE | M16: =IF(ISBLANK('ONR 2'!M9),"",'ONR 2'!M9) -> FALSE | N17: =IF(ISBLANK('ONR 2'!N10),"",'ONR 2'!N10) -> FALSE | N16: =IF(ISBLANK('ONR 2'!N9),"",'ONR 2'!N9) -> FALSE | O17: =IF(ISBLANK('ONR 2'!O10),"",'ONR 2'!O10) -> FALSE | O16: =IF(ISBLANK('ONR 2'!O9),"",'ONR 2'!O9) -> FALSE | P17: =IF(ISBLANK('ONR 2'!P10),"",'ONR 2'!P10) -> FALSE | P16: =IF(ISBLANK('ONR 2'!P9),"",'ONR 2'!P9) -> FALSE | Q17: =IF(ISBLANK('ONR 2'!Q10),"",'ONR 2'!Q10) -> FALSE | Q16: =IF(ISBLANK('ONR 2'!Q9),"",'ONR 2'!Q9) -> FALSE | R17: =IF(ISBLANK('ONR 2'!R10),"",'ONR 2'!R10) -> FALSE | R16: =IF(ISBLANK('ONR 2'!R9),"",'ONR 2'!R9) -> FALSE | S17: =IF(ISBLANK('ONR 2'!S10),"",'ONR 2'!S10) | S16: =IF(ISBLANK('ONR 2'!S9),"",'ONR 2'!S9) | T17: =IF(ISBLANK('ONR 2'!T10),"",'ONR 2'!T10) | T16: =IF(ISBLANK('ONR 2'!T9),"",'ONR 2'!T9) | U17: =IF(ISBLANK('ONR 2'!U10),"",'ONR 2'!U10) | U16: =IF(ISBLANK('ONR 2'!U9),"",'ONR 2'!U9) | V17: =IF(ISBLANK('ONR 2'!G10),"",'ONR 2'!G10) | V16: =IF(ISBLANK('ONR 2'!G9),"",'ONR 2'!G9) | W16: =IF(ISBLANK('ONR 2'!V9),"",'ONR 2'!V9) | X16: =IF(ISBLANK('ONR 2'!W9),"",'ONR 2'!W9) | Y16: =IF(ISBLANK('ONR 2'!I9),"",'ONR 2'!I9) | Z16: =IF(ISBLANK('ONR 2'!D9),"",'ONR 2'!D9) | AE16: =IF(ISNUMBER(T16),0,1) -> 1 | AF16: =IF(L16=TRUE,1,0) -> 0 | AG16: =IF(M16=TRUE,1,0) -> 0 | AH16: =IF(N16=TRUE,1,0) -> 0 | AI16: =IF(O16=TRUE,1,0) -> 0 | AJ16: =IF(P16=TRUE,1,0) -> 0 | AK16: =IF(Q16=TRUE,1,0) -> 0 | AL16: =IF(R16=TRUE,1,0) -> 0 | AM16: =IF(LEN(TRIM(W16))>0,1,0) -> 0
B17: =IF(ISBLANK('ONR 2'!B10),"",'ONR 2'!B10) -> 2.4 | C17: =IF(ISBLANK('ONR 2'!C10),"",'ONR 2'!C10) -> Concevoir les services avec leurs utilisateurs et utilisatrices, en se concentrant sur leurs besoins réels. | D17: =IF(ISBLANK('ONR 2'!D10),"",'ONR 2'!D10) | E17: =IF(ISBLANK('ONR 2'!E10),"",'ONR 2'!E10) | F17: =IF(ISBLANK('ONR 2'!F10),"",'ONR 2'!F10) | G17: =IF(ISBLANK('ONR 2'!G10),"",'ONR 2'!G10) | H17: =IF(ISBLANK('ONR 2'!H10),"",'ONR 2'!H10) | I17: =IF(ISBLANK('ONR 2'!I10),"",'ONR 2'!I10) | ... U19: =IF(ISBLANK('ONR 2'!U12),"",'ONR 2'!U12) | V19: =G17 | W17: =IF(ISBLANK('ONR 2'!V10),"",'ONR 2'!V10) | X17: =IF(ISBLANK('ONR 2'!W10),"",'ONR 2'!W10) | Y17: =IF(ISBLANK('ONR 2'!I10),"",'ONR 2'!I10) | Z17: =IF(ISBLANK('ONR 2'!D10),"",'ONR 2'!D10) | AE17: =IF(ISNUMBER(T17),0,1) -> 1 | AF17: =IF(L17=TRUE,1,0) -> 0 | AG17: =IF(M17=TRUE,1,0) -> 0 | AH17: =IF(N17=TRUE,1,0) -> 0 | AI17: =IF(O17=TRUE,1,0) -> 0 | AJ17: =IF(P17=TRUE,1,0) -> 0 | AK17: =IF(Q17=TRUE,1,0) -> 0 | AL17: =IF(R17=TRUE,1,0) -> 0 | AM17: =IF(LEN(TRIM(W17))>0,1,0) -> 0
B18: =IF(ISBLANK('ONR 2'!B11),"",'ONR 2'!B11) -> 2.5 | C18: =IF(ISBLANK('ONR 2'!C11),"",'ONR 2'!C11) -> Vérifier que l’intelligence artificielle ne discrimine personne et que ses services peuvent être utilisés par toutes et tous. | D18: =IF(ISBLANK('ONR 2'!D11),"",'ONR 2'!D11) | E18: =IF(ISBLANK('ONR 2'!E11),"",'ONR 2'!E11) | F18: =IF(ISBLANK('ONR 2'!F11),"",'ONR 2'!F11) | G18: =IF(ISBLANK('ONR 2'!G11),"",'ONR 2'!G11) | H18: =IF(ISBLANK('ONR 2'!H11),"",'ONR 2'!H11) | I18: =IF(ISBLANK('ONR 2'!I11),"",'ONR 2'!I11) | ... U18: =IF(ISBLANK('ONR 2'!U11),"",'ONR 2'!U11) | V18: =IF(ISBLANK('ONR 2'!G11),"",'ONR 2'!G11) | W18: =IF(ISBLANK('ONR 2'!V11),"",'ONR 2'!V11) | X18: =IF(ISBLANK('ONR 2'!W11),"",'ONR 2'!W11) | Y18: =IF(ISBLANK('ONR 2'!I11),"",'ONR 2'!I11) | Z18: =IF(ISBLANK('ONR 2'!D11),"",'ONR 2'!D11) | AE18: =IF(ISNUMBER(T18),0,1) -> 1 | AF18: =IF(L18=TRUE,1,0) -> 0 | AG18: =IF(M18=TRUE,1,0) -> 0 | AH18: =IF(N18=TRUE,1,0) -> 0 | AI18: =IF(O18=TRUE,1,0) -> 0 | AJ18: =IF(P18=TRUE,1,0) -> 0 | AK18: =IF(Q18=TRUE,1,0) -> 0 | AL18: =IF(R18=TRUE,1,0) -> 0 | AM18: =IF(LEN(TRIM(W18))>0,1,0) -> 0
B19: ='ONR 3'!B2 -> ONR 3 : RSE · Utiliser le numérique de façon éthique et responsable | AB19: =B19 -> ONR 3 : RSE · Utiliser le numérique de façon éthique et responsable | AC19: =COUNTA('ONR 3'!B7:B14) -> 8 | AD19: =COUNT(T20:T27) -> 0 | AE19: =SUM(AE20:AE27) -> 8 | AF19: =SUM(AF20:AF27) -> 0 | AG19: =SUM(AG20:AG27) -> 0 | AH19: =SUM(AH20:AH27) -> 0 | AI19: =SUM(AI20:AI27) -> 0 | AJ19: =SUM(AJ20:AJ27) -> 0 | AK19: =SUM(AK20:AK27) -> 0 | AL19: =SUM(AL20:AL27) -> 0
B20: =IF(ISBLANK('ONR 3'!B7),"",'ONR 3'!B7) -> 3.1 | C20: =IF(ISBLANK('ONR 3'!C7),"",'ONR 3'!C7) -> Utiliser les données et les services numériques avec mesure, en respectant les personnes et l’environnement. | D20: =IF(ISBLANK('ONR 3'!D7),"",'ONR 3'!D7) | E20: =IF(ISBLANK('ONR 3'!E7),"",'ONR 3'!E7) | F20: =IF(ISBLANK('ONR 3'!F7),"",'ONR 3'!F7) | G20: =IF(ISBLANK('ONR 3'!G7),"",'ONR 3'!G7) | H20: =IF(ISBLANK('ONR 3'!H7),"",'ONR 3'!H7) | I20: =IF(ISBLANK('ONR 3'!I7),"",'ONR 3'!I7) | ... U20: =IF(ISBLANK('ONR 3'!U7),"",'ONR 3'!U7) | V20: =IF(ISBLANK('ONR 3'!G7),"",'ONR 3'!G7) | W20: =IF(ISBLANK('ONR 3'!V7),"",'ONR 3'!V7) | X20: =IF(ISBLANK('ONR 3'!W7),"",'ONR 3'!W7) | Y20: =IF(ISBLANK('ONR 3'!I7),"",'ONR 3'!I7) | Z20: =IF(ISBLANK('ONR 3'!D7),"",'ONR 3'!D7) | AE20: =IF(ISNUMBER(T20),0,1) -> 1 | AF20: =IF(L20=TRUE,1,0) -> 0 | AG20: =IF(M20=TRUE,1,0) -> 0 | AH20: =IF(N20=TRUE,1,0) -> 0 | AI20: =IF(O20=TRUE,1,0) -> 0 | AJ20: =IF(P20=TRUE,1,0) -> 0 | AK20: =IF(Q20=TRUE,1,0) -> 0 | AL20: =IF(R20=TRUE,1,0) -> 0 | AM20: =IF(LEN(TRIM(W20))>0,1,0) -> 0
B21: =IF(ISBLANK('ONR 3'!B8),"",'ONR 3'!B8) -> 3.2 | C21: =IF(ISBLANK('ONR 3'!C8),"",'ONR 3'!C8) -> Supprimer les pratiques et les interfaces qui trompent les utilisateurs sur les sites web, aussi appelées « dark patterns ». Respecter la réglementation. | D21: =IF(ISBLANK('ONR 3'!D8),"",'ONR 3'!D8) | E21: =IF(ISBLANK('ONR 3'!E8),"",'ONR 3'!E8) | F21: =IF(ISBLANK('ONR 3'!F8),"",'ONR 3'!F8) | G21: =IF(ISBLANK('ONR 3'!G8),"",'ONR 3'!G8) | H21: =IF(ISBLANK('ONR 3'!H8),"",'ONR 3'!H8) | I21: =IF(ISBLANK('ONR 3'!I8),"",'ONR 3'!I8) | ... K23: =IF(ISBLANK('ONR 3'!K10),"",'ONR 3'!K10) | K21: =IF(ISBLANK('ONR 3'!K8),"",'ONR 3'!K8) | L23: =IF(ISBLANK('ONR 3'!L10),"",'ONR 3'!L10) -> FALSE | L21: =IF(ISBLANK('ONR 3'!L8),"",'ONR 3'!L8) -> FALSE | M23: =IF(ISBLANK('ONR 3'!M10),"",'ONR 3'!M10) -> FALSE | M21: =IF(ISBLANK('ONR 3'!M8),"",'ONR 3'!M8) -> FALSE | N23: =IF(ISBLANK('ONR 3'!N10),"",'ONR 3'!N10) -> FALSE | N21: =IF(ISBLANK('ONR 3'!N8),"",'ONR 3'!N8) -> FALSE | O23: =IF(ISBLANK('ONR 3'!O10),"",'ONR 3'!O10) -> FALSE | O21: =IF(ISBLANK('ONR 3'!O8),"",'ONR 3'!O8) -> FALSE | P23: =IF(ISBLANK('ONR 3'!P10),"",'ONR 3'!P10) -> FALSE | P21: =IF(ISBLANK('ONR 3'!P8),"",'ONR 3'!P8) -> FALSE | Q23: =IF(ISBLANK('ONR 3'!Q10),"",'ONR 3'!Q10) -> FALSE | Q21: =IF(ISBLANK('ONR 3'!Q8),"",'ONR 3'!Q8) -> FALSE | R23: =IF(ISBLANK('ONR 3'!R10),"",'ONR 3'!R10) -> FALSE | R21: =IF(ISBLANK('ONR 3'!R8),"",'ONR 3'!R8) -> FALSE | S23: =IF(ISBLANK('ONR 3'!S10),"",'ONR 3'!S10) | S21: =IF(ISBLANK('ONR 3'!S8),"",'ONR 3'!S8) | T23: =IF(ISBLANK('ONR 3'!T10),"",'ONR 3'!T10) | T21: =IF(ISBLANK('ONR 3'!T8),"",'ONR 3'!T8) | U23: =IF(ISBLANK('ONR 3'!U10),"",'ONR 3'!U10) | U21: =IF(ISBLANK('ONR 3'!U8),"",'ONR 3'!U8) | V23: =IF(ISBLANK('ONR 3'!G10),"",'ONR 3'!G10) | V21: =IF(ISBLANK('ONR 3'!G8),"",'ONR 3'!G8) | W23: =IF(ISBLANK('ONR 3'!V10),"",'ONR 3'!V10) | W21: =IF(ISBLANK('ONR 3'!V8),"",'ONR 3'!V8) | X21: =IF(ISBLANK('ONR 3'!W8),"",'ONR 3'!W8) | Y21: =IF(ISBLANK('ONR 3'!I8),"",'ONR 3'!I8) | Z21: =IF(ISBLANK('ONR 3'!D8),"",'ONR 3'!D8) | AE21: =IF(ISNUMBER(T21),0,1) -> 1 | AF21: =IF(L21=TRUE,1,0) -> 0 | AG21: =IF(M21=TRUE,1,0) -> 0 | AH21: =IF(N21=TRUE,1,0) -> 0 | AI21: =IF(O21=TRUE,1,0) -> 0 | AJ21: =IF(P21=TRUE,1,0) -> 0 | AK21: =IF(Q21=TRUE,1,0) -> 0 | AL21: =IF(R21=TRUE,1,0) -> 0 | AM21: =IF(LEN(TRIM(W21))>0,1,0) -> 0
B22: =IF(ISBLANK('ONR 3'!B9),"",'ONR 3'!B9) -> 3.3 | C22: =IF(ISBLANK('ONR 3'!C9),"",'ONR 3'!C9) -> Collecter seulement les données nécessaires au service rendu. Protéger la vie privée, réduire les effets sur l’environnement et respecter le RGPD, le règlement sur la protection des données personnelles. | D22: =IF(ISBLANK('ONR 3'!D9),"",'ONR 3'!D9) | E22: =IF(ISBLANK('ONR 3'!E9),"",'ONR 3'!E9) | F22: =IF(ISBLANK('ONR 3'!F9),"",'ONR 3'!F9) | G22: =IF(ISBLANK('ONR 3'!G9),"",'ONR 3'!G9) | H22: =IF(ISBLANK('ONR 3'!H9),"",'ONR 3'!H9) | I22: =IF(ISBLANK('ONR 3'!I9),"",'ONR 3'!I9) | ... K24: =IF(ISBLANK('ONR 3'!K11),"",'ONR 3'!K11) | K22: =IF(ISBLANK('ONR 3'!K9),"",'ONR 3'!K9) | L24: =IF(ISBLANK('ONR 3'!L11),"",'ONR 3'!L11) -> FALSE | L22: =IF(ISBLANK('ONR 3'!L9),"",'ONR 3'!L9) -> FALSE | M24: =IF(ISBLANK('ONR 3'!M11),"",'ONR 3'!M11) -> FALSE | M22: =IF(ISBLANK('ONR 3'!M9),"",'ONR 3'!M9) -> FALSE | N24: =IF(ISBLANK('ONR 3'!N11),"",'ONR 3'!N11) -> FALSE | N22: =IF(ISBLANK('ONR 3'!N9),"",'ONR 3'!N9) -> FALSE | O24: =IF(ISBLANK('ONR 3'!O11),"",'ONR 3'!O11) -> FALSE | O22: =IF(ISBLANK('ONR 3'!O9),"",'ONR 3'!O9) -> FALSE | P24: =IF(ISBLANK('ONR 3'!P11),"",'ONR 3'!P11) -> FALSE | P22: =IF(ISBLANK('ONR 3'!P9),"",'ONR 3'!P9) -> FALSE | Q24: =IF(ISBLANK('ONR 3'!Q11),"",'ONR 3'!Q11) -> FALSE | Q22: =IF(ISBLANK('ONR 3'!Q9),"",'ONR 3'!Q9) -> FALSE | R24: =IF(ISBLANK('ONR 3'!R11),"",'ONR 3'!R11) -> FALSE | R22: =IF(ISBLANK('ONR 3'!R9),"",'ONR 3'!R9) -> FALSE | S24: =IF(ISBLANK('ONR 3'!S11),"",'ONR 3'!S11) | S22: =IF(ISBLANK('ONR 3'!S9),"",'ONR 3'!S9) | T24: =IF(ISBLANK('ONR 3'!T11),"",'ONR 3'!T11) | T22: =IF(ISBLANK('ONR 3'!T9),"",'ONR 3'!T9) | U24: =IF(ISBLANK('ONR 3'!U11),"",'ONR 3'!U11) | U22: =IF(ISBLANK('ONR 3'!U9),"",'ONR 3'!U9) | V24: =IF(ISBLANK('ONR 3'!G11),"",'ONR 3'!G11) | V22: =IF(ISBLANK('ONR 3'!G9),"",'ONR 3'!G9) | W24: =IF(ISBLANK('ONR 3'!V11),"",'ONR 3'!V11) | W22: =IF(ISBLANK('ONR 3'!V9),"",'ONR 3'!V9) | X22: =IF(ISBLANK('ONR 3'!W9),"",'ONR 3'!W9) | Y22: =IF(ISBLANK('ONR 3'!I9),"",'ONR 3'!I9) | Z22: =IF(ISBLANK('ONR 3'!D9),"",'ONR 3'!D9) | AE22: =IF(ISNUMBER(T22),0,1) -> 1 | AF22: =IF(L22=TRUE,1,0) -> 0 | AG22: =IF(M22=TRUE,1,0) -> 0 | AH22: =IF(N22=TRUE,1,0) -> 0 | AI22: =IF(O22=TRUE,1,0) -> 0 | AJ22: =IF(P22=TRUE,1,0) -> 0 | AK22: =IF(Q22=TRUE,1,0) -> 0 | AL22: =IF(R22=TRUE,1,0) -> 0 | AM22: =IF(LEN(TRIM(W22))>0,1,0) -> 0
B23: =IF(ISBLANK('ONR 3'!B10),"",'ONR 3'!B10) -> 3.4 | C23: =IF(ISBLANK('ONR 3'!C10),"",'ONR 3'!C10) -> Recruter des personnes aux profils variés dans les métiers du numérique. | D23: =IF(ISBLANK('ONR 3'!D10),"",'ONR 3'!D10) | E23: =IF(ISBLANK('ONR 3'!E10),"",'ONR 3'!E10) | F23: =IF(ISBLANK('ONR 3'!F10),"",'ONR 3'!F10) | G23: =IF(ISBLANK('ONR 3'!G10),"",'ONR 3'!G10) | H23: =IF(ISBLANK('ONR 3'!H10),"",'ONR 3'!H10) | I23: =IF(ISBLANK('ONR 3'!I10),"",'ONR 3'!I10) | ... U25: =IF(ISBLANK('ONR 3'!U12),"",'ONR 3'!U12) | V25: =IF(ISBLANK('ONR 3'!G12),"",'ONR 3'!G12) | W25: =IF(ISBLANK('ONR 3'!V12),"",'ONR 3'!V12) | X23: =IF(ISBLANK('ONR 3'!W10),"",'ONR 3'!W10) | Y23: =IF(ISBLANK('ONR 3'!I10),"",'ONR 3'!I10) | Z23: =IF(ISBLANK('ONR 3'!D10),"",'ONR 3'!D10) | AE23: =IF(ISNUMBER(T23),0,1) -> 1 | AF23: =IF(L23=TRUE,1,0) -> 0 | AG23: =IF(M23=TRUE,1,0) -> 0 | AH23: =IF(N23=TRUE,1,0) -> 0 | AI23: =IF(O23=TRUE,1,0) -> 0 | AJ23: =IF(P23=TRUE,1,0) -> 0 | AK23: =IF(Q23=TRUE,1,0) -> 0 | AL23: =IF(R23=TRUE,1,0) -> 0 | AM23: =IF(LEN(TRIM(W23))>0,1,0) -> 0
B24: =IF(ISBLANK('ONR 3'!B11),"",'ONR 3'!B11) -> 3.5 | C24: =IF(ISBLANK('ONR 3'!C11),"",'ONR 3'!C11) -> Améliorer les conditions de travail des personnes qui travaillent dans le numérique. | D24: =IF(ISBLANK('ONR 3'!D11),"",'ONR 3'!D11) | E24: =IF(ISBLANK('ONR 3'!E11),"",'ONR 3'!E11) | F24: =IF(ISBLANK('ONR 3'!F11),"",'ONR 3'!F11) | G24: =IF(ISBLANK('ONR 3'!G11),"",'ONR 3'!G11) | H24: =IF(ISBLANK('ONR 3'!H11),"",'ONR 3'!H11) | I24: =IF(ISBLANK('ONR 3'!I11),"",'ONR 3'!I11) | ... U26: =IF(ISBLANK('ONR 3'!U13),"",'ONR 3'!U13) | V26: =IF(ISBLANK('ONR 3'!G13),"",'ONR 3'!G13) | W26: =IF(ISBLANK('ONR 3'!V13),"",'ONR 3'!V13) | X24: =IF(ISBLANK('ONR 3'!W11),"",'ONR 3'!W11) | Y24: =IF(ISBLANK('ONR 3'!I11),"",'ONR 3'!I11) | Z24: =IF(ISBLANK('ONR 3'!D11),"",'ONR 3'!D11) | AE24: =IF(ISNUMBER(T24),0,1) -> 1 | AF24: =IF(L24=TRUE,1,0) -> 0 | AG24: =IF(M24=TRUE,1,0) -> 0 | AH24: =IF(N24=TRUE,1,0) -> 0 | AI24: =IF(O24=TRUE,1,0) -> 0 | AJ24: =IF(P24=TRUE,1,0) -> 0 | AK24: =IF(Q24=TRUE,1,0) -> 0 | AL24: =IF(R24=TRUE,1,0) -> 0 | AM24: =IF(LEN(TRIM(W24))>0,1,0) -> 0
B25: =IF(ISBLANK('ONR 3'!B12),"",'ONR 3'!B12) -> 3.6 | C25: =IF(ISBLANK('ONR 3'!C12),"",'ONR 3'!C12) -> Fixer et appliquer des règles éthiques pour utiliser les algorithmes, en particulier l’intelligence artificielle. Encadrer l’utilisation des données et assurer leur protection. | D25: =IF(ISBLANK('ONR 3'!D12),"",'ONR 3'!D12) | E25: =IF(ISBLANK('ONR 3'!E12),"",'ONR 3'!E12) | F25: =IF(ISBLANK('ONR 3'!F12),"",'ONR 3'!F12) | G25: =IF(ISBLANK('ONR 3'!G12),"",'ONR 3'!G12) | H25: =IF(ISBLANK('ONR 3'!H12),"",'ONR 3'!H12) | I25: =IF(ISBLANK('ONR 3'!I12),"",'ONR 3'!I12) | ... U28: =IF(ISBLANK('ONR 3'!U15),"",'ONR 3'!U15) | V28: =IF(ISBLANK('ONR 3'!G15),"",'ONR 3'!G15) | W28: ='ONR 3'!V12 | X25: =IF(ISBLANK('ONR 3'!W12),"",'ONR 3'!W12) | Y25: =IF(ISBLANK('ONR 3'!I12),"",'ONR 3'!I12) | Z25: =IF(ISBLANK('ONR 3'!D12),"",'ONR 3'!D12) | AE25: =IF(ISNUMBER(T25),0,1) -> 1 | AF25: =IF(L25=TRUE,1,0) -> 0 | AG25: =IF(M25=TRUE,1,0) -> 0 | AH25: =IF(N25=TRUE,1,0) -> 0 | AI25: =IF(O25=TRUE,1,0) -> 0 | AJ25: =IF(P25=TRUE,1,0) -> 0 | AK25: =IF(Q25=TRUE,1,0) -> 0 | AL25: =IF(R25=TRUE,1,0) -> 0 | AM25: =IF(LEN(TRIM(W25))>0,1,0) -> 0
B26: =IF(ISBLANK('ONR 3'!B13),"",'ONR 3'!B13) -> 3.7 | C26: =IF(ISBLANK('ONR 3'!C13),"",'ONR 3'!C13) -> Mettre en place et faire connaître les actions de responsabilité sociétale (RSE), qui prennent en compte les effets de l’organisation sur la société et l’environnement. | D26: =IF(ISBLANK('ONR 3'!D13),"",'ONR 3'!D13) | E26: =IF(ISBLANK('ONR 3'!E13),"",'ONR 3'!E13) | F26: =IF(ISBLANK('ONR 3'!F13),"",'ONR 3'!F13) | G26: =IF(ISBLANK('ONR 3'!G13),"",'ONR 3'!G13) | H26: =IF(ISBLANK('ONR 3'!H13),"",'ONR 3'!H13) | I26: =IF(ISBLANK('ONR 3'!I13),"",'ONR 3'!I13) | ... U26: =IF(ISBLANK('ONR 3'!U13),"",'ONR 3'!U13) | V26: =IF(ISBLANK('ONR 3'!G13),"",'ONR 3'!G13) | W29: ='ONR 3'!V13 | X26: =IF(ISBLANK('ONR 3'!W13),"",'ONR 3'!W13) | Y26: =IF(ISBLANK('ONR 3'!I13),"",'ONR 3'!I13) | Z26: =IF(ISBLANK('ONR 3'!D13),"",'ONR 3'!D13) | AE26: =IF(ISNUMBER(T26),0,1) -> 1 | AF26: =IF(L26=TRUE,1,0) -> 0 | AG26: =IF(M26=TRUE,1,0) -> 0 | AH26: =IF(N26=TRUE,1,0) -> 0 | AI26: =IF(O26=TRUE,1,0) -> 0 | AJ26: =IF(P26=TRUE,1,0) -> 0 | AK26: =IF(Q26=TRUE,1,0) -> 0 | AL26: =IF(R26=TRUE,1,0) -> 0 | AM26: =IF(LEN(TRIM(W26))>0,1,0) -> 0
B27: =IF(ISBLANK('ONR 3'!B14),"",'ONR 3'!B14) -> 3.8 | C27: =IF(ISBLANK('ONR 3'!C14),"",'ONR 3'!C14) -> Indiquer quand une intelligence artificielle répond et expliquer comment elle prend ses décisions. Garder un contrôle humain sur les sujets sensibles. | D27: =IF(ISBLANK('ONR 3'!D14),"",'ONR 3'!D14) | E27: =IF(ISBLANK('ONR 3'!E14),"",'ONR 3'!E14) | F27: =IF(ISBLANK('ONR 3'!F14),"",'ONR 3'!F14) | G27: =IF(ISBLANK('ONR 3'!G14),"",'ONR 3'!G14) | H27: =IF(ISBLANK('ONR 3'!H14),"",'ONR 3'!H14) | I27: =IF(ISBLANK('ONR 3'!I14),"",'ONR 3'!I14) | ... U27: =IF(ISBLANK('ONR 3'!U14),"",'ONR 3'!U14) | V27: =IF(ISBLANK('ONR 3'!G14),"",'ONR 3'!G14) | W27: =IF(ISBLANK('ONR 3'!V14),"",'ONR 3'!V14) | X27: =IF(ISBLANK('ONR 3'!W14),"",'ONR 3'!W14) | Y27: =IF(ISBLANK('ONR 3'!I14),"",'ONR 3'!I14) | Z27: =IF(ISBLANK('ONR 3'!D14),"",'ONR 3'!D14) | AE27: =IF(ISNUMBER(T27),0,1) -> 1 | AF27: =IF(L27=TRUE,1,0) -> 0 | AG27: =IF(M27=TRUE,1,0) -> 0 | AH27: =IF(N27=TRUE,1,0) -> 0 | AI27: =IF(O27=TRUE,1,0) -> 0 | AJ27: =IF(P27=TRUE,1,0) -> 0 | AK27: =IF(Q27=TRUE,1,0) -> 0 | AL27: =IF(R27=TRUE,1,0) -> 0 | AM27: =IF(LEN(TRIM(W27))>0,1,0) -> 0
B28: ='ONR 4'!B2 -> ONR 4 : Résilience et stratégie · Utiliser le numérique responsable pour aider l’organisation à faire face aux difficultés et à s’adapter | AB28: =B28 -> ONR 4 : Résilience et stratégie · Utiliser le numérique responsable pour aider l’organisation à faire face aux difficultés et à s’adapter | AC28: =COUNTA('ONR 4'!B7:B10) -> 4 | AD28: =COUNT(T29:T32) -> 0 | AE28: =SUM(AE29:AE32) -> 4 | AF28: =SUM(AF29:AF32) -> 0 | AG28: =SUM(AG29:AG32) -> 0 | AH28: =SUM(AH29:AH32) -> 0 | AI28: =SUM(AI29:AI32) -> 0 | AJ28: =SUM(AJ29:AJ32) -> 0 | AK28: =SUM(AK29:AK32) -> 0 | AL28: =SUM(AL29:AL32) -> 0
B29: =IF(ISBLANK('ONR 4'!B7),"",'ONR 4'!B7) -> 4.1 | C29: =IF(ISBLANK('ONR 4'!C7),"",'ONR 4'!C7) -> Suivre des normes communes pour recueillir, regrouper, analyser et partager les données sur les effets des technologies de l’information et de la communication (TIC). | D29: =IF(ISBLANK('ONR 4'!D7),"",'ONR 4'!D7) | E29: =IF(ISBLANK('ONR 4'!E7),"",'ONR 4'!E7) | F29: =IF(ISBLANK('ONR 4'!F7),"",'ONR 4'!F7) | G29: =IF(ISBLANK('ONR 4'!G7),"",'ONR 4'!G7) | H29: =IF(ISBLANK('ONR 4'!H7),"",'ONR 4'!H7) | I29: =IF(ISBLANK('ONR 4'!I7),"",'ONR 4'!I7) | ... U29: =IF(ISBLANK('ONR 4'!U7),"",'ONR 4'!U7) | V29: =IF(ISBLANK('ONR 4'!G7),"",'ONR 4'!G7) | W29: =IF(ISBLANK('ONR 4'!V7),"",'ONR 4'!V7) | X29: =IF(ISBLANK('ONR 4'!W7),"",'ONR 4'!W7) | Y29: =IF(ISBLANK('ONR 4'!I7),"",'ONR 4'!I7) | Z29: =IF(ISBLANK('ONR 4'!D7),"",'ONR 4'!D7) | AE29: =IF(ISNUMBER(T29),0,1) -> 1 | AF29: =IF(L29=TRUE,1,0) -> 0 | AG29: =IF(M29=TRUE,1,0) -> 0 | AH29: =IF(N29=TRUE,1,0) -> 0 | AI29: =IF(O29=TRUE,1,0) -> 0 | AJ29: =IF(P29=TRUE,1,0) -> 0 | AK29: =IF(Q29=TRUE,1,0) -> 0 | AL29: =IF(R29=TRUE,1,0) -> 0 | AM29: =IF(LEN(TRIM(W29))>0,1,0) -> 0
B30: =IF(ISBLANK('ONR 4'!B8),"",'ONR 4'!B8) -> 4.2 | C30: =IF(ISBLANK('ONR 4'!C8),"",'ONR 4'!C8) -> Évaluer les services numériques au fil du temps et partager les résultats. | D30: =IF(ISBLANK('ONR 4'!D8),"",'ONR 4'!D8) | E30: =IF(ISBLANK('ONR 4'!E8),"",'ONR 4'!E8) | F30: =IF(ISBLANK('ONR 4'!F8),"",'ONR 4'!F8) | G30: =IF(ISBLANK('ONR 4'!G8),"",'ONR 4'!G8) | H30: =IF(ISBLANK('ONR 4'!H8),"",'ONR 4'!H8) | I30: =IF(ISBLANK('ONR 4'!I8),"",'ONR 4'!I8) | ... K30: =IF(ISBLANK('ONR 4'!K8),"",'ONR 4'!K8) | L33: =OR(K30=31) | L30: =IF(ISBLANK('ONR 4'!L8),"",'ONR 4'!L8) -> FALSE | M30: =IF(ISBLANK('ONR 4'!M8),"",'ONR 4'!M8) -> FALSE | N30: =IF(ISBLANK('ONR 4'!N8),"",'ONR 4'!N8) -> FALSE | O30: =IF(ISBLANK('ONR 4'!O8),"",'ONR 4'!O8) -> FALSE | P30: =IF(ISBLANK('ONR 4'!P8),"",'ONR 4'!P8) -> FALSE | Q30: =IF(ISBLANK('ONR 4'!Q8),"",'ONR 4'!Q8) -> FALSE | R30: =IF(ISBLANK('ONR 4'!R8),"",'ONR 4'!R8) -> FALSE | S30: =IF(ISBLANK('ONR 4'!S8),"",'ONR 4'!S8) | T33: =IF(ISBLANK('ONR 4'!T11),"",'ONR 4'!T11) | T30: =IF(ISBLANK('ONR 4'!T8),"",'ONR 4'!T8) | U33: =IF(ISBLANK('ONR 4'!U11),"",'ONR 4'!U11) | U30: =IF(ISBLANK('ONR 4'!U8),"",'ONR 4'!U8) | V33: =G30 | V30: =IF(ISBLANK('ONR 4'!G8),"",'ONR 4'!G8) | W30: =IF(ISBLANK('ONR 4'!V8),"",'ONR 4'!V8) | X30: =IF(ISBLANK('ONR 4'!W8),"",'ONR 4'!W8) | Y30: =IF(ISBLANK('ONR 4'!I8),"",'ONR 4'!I8) | Z30: =IF(ISBLANK('ONR 4'!D8),"",'ONR 4'!D8) | AE30: =IF(ISNUMBER(T30),0,1) -> 1 | AF30: =IF(L30=TRUE,1,0) -> 0 | AG30: =IF(M30=TRUE,1,0) -> 0 | AH30: =IF(N30=TRUE,1,0) -> 0 | AI30: =IF(O30=TRUE,1,0) -> 0 | AJ30: =IF(P30=TRUE,1,0) -> 0 | AK30: =IF(Q30=TRUE,1,0) -> 0 | AL30: =IF(R30=TRUE,1,0) -> 0 | AM30: =IF(LEN(TRIM(W30))>0,1,0) -> 0
B31: =IF(ISBLANK('ONR 4'!B9),"",'ONR 4'!B9) -> 4.3 | C31: =IF(ISBLANK('ONR 4'!C9),"",'ONR 4'!C9) -> Innover en utilisant de nouveaux outils numériques. Évaluer leurs effets et expliquer les résultats aux personnes qui les utilisent. | D31: =IF(ISBLANK('ONR 4'!D9),"",'ONR 4'!D9) | E31: =IF(ISBLANK('ONR 4'!E9),"",'ONR 4'!E9) | F31: =IF(ISBLANK('ONR 4'!F9),"",'ONR 4'!F9) | G31: =IF(ISBLANK('ONR 4'!G9),"",'ONR 4'!G9) | H31: =IF(ISBLANK('ONR 4'!H9),"",'ONR 4'!H9) | I31: =IF(ISBLANK('ONR 4'!I9),"",'ONR 4'!I9) | ... U31: =IF(ISBLANK('ONR 4'!U9),"",'ONR 4'!U9) | V31: =IF(ISBLANK('ONR 4'!G9),"",'ONR 4'!G9) | W31: =IF(ISBLANK('ONR 4'!V9),"",'ONR 4'!V9) | X31: =IF(ISBLANK('ONR 4'!W9),"",'ONR 4'!W9) | Y31: =IF(ISBLANK('ONR 4'!I9),"",'ONR 4'!I9) | Z31: =IF(ISBLANK('ONR 4'!D9),"",'ONR 4'!D9) | AE31: =IF(ISNUMBER(T31),0,1) -> 1 | AF31: =IF(L31=TRUE,1,0) -> 0 | AG31: =IF(M31=TRUE,1,0) -> 0 | AH31: =IF(N31=TRUE,1,0) -> 0 | AI31: =IF(O31=TRUE,1,0) -> 0 | AJ31: =IF(P31=TRUE,1,0) -> 0 | AK31: =IF(Q31=TRUE,1,0) -> 0 | AL31: =IF(R31=TRUE,1,0) -> 0 | AM31: =IF(LEN(TRIM(W31))>0,1,0) -> 0
B32: =IF(ISBLANK('ONR 4'!B10),"",'ONR 4'!B10) -> 4.4 | C32: =IF(ISBLANK('ONR 4'!C10),"",'ONR 4'!C10) -> Renforcer la souveraineté numérique : garder la maîtrise de nos choix, de nos outils et de nos données. | D32: =IF(ISBLANK('ONR 4'!D10),"",'ONR 4'!D10) | E32: =IF(ISBLANK('ONR 4'!E10),"",'ONR 4'!E10) | F32: =IF(ISBLANK('ONR 4'!F10),"",'ONR 4'!F10) | G32: =IF(ISBLANK('ONR 4'!G10),"",'ONR 4'!G10) | H32: =IF(ISBLANK('ONR 4'!H10),"",'ONR 4'!H10) | I32: =IF(ISBLANK('ONR 4'!I10),"",'ONR 4'!I10) | J32: =IF(ISBLANK('ONR 4'!J10),"",'ONR 4'!J10) -> 0 | K35: =IF(ISBLANK('ONR 5'!K8),"",'ONR 5'!K8) | K32: =IF(ISBLANK('ONR 4'!K10),"",'ONR 4'!K10) | L35: =IF(ISBLANK('ONR 5'!L8),"",'ONR 5'!L8) -> FALSE | L32: =IF(ISBLANK('ONR 4'!L10),"",'ONR 4'!L10) -> FALSE | M35: =IF(ISBLANK('ONR 4'!M13),"",'ONR 4'!M13) -> FALSE | M32: =IF(ISBLANK('ONR 4'!M10),"",'ONR 4'!M10) -> FALSE | N35: =IF(ISBLANK('ONR 4'!N13),"",'ONR 4'!N13) -> FALSE | N32: =IF(ISBLANK('ONR 4'!N10),"",'ONR 4'!N10) -> FALSE | O35: =IF(ISBLANK('ONR 4'!O13),"",'ONR 4'!O13) -> FALSE | O32: =IF(ISBLANK('ONR 4'!O10),"",'ONR 4'!O10) -> FALSE | P35: =IF(ISBLANK('ONR 4'!P13),"",'ONR 4'!P13) -> FALSE | P32: =IF(ISBLANK('ONR 4'!P10),"",'ONR 4'!P10) -> FALSE | Q35: =IF(ISBLANK('ONR 4'!Q13),"",'ONR 4'!Q13) -> FALSE | Q32: =IF(ISBLANK('ONR 4'!Q10),"",'ONR 4'!Q10) -> FALSE | R35: =IF(ISBLANK('ONR 4'!R13),"",'ONR 4'!R13) -> FALSE | R32: =IF(ISBLANK('ONR 4'!R10),"",'ONR 4'!R10) -> FALSE | S35: =IF(ISBLANK('ONR 4'!S13),"",'ONR 4'!S13) | S32: =IF(ISBLANK('ONR 4'!S10),"",'ONR 4'!S10) | T35: =IF(ISBLANK('ONR 5'!T8),"",'ONR 5'!T8) | T32: =IF(ISBLANK('ONR 4'!T10),"",'ONR 4'!T10) | U35: =IF(ISBLANK('ONR 5'!U8),"",'ONR 5'!U8) | U32: =IF(ISBLANK('ONR 4'!U10),"",'ONR 4'!U10) | V35: =IF(ISBLANK('ONR 5'!G8),"",'ONR 5'!G8) | V32: =IF(ISBLANK('ONR 4'!G10),"",'ONR 4'!G10) | W32: =IF(ISBLANK('ONR 4'!V10),"",'ONR 4'!V10) | X32: =IF(ISBLANK('ONR 4'!W10),"",'ONR 4'!W10) | Y32: =IF(ISBLANK('ONR 4'!I10),"",'ONR 4'!I10) | Z32: =IF(ISBLANK('ONR 4'!D10),"",'ONR 4'!D10) | AE32: =IF(ISNUMBER(T32),0,1) -> 1 | AF32: =IF(L32=TRUE,1,0) -> 0 | AG32: =IF(M32=TRUE,1,0) -> 0 | AH32: =IF(N32=TRUE,1,0) -> 0 | AI32: =IF(O32=TRUE,1,0) -> 0 | AJ32: =IF(P32=TRUE,1,0) -> 0 | AK32: =IF(Q32=TRUE,1,0) -> 0 | AL32: =IF(R32=TRUE,1,0) -> 0 | AM32: =IF(LEN(TRIM(W32))>0,1,0) -> 0
B33: ='ONR 5'!B2 -> ONR 5 : Management · Donner du sens au travail et préserver les personnes et les ressources nécessaires à nos activités | AB33: =B33 -> ONR 5 : Management · Donner du sens au travail et préserver les personnes et les ressources nécessaires à nos activités | AC33: =COUNTA('ONR 5'!B7:B13) -> 7 | AD33: =COUNT(T34:T40) -> 0 | AE33: =SUM(AE34:AE40) -> 7 | AF33: =SUM(AF34:AF40) -> 0 | AG33: =SUM(AG34:AG40) -> 0 | AH33: =SUM(AH34:AH40) -> 0 | AI33: =SUM(AI34:AI40) -> 0 | AJ33: =SUM(AJ34:AJ40) -> 0 | AK33: =SUM(AK34:AK40) -> 0 | AL33: =SUM(AL34:AL40) -> 0
B34: =IF(ISBLANK('ONR 5'!B7),"",'ONR 5'!B7) -> 5.1 | C34: =IF(ISBLANK('ONR 5'!C7),"",'ONR 5'!C7) -> Concevoir les systèmes et les services numériques en intégrant de nouvelles façons de répondre aux besoins sociaux. | D34: =IF(ISBLANK('ONR 5'!D7),"",'ONR 5'!D7) | E34: =IF(ISBLANK('ONR 5'!E7),"",'ONR 5'!E7) | F34: =IF(ISBLANK('ONR 5'!F7),"",'ONR 5'!F7) | G34: =IF(ISBLANK('ONR 5'!G7),"",'ONR 5'!G7) | H34: =IF(ISBLANK('ONR 5'!H7),"",'ONR 5'!H7) | I34: =IF(ISBLANK('ONR 5'!I7),"",'ONR 5'!I7) | J34: =IF(ISBLANK('ONR 5'!J7),"",'ONR 5'!J7) | K37: =E34*10+F34 | K34: =IF(ISBLANK('ONR 5'!K7),"",'ONR 5'!K7) | L34: =IF(ISBLANK('ONR 5'!L7),"",'ONR 5'!L7) -> FALSE | M34: =IF(ISBLANK('ONR 5'!M7),"",'ONR 5'!M7) -> FALSE | N34: =IF(ISBLANK('ONR 5'!N7),"",'ONR 5'!N7) -> FALSE | O34: =IF(ISBLANK('ONR 5'!O7),"",'ONR 5'!O7) -> FALSE | P34: =IF(ISBLANK('ONR 5'!P7),"",'ONR 5'!P7) -> FALSE | Q34: =IF(ISBLANK('ONR 5'!Q7),"",'ONR 5'!Q7) -> FALSE | R34: =IF(ISBLANK('ONR 5'!R7),"",'ONR 5'!R7) -> FALSE | ... U34: =IF(ISBLANK('ONR 5'!U7),"",'ONR 5'!U7) | V34: =IF(ISBLANK('ONR 5'!G7),"",'ONR 5'!G7) | W34: =IF(ISBLANK('ONR 5'!V7),"",'ONR 5'!V7) | X34: =IF(ISBLANK('ONR 5'!W7),"",'ONR 5'!W7) | Y34: =IF(ISBLANK('ONR 5'!I7),"",'ONR 5'!I7) | Z34: =IF(ISBLANK('ONR 5'!D7),"",'ONR 5'!D7) | AE34: =IF(ISNUMBER(T34),0,1) -> 1 | AF34: =IF(L34=TRUE,1,0) -> 0 | AG34: =IF(M34=TRUE,1,0) -> 0 | AH34: =IF(N34=TRUE,1,0) -> 0 | AI34: =IF(O34=TRUE,1,0) -> 0 | AJ34: =IF(P34=TRUE,1,0) -> 0 | AK34: =IF(Q34=TRUE,1,0) -> 0 | AL34: =IF(R34=TRUE,1,0) -> 0 | AM34: =IF(LEN(TRIM(W34))>0,1,0) -> 0
B35: =IF(ISBLANK('ONR 5'!B8),"",'ONR 5'!B8) -> 5.2 | C35: =IF(ISBLANK('ONR 5'!C8),"",'ONR 5'!C8) -> Faire connaître et soutenir les initiatives des équipes qui encouragent l’engagement, la coopération entre services et le bien-être au travail. | D35: =IF(ISBLANK('ONR 5'!D8),"",'ONR 5'!D8) | E35: =IF(ISBLANK('ONR 5'!E8),"",'ONR 5'!E8) | F35: =IF(ISBLANK('ONR 5'!F8),"",'ONR 5'!F8) | G35: =IF(ISBLANK('ONR 5'!G8),"",'ONR 5'!G8) | H35: =IF(ISBLANK('ONR 5'!H8),"",'ONR 5'!H8) | I35: =IF(ISBLANK('ONR 5'!I8),"",'ONR 5'!I8) | J35: =IF(ISBLANK('ONR 5'!J8),"",'ONR 5'!J8) | K38: =E35*10+F35 | L38: =OR(K35=31) -> FALSE | M35: =IF(ISBLANK('ONR 5'!M8),"",'ONR 5'!M8) -> FALSE | N35: =IF(ISBLANK('ONR 5'!N8),"",'ONR 5'!N8) -> FALSE | O35: =IF(ISBLANK('ONR 5'!O8),"",'ONR 5'!O8) -> FALSE | P35: =IF(ISBLANK('ONR 5'!P8),"",'ONR 5'!P8) -> FALSE | Q35: =IF(ISBLANK('ONR 5'!Q8),"",'ONR 5'!Q8) -> FALSE | R35: =IF(ISBLANK('ONR 5'!R8),"",'ONR 5'!R8) -> FALSE | S35: =IF(ISBLANK('ONR 5'!S8),"",'ONR 5'!S8) | T38: =IF(ISBLANK('ONR 5'!T11),"",'ONR 5'!T11) | U38: =IF(ISBLANK('ONR 5'!U11),"",'ONR 5'!U11) | V38: =IF(ISBLANK('ONR 5'!G11),"",'ONR 5'!G11) | W38: ='ONR 5'!V8 | W35: =IF(ISBLANK('ONR 5'!V8),"",'ONR 5'!V8) | X35: =IF(ISBLANK('ONR 5'!W8),"",'ONR 5'!W8) | Y35: =IF(ISBLANK('ONR 5'!I8),"",'ONR 5'!I8) | Z38: =D35 | Z35: =IF(ISBLANK('ONR 5'!D8),"",'ONR 5'!D8) | AE35: =IF(ISNUMBER(T35),0,1) -> 1 | AF35: =IF(L35=TRUE,1,0) -> 0 | AG35: =IF(M35=TRUE,1,0) -> 0 | AH35: =IF(N35=TRUE,1,0) -> 0 | AI35: =IF(O35=TRUE,1,0) -> 0 | AJ35: =IF(P35=TRUE,1,0) -> 0 | AK35: =IF(Q35=TRUE,1,0) -> 0 | AL35: =IF(R35=TRUE,1,0) -> 0 | AM35: =IF(LEN(TRIM(W35))>0,1,0) -> 0
B36: =IF(ISBLANK('ONR 5'!B9),"",'ONR 5'!B9) -> 5.3 | C36: =IF(ISBLANK('ONR 5'!C9),"",'ONR 5'!C9) -> Faire participer les personnes et les organisations concernées. S’appuyer sur leurs connaissances des questions d’environnement, de conditions de vie et de société. | D36: =IF(ISBLANK('ONR 5'!D9),"",'ONR 5'!D9) | E36: =IF(ISBLANK('ONR 5'!E9),"",'ONR 5'!E9) | F36: =IF(ISBLANK('ONR 5'!F9),"",'ONR 5'!F9) | G36: =IF(ISBLANK('ONR 5'!G9),"",'ONR 5'!G9) | H36: =IF(ISBLANK('ONR 5'!H9),"",'ONR 5'!H9) | I36: =IF(ISBLANK('ONR 5'!I9),"",'ONR 5'!I9) | J36: =IF(ISBLANK('ONR 5'!J9),"",'ONR 5'!J9) | K39: =E36*10+F36 | K36: =IF(ISBLANK('ONR 5'!K9),"",'ONR 5'!K9) | L39: =OR(K36=31) -> FALSE | L36: =IF(ISBLANK('ONR 5'!L9),"",'ONR 5'!L9) -> FALSE | M39: =IF(ISBLANK('ONR 5'!M12),"",'ONR 5'!M12) -> FALSE | M36: =IF(ISBLANK('ONR 5'!M9),"",'ONR 5'!M9) -> FALSE | N39: =IF(ISBLANK('ONR 5'!N12),"",'ONR 5'!N12) -> FALSE | N36: =IF(ISBLANK('ONR 5'!N9),"",'ONR 5'!N9) -> FALSE | O39: =IF(ISBLANK('ONR 5'!O12),"",'ONR 5'!O12) -> FALSE | O36: =IF(ISBLANK('ONR 5'!O9),"",'ONR 5'!O9) -> FALSE | P39: =IF(ISBLANK('ONR 5'!P12),"",'ONR 5'!P12) -> FALSE | P36: =IF(ISBLANK('ONR 5'!P9),"",'ONR 5'!P9) -> FALSE | Q39: =IF(ISBLANK('ONR 5'!Q12),"",'ONR 5'!Q12) -> FALSE | Q36: =IF(ISBLANK('ONR 5'!Q9),"",'ONR 5'!Q9) -> FALSE | R39: =IF(ISBLANK('ONR 5'!R12),"",'ONR 5'!R12) -> FALSE | R36: =IF(ISBLANK('ONR 5'!R9),"",'ONR 5'!R9) -> FALSE | S39: =IF(ISBLANK('ONR 5'!S12),"",'ONR 5'!S12) | S36: =IF(ISBLANK('ONR 5'!S9),"",'ONR 5'!S9) | T39: =IF(ISBLANK('ONR 5'!T12),"",'ONR 5'!T12) | T36: =IF(ISBLANK('ONR 5'!T9),"",'ONR 5'!T9) | U39: =IF(ISBLANK('ONR 5'!U12),"",'ONR 5'!U12) | U36: =IF(ISBLANK('ONR 5'!U9),"",'ONR 5'!U9) | V39: =IF(ISBLANK('ONR 5'!G12),"",'ONR 5'!G12) | V36: =IF(ISBLANK('ONR 5'!G9),"",'ONR 5'!G9) | W39: ='ONR 5'!V9 | W36: =IF(ISBLANK('ONR 5'!V9),"",'ONR 5'!V9) | X36: =IF(ISBLANK('ONR 5'!W9),"",'ONR 5'!W9) | Y36: =IF(ISBLANK('ONR 5'!I9),"",'ONR 5'!I9) | Z36: =IF(ISBLANK('ONR 5'!D9),"",'ONR 5'!D9) | AE36: =IF(ISNUMBER(T36),0,1) -> 1 | AF36: =IF(L36=TRUE,1,0) -> 0 | AG36: =IF(M36=TRUE,1,0) -> 0 | AH36: =IF(N36=TRUE,1,0) -> 0 | AI36: =IF(O36=TRUE,1,0) -> 0 | AJ36: =IF(P36=TRUE,1,0) -> 0 | AK36: =IF(Q36=TRUE,1,0) -> 0 | AL36: =IF(R36=TRUE,1,0) -> 0 | AM36: =IF(LEN(TRIM(W36))>0,1,0) -> 0
B37: =IF(ISBLANK('ONR 5'!B10),"",'ONR 5'!B10) -> 5.4 | C37: =IF(ISBLANK('ONR 5'!C10),"",'ONR 5'!C10) -> Permettre aux générations futures d’innover pour mieux vivre ensemble, s’ouvrir aux autres et préserver l’équilibre de la nature. | D37: =IF(ISBLANK('ONR 5'!D10),"",'ONR 5'!D10) | E37: =IF(ISBLANK('ONR 5'!E10),"",'ONR 5'!E10) | F37: =IF(ISBLANK('ONR 5'!F10),"",'ONR 5'!F10) | G37: =IF(ISBLANK('ONR 5'!G10),"",'ONR 5'!G10) | H37: =IF(ISBLANK('ONR 5'!H10),"",'ONR 5'!H10) | I37: =IF(ISBLANK('ONR 5'!I10),"",'ONR 5'!I10) | ... U37: =IF(ISBLANK('ONR 5'!U10),"",'ONR 5'!U10) | V37: =IF(ISBLANK('ONR 5'!G10),"",'ONR 5'!G10) | W37: =IF(ISBLANK('ONR 5'!V10),"",'ONR 5'!V10) | X37: =IF(ISBLANK('ONR 5'!W10),"",'ONR 5'!W10) | Y37: =IF(ISBLANK('ONR 5'!I10),"",'ONR 5'!I10) | Z37: =IF(ISBLANK('ONR 5'!D10),"",'ONR 5'!D10) | AE37: =IF(ISNUMBER(T37),0,1) -> 1 | AF37: =IF(L37=TRUE,1,0) -> 0 | AG37: =IF(M37=TRUE,1,0) -> 0 | AH37: =IF(N37=TRUE,1,0) -> 0 | AI37: =IF(O37=TRUE,1,0) -> 0 | AJ37: =IF(P37=TRUE,1,0) -> 0 | AK37: =IF(Q37=TRUE,1,0) -> 0 | AL37: =IF(R37=TRUE,1,0) -> 0 | AM37: =IF(LEN(TRIM(W37))>0,1,0) -> 0
B38: =IF(ISBLANK('ONR 5'!B11),"",'ONR 5'!B11) -> 5.5 | C38: =IF(ISBLANK('ONR 5'!C11),"",'ONR 5'!C11) -> Suivre les résultats obtenus et le respect des règles à l’aide d’indicateurs. | D38: =IF(ISBLANK('ONR 5'!D11),"",'ONR 5'!D11) | E38: =IF(ISBLANK('ONR 5'!E11),"",'ONR 5'!E11) | F38: =IF(ISBLANK('ONR 5'!F11),"",'ONR 5'!F11) | G38: =IF(ISBLANK('ONR 5'!G11),"",'ONR 5'!G11) | H38: =IF(ISBLANK('ONR 5'!H11),"",'ONR 5'!H11) | I38: =IF(ISBLANK('ONR 5'!I11),"",'ONR 5'!I11) | ... U38: =IF(ISBLANK('ONR 5'!U11),"",'ONR 5'!U11) | V38: =IF(ISBLANK('ONR 5'!G11),"",'ONR 5'!G11) | W38: =IF(ISBLANK('ONR 5'!V11),"",'ONR 5'!V11) | X38: =IF(ISBLANK('ONR 5'!W11),"",'ONR 5'!W11) | Y38: =IF(ISBLANK('ONR 5'!I11),"",'ONR 5'!I11) | Z38: =IF(ISBLANK('ONR 5'!D11),"",'ONR 5'!D11) | AE38: =IF(ISNUMBER(T38),0,1) -> 1 | AF38: =IF(L38=TRUE,1,0) -> 0 | AG38: =IF(M38=TRUE,1,0) -> 0 | AH38: =IF(N38=TRUE,1,0) -> 0 | AI38: =IF(O38=TRUE,1,0) -> 0 | AJ38: =IF(P38=TRUE,1,0) -> 0 | AK38: =IF(Q38=TRUE,1,0) -> 0 | AL38: =IF(R38=TRUE,1,0) -> 0 | AM38: =IF(LEN(TRIM(W38))>0,1,0) -> 0
B39: =IF(ISBLANK('ONR 5'!B12),"",'ONR 5'!B12) -> 5.6 | C39: =IF(ISBLANK('ONR 5'!C12),"",'ONR 5'!C12) -> Proposer des améliorations et de nouvelles idées pour un numérique responsable, y compris des solutions sans outils numériques. | D39: =IF(ISBLANK('ONR 5'!D12),"",'ONR 5'!D12) | E39: =IF(ISBLANK('ONR 5'!E12),"",'ONR 5'!E12) | F39: =IF(ISBLANK('ONR 5'!F12),"",'ONR 5'!F12) | G39: =IF(ISBLANK('ONR 5'!G12),"",'ONR 5'!G12) | H39: =IF(ISBLANK('ONR 5'!H12),"",'ONR 5'!H12) | I39: =IF(ISBLANK('ONR 5'!I12),"",'ONR 5'!I12) | ... U39: =IF(ISBLANK('ONR 5'!U12),"",'ONR 5'!U12) | V39: =IF(ISBLANK('ONR 5'!G12),"",'ONR 5'!G12) | W39: =IF(ISBLANK('ONR 5'!V12),"",'ONR 5'!V12) | X39: =IF(ISBLANK('ONR 5'!W12),"",'ONR 5'!W12) | Y39: =IF(ISBLANK('ONR 5'!I12),"",'ONR 5'!I12) | Z39: =IF(ISBLANK('ONR 5'!D12),"",'ONR 5'!D12) | AE39: =IF(ISNUMBER(T39),0,1) -> 1 | AF39: =IF(L39=TRUE,1,0) -> 0 | AG39: =IF(M39=TRUE,1,0) -> 0 | AH39: =IF(N39=TRUE,1,0) -> 0 | AI39: =IF(O39=TRUE,1,0) -> 0 | AJ39: =IF(P39=TRUE,1,0) -> 0 | AK39: =IF(Q39=TRUE,1,0) -> 0 | AL39: =IF(R39=TRUE,1,0) -> 0 | AM39: =IF(LEN(TRIM(W39))>0,1,0) -> 0
B40: =IF(ISBLANK('ONR 5'!B13),"",'ONR 5'!B13) -> 5.7 | C40: =IF(ISBLANK('ONR 5'!C13),"",'ONR 5'!C13) -> Décider avec les équipes comment utiliser l’intelligence artificielle. Les former à ses limites et préserver le sens de leur travail. | D40: =IF(ISBLANK('ONR 5'!D13),"",'ONR 5'!D13) | E40: =IF(ISBLANK('ONR 5'!E13),"",'ONR 5'!E13) | F40: =IF(ISBLANK('ONR 5'!F13),"",'ONR 5'!F13) | G40: =IF(ISBLANK('ONR 5'!G13),"",'ONR 5'!G13) | H40: =IF(ISBLANK('ONR 5'!H13),"",'ONR 5'!H13) | I40: =IF(ISBLANK('ONR 5'!I13),"",'ONR 5'!I13) | ... U40: =IF(ISBLANK('ONR 5'!U13),"",'ONR 5'!U13) | V40: =IF(ISBLANK('ONR 5'!G13),"",'ONR 5'!G13) | W40: =IF(ISBLANK('ONR 5'!V13),"",'ONR 5'!V13) | X40: =IF(ISBLANK('ONR 5'!W13),"",'ONR 5'!W13) | Y40: =IF(ISBLANK('ONR 5'!I13),"",'ONR 5'!I13) | Z40: =IF(ISBLANK('ONR 5'!D13),"",'ONR 5'!D13) | AE40: =IF(ISNUMBER(T40),0,1) -> 1 | AF40: =IF(L40=TRUE,1,0) -> 0 | AG40: =IF(M40=TRUE,1,0) -> 0 | AH40: =IF(N40=TRUE,1,0) -> 0 | AI40: =IF(O40=TRUE,1,0) -> 0 | AJ40: =IF(P40=TRUE,1,0) -> 0 | AK40: =IF(Q40=TRUE,1,0) -> 0 | AL40: =IF(R40=TRUE,1,0) -> 0 | AM40: =IF(LEN(TRIM(W40))>0,1,0) -> 0

Sheet Résultats synthèse
B2: Résultats de synthèse
B3: Vue d’ensemble des 32 cibles. Saisir les informations dans les onglets ONR 1 à 5. | D3: =SUM(D4:D8) | E3: =SUM(E4:E8) | F3: =SUM(F4:F8) | G3: =SUM(G4:G8) | H3: =SUM(H4:H8) | I3: =SUM(I4:I8) | J3: =SUM(J4:J8) | K3: =SUM(K4:K8) | ... M3: =SUM(M4:M8)
B5: Cibles à évaluer | D5: Cibles évaluées | F5: Part évaluée | H5: Urgentes ou prioritaires | J5: Part des cibles atteintes | L5: Priorités avec une action proposée | AA5: ONR | AB5: Score de priorité | AC5: Clé de classement | AD5: Cible | AE5: Texte de la cible | AF5: Importance | AG5: Niveau atteint | AH5: Compétences | AI5: Action proposée | AJ5: Action renseignée | AK5: Justification renseignée | AL5: Note hors échelle | AM5: Justification manquante | AN5: Ligne source | AO5: Applicabilité | AP5: Compétences à préciser | AQ5: Priorité sans action | AR5: Cible évaluée
B6: =E16 -> 27 | D6: =D16 -> 5 | F6: =F16 -> 0.15625 | H6: =H16+I16 -> 4 | J6: =J16 -> 0 | L6: =K16 -> 1 | AA6: 1 | AB6: =IF(ISNUMBER('Résultats détaillés'!T5),'Résultats détaillés'!T5,"") -> 6 | AC6: =IF(AND(ISNUMBER(AB6),AB6>=5),AB6*100+32,0) -> 632 | AD6: =IF(ISBLANK('Résultats détaillés'!B5),"",'Résultats détaillés'!B5) -> 1.1 | AE6: =IF(ISBLANK('Résultats détaillés'!C5),"",'Résultats détaillés'!C5) -> Prendre en compte toutes les étapes de la vie des équipements et des logiciels, de leur création à leur fin de vie, pour contribuer à la transition énergétique. | AF6: =IF(ISBLANK('Résultats détaillés'!E5),"",'Résultats détaillés'!E5) -> 3 | AG6: =IF(ISBLANK('Résultats détaillés'!F5),"",'Résultats détaillés'!F5) -> 1 | AH6: =IF(ISNUMBER('Résultats détaillés'!H5),IF(AND('Résultats détaillés'!H5>=1,'Résultats détaillés'!H5<=4,MOD('Résultats détaillés'!H5,1)=0),'Résultats détaillés'!H5,0),0) -> 3 | AI6: =IF(ISBLANK('Résultats détaillés'!W5),"",'Résultats détaillés'!W5) -> Former l’équipe Achats aux critères du numérique responsable et aux labels TCO et EPEAT. Dans les prochains appels d’offres pour remplacer les serveurs, faire compter les critères environnementaux pour 15 % de la note. | AJ6: =IF(LEN(TRIM(AI6))>0,1,0) -> 1 | AK6: =IF(LEN(TRIM('Résultats détaillés'!G5))>0,1,0) -> 1 | AL6: =IF(OR(IF(LEN('Résultats détaillés'!E5)=0,FALSE,NOT(IF(ISNUMBER('Résultats détaillés'!E5),AND('Résultats détaillés'!E5>=0,'Résultats détaillés'!E5<=3,MOD('Résultats détaillés'!E5,1)=0),FALSE))),IF(LEN('Résultats détaillés'!F5)=0,FALSE,NOT(IF(ISNUMBER('Résultats détaillés'!F5),AND('Résultats détaillés'!F5>=1,'Résultats détaillés'!F5<=4,MOD('Résultats détaillés'!F5,1)=0),FALSE))),IF(LEN('Résultats détaillés'!H5)=0,FALSE,NOT(IF(ISNUMBER('Résultats détaillés'!H5),AND('Résultats détaillés'!H5>=1,'Résultats détaillés'!H5<=4,MOD('Résultats détaillés'!H5,1)=0),FALSE)))),1,0) -> 0 | AM6: =IF(AND(ISNUMBER(AB6),AB6>0,AK6=0),1,0) -> 0 | AN6: 5 | AO6: =IF(AND(ISNUMBER(AB6),AB6>0),1,0) -> 1 | AP6: =IF(AND(AC6>0,AH6=0),1,0) -> 0 | AQ6: =IF(AND(AC6>0,AJ6=0),1,0) -> 0 | AR6: =IF(ISNUMBER(AB6),1,0) -> 1
B7: Les taux d’atteinte portent sur les cibles applicables évaluées. Une action proposée ne signifie pas qu’elle a été réalisée. | AA7: 1 | AB7: =IF(ISNUMBER('Résultats détaillés'!T6),'Résultats détaillés'!T6,"") -> 4 | AC7: =IF(AND(ISNUMBER(AB7),AB7>=5),AB7*100+31,0) -> 0 | AD7: =IF(ISBLANK('Résultats détaillés'!B6),"",'Résultats détaillés'!B6) -> 1.2 | AE7: =IF(ISBLANK('Résultats détaillés'!C6),"",'Résultats détaillés'!C6) -> Utiliser les équipements plus longtemps, même après la fin de leur amortissement, c’est-à-dire la période sur laquelle leur coût est réparti dans les comptes. | AF7: =IF(ISBLANK('Résultats détaillés'!E6),"",'Résultats détaillés'!E6) -> 3 | AG7: =IF(ISBLANK('Résultats détaillés'!F6),"",'Résultats détaillés'!F6) -> 3 | AH7: =IF(ISNUMBER('Résultats détaillés'!H6),IF(AND('Résultats détaillés'!H6>=1,'Résultats détaillés'!H6<=4,MOD('Résultats détaillés'!H6,1)=0),'Résultats détaillés'!H6,0),0) -> 2 | AI7: =IF(ISBLANK('Résultats détaillés'!W6),"",'Résultats détaillés'!W6) -> Répartir le coût des équipements dans les comptes sur cinq ans au minimum : c’est la durée d’amortissement. Prévoir un stock de pièces détachées pour faciliter les réparations. Expliquer aux équipes comment garder leur ordinateur plus longtemps permet d’éviter des émissions de gaz à effet de serre. | AJ7: =IF(LEN(TRIM(AI7))>0,1,0) -> 1 | AK7: =IF(LEN(TRIM('Résultats détaillés'!G6))>0,1,0) -> 1 | AL7: =IF(OR(IF(LEN('Résultats détaillés'!E6)=0,FALSE,NOT(IF(ISNUMBER('Résultats détaillés'!E6),AND('Résultats détaillés'!E6>=0,'Résultats détaillés'!E6<=3,MOD('Résultats détaillés'!E6,1)=0),FALSE))),IF(LEN('Résultats détaillés'!F6)=0,FALSE,NOT(IF(ISNUMBER('Résultats détaillés'!F6),AND('Résultats détaillés'!F6>=1,'Résultats détaillés'!F6<=4,MOD('Résultats détaillés'!F6,1)=0),FALSE))),IF(LEN('Résultats détaillés'!H6)=0,FALSE,NOT(IF(ISNUMBER('Résultats détaillés'!H6),AND('Résultats détaillés'!H6>=1,'Résultats détaillés'!H6<=4,MOD('Résultats détaillés'!H6,1)=0),FALSE)))),1,0) -> 0 | AM7: =IF(AND(ISNUMBER(AB7),AB7>0,AK7=0),1,0) -> 0 | AN7: 6 | AO7: =IF(AND(ISNUMBER(AB7),AB7>0),1,0) -> 1 | AP7: =IF(AND(AC7>0,AH7=0),1,0) -> 0 | AQ7: =IF(AND(AC7>0,AJ7=0),1,0) -> 0 | AR7: =IF(ISNUMBER(AB7),1,0) -> 1
AA8: 1 | AB8: =IF(ISNUMBER('Résultats détaillés'!T7),'Résultats détaillés'!T7,"") -> 5 | AC8: =IF(AND(ISNUMBER(AB8),AB8>=5),AB8*100+30,0) -> 530 | AD8: =IF(ISBLANK('Résultats détaillés'!B7),"",'Résultats détaillés'!B7) -> 1.3 | AE8: =IF(ISBLANK('Résultats détaillés'!C7),"",'Résultats détaillés'!C7) -> Concevoir des services numériques qui limitent leurs effets sur l’environnement. Choisir des technologies qui contribuent aux Objectifs de développement durable (ODD). | AF8: =IF(ISBLANK('Résultats détaillés'!E7),"",'Résultats détaillés'!E7) -> 3 | AG8: =IF(ISBLANK('Résultats détaillés'!F7),"",'Résultats détaillés'!F7) -> 2 | AH8: =IF(ISNUMBER('Résultats détaillés'!H7),IF(AND('Résultats détaillés'!H7>=1,'Résultats détaillés'!H7<=4,MOD('Résultats détaillés'!H7,1)=0),'Résultats détaillés'!H7,0),0) -> 2 | AI8: =IF(ISBLANK('Résultats détaillés'!W7),"",'Résultats détaillés'!W7) -> 1. Former les équipes de conception, de développement et de gestion de projet à créer des services numériques qui limitent leurs effets sur l’environnement. 2. Ajouter des exigences environnementales aux cahiers des charges, comme limiter le poids des images et réduire les demandes envoyées aux serveurs. 3. Pour chaque nouveau projet, préciser à quels Objectifs de développement durable il contribue. | AJ8: =IF(LEN(TRIM(AI8))>0,1,0) -> 1 | AK8: =IF(LEN(TRIM('Résultats détaillés'!G7))>0,1,0) -> 1 | AL8: =IF(OR(IF(LEN('Résultats détaillés'!E7)=0,FALSE,NOT(IF(ISNUMBER('Résultats détaillés'!E7),AND('Résultats détaillés'!E7>=0,'Résultats détaillés'!E7<=3,MOD('Résultats détaillés'!E7,1)=0),FALSE))),IF(LEN('Résultats détaillés'!F7)=0,FALSE,NOT(IF(ISNUMBER('Résultats détaillés'!F7),AND('Résultats détaillés'!F7>=1,'Résultats détaillés'!F7<=4,MOD('Résultats détaillés'!F7,1)=0),FALSE))),IF(LEN('Résultats détaillés'!H7)=0,FALSE,NOT(IF(ISNUMBER('Résultats détaillés'!H7),AND('Résultats détaillés'!H7>=1,'Résultats détaillés'!H7<=4,MOD('Résultats détaillés'!H7,1)=0),FALSE)))),1,0) -> 0 | AM8: =IF(AND(ISNUMBER(AB8),AB8>0,AK8=0),1,0) -> 0 | AN8: 7 | AO8: =IF(AND(ISNUMBER(AB8),AB8>0),1,0) -> 1 | AP8: =IF(AND(AC8>0,AH8=0),1,0) -> 0 | AQ8: =IF(AND(AC8>0,AJ8=0),1,0) -> 0 | AR8: =IF(ISNUMBER(AB8),1,0) -> 1
B9: Comparaison des cinq ONR | AA9: 1 | AB9: =IF(ISNUMBER('Résultats détaillés'!T8),'Résultats détaillés'!T8,"") | AC9: =IF(AND(ISNUMBER(AB9),AB9>=5),AB9*100+29,0) -> 0 | AD9: =IF(ISBLANK('Résultats détaillés'!B8),"",'Résultats détaillés'!B8) -> 1.4 | AE9: =IF(ISBLANK('Résultats détaillés'!C8),"",'Résultats détaillés'!C8) -> Adopter des pratiques qui consomment moins de matériel, de ressources, d’énergie et de consommables, comme le papier ou l’encre. | AF9: =IF(ISBLANK('Résultats détaillés'!E8),"",'Résultats détaillés'!E8) | AG9: =IF(ISBLANK('Résultats détaillés'!F8),"",'Résultats détaillés'!F8) | AH9: =IF(ISNUMBER('Résultats détaillés'!H8),IF(AND('Résultats détaillés'!H8>=1,'Résultats détaillés'!H8<=4,MOD('Résultats détaillés'!H8,1)=0),'Résultats détaillés'!H8,0),0) -> 0 | AI9: =IF(ISBLANK('Résultats détaillés'!W8),"",'Résultats détaillés'!W8) | AJ9: =IF(LEN(TRIM(AI9))>0,1,0) -> 0 | AK9: =IF(LEN(TRIM('Résultats détaillés'!G8))>0,1,0) -> 0 | AL9: =IF(OR(IF(LEN('Résultats détaillés'!E8)=0,FALSE,NOT(IF(ISNUMBER('Résultats détaillés'!E8),AND('Résultats détaillés'!E8>=0,'Résultats détaillés'!E8<=3,MOD('Résultats détaillés'!E8,1)=0),FALSE))),IF(LEN('Résultats détaillés'!F8)=0,FALSE,NOT(IF(ISNUMBER('Résultats détaillés'!F8),AND('Résultats détaillés'!F8>=1,'Résultats détaillés'!F8<=4,MOD('Résultats détaillés'!F8,1)=0),FALSE))),IF(LEN('Résultats détaillés'!H8)=0,FALSE,NOT(IF(ISNUMBER('Résultats détaillés'!H8),AND('Résultats détaillés'!H8>=1,'Résultats détaillés'!H8<=4,MOD('Résultats détaillés'!H8,1)=0),FALSE)))),1,0) -> 0 | AM9: =IF(AND(ISNUMBER(AB9),AB9>0,AK9=0),1,0) -> 0 | AN9: 8 | AO9: =IF(AND(ISNUMBER(AB9),AB9>0),1,0) -> 0 | AP9: =IF(AND(AC9>0,AH9=0),1,0) -> 0 | AQ9: =IF(AND(AC9>0,AJ9=0),1,0) -> 0 | AR9: =IF(ISNUMBER(AB9),1,0) -> 0
B10: ONR | C10: Total | D10: Évaluées | E10: À évaluer | F10: Part évaluée | G10: Applicables évaluées | H10: Urgentes | I10: Prioritaires | J10: Part atteinte | K10: Priorités avec action | L10: Priorités sans action | M10: Part prioritaire | AA10: 1 | AB10: =IF(ISNUMBER('Résultats détaillés'!T9),'Résultats détaillés'!T9,"") | AC10: =IF(AND(ISNUMBER(AB10),AB10>=5),AB10*100+28,0) -> 0 | AD10: =IF(ISBLANK('Résultats détaillés'!B9),"",'Résultats détaillés'!B9) -> 1.5 | AE10: =IF(ISBLANK('Résultats détaillés'!C9),"",'Résultats détaillés'!C9) -> Réutiliser ou recycler les déchets pour en faire de nouvelles ressources. Soutenir les emplois liés à leur traitement et à l’économie circulaire. | AF10: =IF(ISBLANK('Résultats détaillés'!E9),"",'Résultats détaillés'!E9) | AG10: =IF(ISBLANK('Résultats détaillés'!F9),"",'Résultats détaillés'!F9) | AH10: =IF(ISNUMBER('Résultats détaillés'!H9),IF(AND('Résultats détaillés'!H9>=1,'Résultats détaillés'!H9<=4,MOD('Résultats détaillés'!H9,1)=0),'Résultats détaillés'!H9,0),0) -> 0 | AI10: =IF(ISBLANK('Résultats détaillés'!W9),"",'Résultats détaillés'!W9) | AJ10: =IF(LEN(TRIM(AI10))>0,1,0) -> 0 | AK10: =IF(LEN(TRIM('Résultats détaillés'!G9))>0,1,0) -> 0 | AL10: =IF(OR(IF(LEN('Résultats détaillés'!E9)=0,FALSE,NOT(IF(ISNUMBER('Résultats détaillés'!E9),AND('Résultats détaillés'!E9>=0,'Résultats détaillés'!E9<=3,MOD('Résultats détaillés'!E9,1)=0),FALSE))),IF(LEN('Résultats détaillés'!F9)=0,FALSE,NOT(IF(ISNUMBER('Résultats détaillés'!F9),AND('Résultats détaillés'!F9>=1,'Résultats détaillés'!F9<=4,MOD('Résultats détaillés'!F9,1)=0),FALSE))),IF(LEN('Résultats détaillés'!H9)=0,FALSE,NOT(IF(ISNUMBER('Résultats détaillés'!H9),AND('Résultats détaillés'!H9>=1,'Résultats détaillés'!H9<=4,MOD('Résultats détaillés'!H9,1)=0),FALSE)))),1,0) -> 0 | AM10: =IF(AND(ISNUMBER(AB10),AB10>0,AK10=0),1,0) -> 0 | AN10: 9 | AO10: =IF(AND(ISNUMBER(AB10),AB10>0),1,0) -> 0 | AP10: =IF(AND(AC10>0,AH10=0),1,0) -> 0 | AQ10: =IF(AND(AC10>0,AJ10=0),1,0) -> 0 | AR10: =IF(ISNUMBER(AB10),1,0) -> 0
B11: 1. Sobriété | C11: ='Résultats détaillés'!AC4 -> 8 | D11: ='Résultats détaillés'!AD4 -> 5 | E11: =C11-D11 -> 3 | F11: =D11/C11 -> 0.625 | G11: =SUMIFS($AO$6:$AO$37,$AA$6:$AA$37,1) -> 5 | H11: ='Résultats détaillés'!AF4 -> 3 | I11: ='Résultats détaillés'!AG4 -> 1 | J11: =IF(G11=0,"",COUNTIFS($AA$6:$AA$37,1,$AO$6:$AO$37,1,$AG$6:$AG$37,4)/G11) -> 0 | K11: =IF(H11+I11=0,"",SUMIFS($AJ$6:$AJ$37,$AA$6:$AA$37,1,$AC$6:$AC$37,">0")/(H11+I11)) -> 1 | L11: =SUMIFS($AQ$6:$AQ$37,$AA$6:$AA$37,1) -> 0 | M11: =IF(G11=0,"",(H11+I11)/G11) -> 0.8 | AA11: 1 | AB11: =IF(ISNUMBER('Résultats détaillés'!T10),'Résultats détaillés'!T10,"") | AC11: =IF(AND(ISNUMBER(AB11),AB11>=5),AB11*100+27,0) -> 0 | AD11: =IF(ISBLANK('Résultats détaillés'!B10),"",'Résultats détaillés'!B10) -> 1.6 | AE11: =IF(ISBLANK('Résultats détaillés'!C10),"",'Résultats détaillés'!C10) -> Choisir des énergies renouvelables et encourager leur utilisation. | AF11: =IF(ISBLANK('Résultats détaillés'!E10),"",'Résultats détaillés'!E10) | AG11: =IF(ISBLANK('Résultats détaillés'!F10),"",'Résultats détaillés'!F10) | AH11: =IF(ISNUMBER('Résultats détaillés'!H10),IF(AND('Résultats détaillés'!H10>=1,'Résultats détaillés'!H10<=4,MOD('Résultats détaillés'!H10,1)=0),'Résultats détaillés'!H10,0),0) -> 0 | AI11: =IF(ISBLANK('Résultats détaillés'!W10),"",'Résultats détaillés'!W10) | AJ11: =IF(LEN(TRIM(AI11))>0,1,0) -> 0 | AK11: =IF(LEN(TRIM('Résultats détaillés'!G10))>0,1,0) -> 0 | AL11: =IF(OR(IF(LEN('Résultats détaillés'!E10)=0,FALSE,NOT(IF(ISNUMBER('Résultats détaillés'!E10),AND('Résultats détaillés'!E10>=0,'Résultats détaillés'!E10<=3,MOD('Résultats détaillés'!E10,1)=0),FALSE))),IF(LEN('Résultats détaillés'!F10)=0,FALSE,NOT(IF(ISNUMBER('Résultats détaillés'!F10),AND('Résultats détaillés'!F10>=1,'Résultats détaillés'!F10<=4,MOD('Résultats détaillés'!F10,1)=0),FALSE))),IF(LEN('Résultats détaillés'!H10)=0,FALSE,NOT(IF(ISNUMBER('Résultats détaillés'!H10),AND('Résultats détaillés'!H10>=1,'Résultats détaillés'!H10<=4,MOD('Résultats détaillés'!H10,1)=0),FALSE)))),1,0) -> 0 | AM11: =IF(AND(ISNUMBER(AB11),AB11>0,AK11=0),1,0) -> 0 | AN11: 10 | AO11: =IF(AND(ISNUMBER(AB11),AB11>0),1,0) -> 0 | AP11: =IF(AND(AC11>0,AH11=0),1,0) -> 0 | AQ11: =IF(AND(AC11>0,AJ11=0),1,0) -> 0 | AR11: =IF(ISNUMBER(AB11),1,0) -> 0
B12: 2. Inclusion | C12: ='Résultats détaillés'!AC13 -> 5 | D12: ='Résultats détaillés'!AD13 -> 0 | E12: =C12-D12 -> 5 | F12: =D12/C12 -> 0 | G12: =SUMIFS($AO$6:$AO$37,$AA$6:$AA$37,2) -> 0 | H12: ='Résultats détaillés'!AF13 -> 0 | I12: ='Résultats détaillés'!AG13 -> 0 | J12: =IF(G12=0,"",COUNTIFS($AA$6:$AA$37,2,$AO$6:$AO$37,1,$AG$6:$AG$37,4)/G12) | K12: =IF(H12+I12=0,"",SUMIFS($AJ$6:$AJ$37,$AA$6:$AA$37,2,$AC$6:$AC$37,">0")/(H12+I12)) | L12: =SUMIFS($AQ$6:$AQ$37,$AA$6:$AA$37,2) -> 0 | M12: =IF(G12=0,"",(H12+I12)/G12) | AA12: 1 | AB12: =IF(ISNUMBER('Résultats détaillés'!T11),'Résultats détaillés'!T11,"") -> 6 | AC12: =IF(AND(ISNUMBER(AB12),AB12>=5),AB12*100+26,0) -> 626 | AD12: =IF(ISBLANK('Résultats détaillés'!B11),"",'Résultats détaillés'!B11) -> 1.7 | AE12: =IF(ISBLANK('Résultats détaillés'!C11),"",'Résultats détaillés'!C11) -> Réserver l’intelligence artificielle aux besoins qui la justifient et privilégier des solutions sobres en ressources. | AF12: =IF(ISBLANK('Résultats détaillés'!E11),"",'Résultats détaillés'!E11) -> 3 | AG12: =IF(ISBLANK('Résultats détaillés'!F11),"",'Résultats détaillés'!F11) -> 1 | AH12: =IF(ISNUMBER('Résultats détaillés'!H11),IF(AND('Résultats détaillés'!H11>=1,'Résultats détaillés'!H11<=4,MOD('Résultats détaillés'!H11,1)=0),'Résultats détaillés'!H11,0),0) -> 2 | AI12: =IF(ISBLANK('Résultats détaillés'!W11),"",'Résultats détaillés'!W11) -> 1. Vérifier le besoin avant chaque projet : faut-il de l’IA ou un outil informatique classique suffit-il ? 2. Choisir de petits modèles spécialisés quand ils répondent au besoin. 3. Former les développeurs et les spécialistes des données à réduire la consommation de l’IA, en améliorant le code et en évitant les calculs répétés. | AJ12: =IF(LEN(TRIM(AI12))>0,1,0) -> 1 | AK12: =IF(LEN(TRIM('Résultats détaillés'!G11))>0,1,0) -> 1 | AL12: =IF(OR(IF(LEN('Résultats détaillés'!E11)=0,FALSE,NOT(IF(ISNUMBER('Résultats détaillés'!E11),AND('Résultats détaillés'!E11>=0,'Résultats détaillés'!E11<=3,MOD('Résultats détaillés'!E11,1)=0),FALSE))),IF(LEN('Résultats détaillés'!F11)=0,FALSE,NOT(IF(ISNUMBER('Résultats détaillés'!F11),AND('Résultats détaillés'!F11>=1,'Résultats détaillés'!F11<=4,MOD('Résultats détaillés'!F11,1)=0),FALSE))),IF(LEN('Résultats détaillés'!H11)=0,FALSE,NOT(IF(ISNUMBER('Résultats détaillés'!H11),AND('Résultats détaillés'!H11>=1,'Résultats détaillés'!H11<=4,MOD('Résultats détaillés'!H11,1)=0),FALSE)))),1,0) -> 0 | AM12: =IF(AND(ISNUMBER(AB12),AB12>0,AK12=0),1,0) -> 0 | AN12: 11 | AO12: =IF(AND(ISNUMBER(AB12),AB12>0),1,0) -> 1 | AP12: =IF(AND(AC12>0,AH12=0),1,0) -> 0 | AQ12: =IF(AND(AC12>0,AJ12=0),1,0) -> 0 | AR12: =IF(ISNUMBER(AB12),1,0) -> 1
B13: 3. RSE et éthique | C13: ='Résultats détaillés'!AC19 -> 8 | D13: ='Résultats détaillés'!AD19 -> 0 | E13: =C13-D13 -> 8 | F13: =D13/C13 -> 0 | G13: =SUMIFS($AO$6:$AO$37,$AA$6:$AA$37,3) -> 0 | H13: ='Résultats détaillés'!AF19 -> 0 | I13: ='Résultats détaillés'!AG19 -> 0 | J13: =IF(G13=0,"",COUNTIFS($AA$6:$AA$37,3,$AO$6:$AO$37,1,$AG$6:$AG$37,4)/G13) | K13: =IF(H13+I13=0,"",SUMIFS($AJ$6:$AJ$37,$AA$6:$AA$37,3,$AC$6:$AC$37,">0")/(H13+I13)) | L13: =SUMIFS($AQ$6:$AQ$37,$AA$6:$AA$37,3) -> 0 | M13: =IF(G13=0,"",(H13+I13)/G13) | AA13: 1 | AB13: =IF(ISNUMBER('Résultats détaillés'!T12),'Résultats détaillés'!T12,"") -> 6 | AC13: =IF(AND(ISNUMBER(AB13),AB13>=5),AB13*100+25,0) -> 625 | AD13: =IF(ISBLANK('Résultats détaillés'!B12),"",'Résultats détaillés'!B12) -> 1.8 | AE13: =IF(ISBLANK('Résultats détaillés'!C12),"",'Résultats détaillés'!C12) -> Mesurer et réduire ce que consomme l’intelligence artificielle, pendant son entraînement comme pendant son utilisation. | AF13: =IF(ISBLANK('Résultats détaillés'!E12),"",'Résultats détaillés'!E12) -> 3 | AG13: =IF(ISBLANK('Résultats détaillés'!F12),"",'Résultats détaillés'!F12) -> 1 | AH13: =IF(ISNUMBER('Résultats détaillés'!H12),IF(AND('Résultats détaillés'!H12>=1,'Résultats détaillés'!H12<=4,MOD('Résultats détaillés'!H12,1)=0),'Résultats détaillés'!H12,0),0) -> 2 | AI13: =IF(ISBLANK('Résultats détaillés'!W12),"",'Résultats détaillés'!W12) -> 1. Vérifier le besoin avant chaque projet : faut-il de l’IA ou un outil informatique classique suffit-il ? 2. Choisir de petits modèles spécialisés quand ils répondent au besoin. 3. Former les développeurs et les spécialistes des données à réduire la consommation de l’IA, en améliorant le code et en évitant les calculs répétés. | AJ13: =IF(LEN(TRIM(AI13))>0,1,0) -> 1 | AK13: =IF(LEN(TRIM('Résultats détaillés'!G12))>0,1,0) -> 1 | AL13: =IF(OR(IF(LEN('Résultats détaillés'!E12)=0,FALSE,NOT(IF(ISNUMBER('Résultats détaillés'!E12),AND('Résultats détaillés'!E12>=0,'Résultats détaillés'!E12<=3,MOD('Résultats détaillés'!E12,1)=0),FALSE))),IF(LEN('Résultats détaillés'!F12)=0,FALSE,NOT(IF(ISNUMBER('Résultats détaillés'!F12),AND('Résultats détaillés'!F12>=1,'Résultats détaillés'!F12<=4,MOD('Résultats détaillés'!F12,1)=0),FALSE))),IF(LEN('Résultats détaillés'!H12)=0,FALSE,NOT(IF(ISNUMBER('Résultats détaillés'!H12),AND('Résultats détaillés'!H12>=1,'Résultats détaillés'!H12<=4,MOD('Résultats détaillés'!H12,1)=0),FALSE)))),1,0) -> 0 | AM13: =IF(AND(ISNUMBER(AB13),AB13>0,AK13=0),1,0) -> 0 | AN13: 12 | AO13: =IF(AND(ISNUMBER(AB13),AB13>0),1,0) -> 1 | AP13: =IF(AND(AC13>0,AH13=0),1,0) -> 0 | AQ13: =IF(AND(AC13>0,AJ13=0),1,0) -> 0 | AR13: =IF(ISNUMBER(AB13),1,0) -> 1
B14: 4. Résilience | C14: ='Résultats détaillés'!AC28 -> 4 | D14: ='Résultats détaillés'!AD28 -> 0 | E14: =C14-D14 -> 4 | F14: =D14/C14 -> 0 | G14: =SUMIFS($AO$6:$AO$37,$AA$6:$AA$37,4) -> 0 | H14: ='Résultats détaillés'!AF28 -> 0 | I14: ='Résultats détaillés'!AG28 -> 0 | J14: =IF(G14=0,"",COUNTIFS($AA$6:$AA$37,4,$AO$6:$AO$37,1,$AG$6:$AG$37,4)/G14) | K14: =IF(H14+I14=0,"",SUMIFS($AJ$6:$AJ$37,$AA$6:$AA$37,4,$AC$6:$AC$37,">0")/(H14+I14)) | L14: =SUMIFS($AQ$6:$AQ$37,$AA$6:$AA$37,4) -> 0 | M14: =IF(G14=0,"",(H14+I14)/G14) | AA14: 2 | AB14: =IF(ISNUMBER('Résultats détaillés'!T14),'Résultats détaillés'!T14,"") | AC14: =IF(AND(ISNUMBER(AB14),AB14>=5),AB14*100+24,0) -> 0 | AD14: =IF(ISBLANK('Résultats détaillés'!B14),"",'Résultats détaillés'!B14) -> 2.1 | AE14: =IF(ISBLANK('Résultats détaillés'!C14),"",'Résultats détaillés'!C14) -> Intégrer dans tous les achats des exigences qui tiennent compte de leurs effets sur la société et l’environnement. | AF14: =IF(ISBLANK('Résultats détaillés'!E14),"",'Résultats détaillés'!E14) | AG14: =IF(ISBLANK('Résultats détaillés'!F14),"",'Résultats détaillés'!F14) | AH14: =IF(ISNUMBER('Résultats détaillés'!H14),IF(AND('Résultats détaillés'!H14>=1,'Résultats détaillés'!H14<=4,MOD('Résultats détaillés'!H14,1)=0),'Résultats détaillés'!H14,0),0) -> 0 | AI14: =IF(ISBLANK('Résultats détaillés'!W14),"",'Résultats détaillés'!W14) | AJ14: =IF(LEN(TRIM(AI14))>0,1,0) -> 0 | AK14: =IF(LEN(TRIM('Résultats détaillés'!G14))>0,1,0) -> 0 | AL14: =IF(OR(IF(LEN('Résultats détaillés'!E14)=0,FALSE,NOT(IF(ISNUMBER('Résultats détaillés'!E14),AND('Résultats détaillés'!E14>=0,'Résultats détaillés'!E14<=3,MOD('Résultats détaillés'!E14,1)=0),FALSE))),IF(LEN('Résultats détaillés'!F14)=0,FALSE,NOT(IF(ISNUMBER('Résultats détaillés'!F14),AND('Résultats détaillés'!F14>=1,'Résultats détaillés'!F14<=4,MOD('Résultats détaillés'!F14,1)=0),FALSE))),IF(LEN('Résultats détaillés'!H14)=0,FALSE,NOT(IF(ISNUMBER('Résultats détaillés'!H14),AND('Résultats détaillés'!H14>=1,'Résultats détaillés'!H14<=4,MOD('Résultats détaillés'!H14,1)=0),FALSE)))),1,0) -> 0 | AM14: =IF(AND(ISNUMBER(AB14),AB14>0,AK14=0),1,0) -> 0 | AN14: 14 | AO14: =IF(AND(ISNUMBER(AB14),AB14>0),1,0) -> 0 | AP14: =IF(AND(AC14>0,AH14=0),1,0) -> 0 | AQ14: =IF(AND(AC14>0,AJ14=0),1,0) -> 0 | AR14: =IF(ISNUMBER(AB14),1,0) -> 0
B15: 5. Management | C15: ='Résultats détaillés'!AC33 -> 7 | D15: ='Résultats détaillés'!AD33 -> 0 | E15: =C15-D15 -> 7 | F15: =D15/C15 -> 0 | G15: =SUMIFS($AO$6:$AO$37,$AA$6:$AA$37,5) -> 0 | H15: ='Résultats détaillés'!AF33 -> 0 | I15: ='Résultats détaillés'!AG33 -> 0 | J15: =IF(G15=0,"",COUNTIFS($AA$6:$AA$37,5,$AO$6:$AO$37,1,$AG$6:$AG$37,4)/G15) | K15: =IF(H15+I15=0,"",SUMIFS($AJ$6:$AJ$37,$AA$6:$AA$37,5,$AC$6:$AC$37,">0")/(H15+I15)) | L15: =SUMIFS($AQ$6:$AQ$37,$AA$6:$AA$37,5) -> 0 | M15: =IF(G15=0,"",(H15+I15)/G15) | AA15: 2 | AB15: =IF(ISNUMBER('Résultats détaillés'!T15),'Résultats détaillés'!T15,"") | AC15: =IF(AND(ISNUMBER(AB15),AB15>=5),AB15*100+23,0) -> 0 | AD15: =IF(ISBLANK('Résultats détaillés'!B15),"",'Résultats détaillés'!B15) -> 2.2 | AE15: =IF(ISBLANK('Résultats détaillés'!C15),"",'Résultats détaillés'!C15) -> Rendre les services numériques accessibles à toutes et tous. Mesurer leur respect du RGAA, le référentiel français sur l’accessibilité numérique. | AF15: =IF(ISBLANK('Résultats détaillés'!E15),"",'Résultats détaillés'!E15) | AG15: =IF(ISBLANK('Résultats détaillés'!F15),"",'Résultats détaillés'!F15) | AH15: =IF(ISNUMBER('Résultats détaillés'!H15),IF(AND('Résultats détaillés'!H15>=1,'Résultats détaillés'!H15<=4,MOD('Résultats détaillés'!H15,1)=0),'Résultats détaillés'!H15,0),0) -> 0 | AI15: =IF(ISBLANK('Résultats détaillés'!W15),"",'Résultats détaillés'!W15) | AJ15: =IF(LEN(TRIM(AI15))>0,1,0) -> 0 | AK15: =IF(LEN(TRIM('Résultats détaillés'!G15))>0,1,0) -> 0 | AL15: =IF(OR(IF(LEN('Résultats détaillés'!E15)=0,FALSE,NOT(IF(ISNUMBER('Résultats détaillés'!E15),AND('Résultats détaillés'!E15>=0,'Résultats détaillés'!E15<=3,MOD('Résultats détaillés'!E15,1)=0),FALSE))),IF(LEN('Résultats détaillés'!F15)=0,FALSE,NOT(IF(ISNUMBER('Résultats détaillés'!F15),AND('Résultats détaillés'!F15>=1,'Résultats détaillés'!F15<=4,MOD('Résultats détaillés'!F15,1)=0),FALSE))),IF(LEN('Résultats détaillés'!H15)=0,FALSE,NOT(IF(ISNUMBER('Résultats détaillés'!H15),AND('Résultats détaillés'!H15>=1,'Résultats détaillés'!H15<=4,MOD('Résultats détaillés'!H15,1)=0),FALSE)))),1,0) -> 0 | AM15: =IF(AND(ISNUMBER(AB15),AB15>0,AK15=0),1,0) -> 0 | AN15: 15 | AO15: =IF(AND(ISNUMBER(AB15),AB15>0),1,0) -> 0 | AP15: =IF(AND(AC15>0,AH15=0),1,0) -> 0 | AQ15: =IF(AND(AC15>0,AJ15=0),1,0) -> 0 | AR15: =IF(ISNUMBER(AB15),1,0) -> 0
B16: TOTAL | C16: =SUM(C11:C15) -> 32 | D16: =SUM(D11:D15) -> 5 | E16: =SUM(E11:E15) -> 27 | F16: =D16/C16 -> 0.15625 | G16: =SUM(G11:G15) -> 5 | H16: =SUM(H11:H15) -> 3 | I16: =SUM(I11:I15) -> 1 | J16: =IF(G16=0,"",COUNTIFS($AO$6:$AO$37,1,$AG$6:$AG$37,4)/G16) -> 0 | K16: =IF(H16+I16=0,"",SUMIFS($AJ$6:$AJ$37,$AC$6:$AC$37,">0")/(H16+I16)) -> 1 | L16: =SUM(L11:L15) -> 0 | M16: =IF(G16=0,"",(H16+I16)/G16) -> 0.8 | AA16: 2 | AB16: =IF(ISNUMBER('Résultats détaillés'!T16),'Résultats détaillés'!T16,"") | AC16: =IF(AND(ISNUMBER(AB16),AB16>=5),AB16*100+22,0) -> 0 | AD16: =IF(ISBLANK('Résultats détaillés'!B16),"",'Résultats détaillés'!B16) -> 2.3 | AE16: =IF(ISBLANK('Résultats détaillés'!C16),"",'Résultats détaillés'!C16) -> Créer des applications utiles, faciles à utiliser et réellement utilisées : les « 3 U ». Les rendre accessibles pour permettre à chacun d’utiliser le numérique. | AF16: =IF(ISBLANK('Résultats détaillés'!E16),"",'Résultats détaillés'!E16) | AG16: =IF(ISBLANK('Résultats détaillés'!F16),"",'Résultats détaillés'!F16) | AH16: =IF(ISNUMBER('Résultats détaillés'!H16),IF(AND('Résultats détaillés'!H16>=1,'Résultats détaillés'!H16<=4,MOD('Résultats détaillés'!H16,1)=0),'Résultats détaillés'!H16,0),0) -> 0 | AI16: =IF(ISBLANK('Résultats détaillés'!W16),"",'Résultats détaillés'!W16) | AJ16: =IF(LEN(TRIM(AI16))>0,1,0) -> 0 | AK16: =IF(LEN(TRIM('Résultats détaillés'!G16))>0,1,0) -> 0 | AL16: =IF(OR(IF(LEN('Résultats détaillés'!E16)=0,FALSE,NOT(IF(ISNUMBER('Résultats détaillés'!E16),AND('Résultats détaillés'!E16>=0,'Résultats détaillés'!E16<=3,MOD('Résultats détaillés'!E16,1)=0),FALSE))),IF(LEN('Résultats détaillés'!F16)=0,FALSE,NOT(IF(ISNUMBER('Résultats détaillés'!F16),AND('Résultats détaillés'!F16>=1,'Résultats détaillés'!F16<=4,MOD('Résultats détaillés'!F16,1)=0),FALSE))),IF(LEN('Résultats détaillés'!H16)=0,FALSE,NOT(IF(ISNUMBER('Résultats détaillés'!H16),AND('Résultats détaillés'!H16>=1,'Résultats détaillés'!H16<=4,MOD('Résultats détaillés'!H16,1)=0),FALSE)))),1,0) -> 0 | AM16: =IF(AND(ISNUMBER(AB16),AB16>0,AK16=0),1,0) -> 0 | AN16: 16 | AO16: =IF(AND(ISNUMBER(AB16),AB16>0),1,0) -> 0 | AP16: =IF(AND(AC16>0,AH16=0),1,0) -> 0 | AQ16: =IF(AND(AC16>0,AJ16=0),1,0) -> 0 | AR16: =IF(ISNUMBER(AB16),1,0) -> 0
AA17: 2 | AB17: =IF(ISNUMBER('Résultats détaillés'!T17),'Résultats détaillés'!T17,"") | AC17: =IF(AND(ISNUMBER(AB17),AB17>=5),AB17*100+21,0) -> 0 | AD17: =IF(ISBLANK('Résultats détaillés'!B17),"",'Résultats détaillés'!B17) -> 2.4 | AE17: =IF(ISBLANK('Résultats détaillés'!C17),"",'Résultats détaillés'!C17) -> Concevoir les services avec leurs utilisateurs et utilisatrices, en se concentrant sur leurs besoins réels. | AF17: =IF(ISBLANK('Résultats détaillés'!E17),"",'Résultats détaillés'!E17) | AG17: =IF(ISBLANK('Résultats détaillés'!F17),"",'Résultats détaillés'!F17) | AH17: =IF(ISNUMBER('Résultats détaillés'!H17),IF(AND('Résultats détaillés'!H17>=1,'Résultats détaillés'!H17<=4,MOD('Résultats détaillés'!H17,1)=0),'Résultats détaillés'!H17,0),0) -> 0 | AI17: =IF(ISBLANK('Résultats détaillés'!W17),"",'Résultats détaillés'!W17) | AJ17: =IF(LEN(TRIM(AI17))>0,1,0) -> 0 | AK17: =IF(LEN(TRIM('Résultats détaillés'!G17))>0,1,0) -> 0 | AL17: =IF(OR(IF(LEN('Résultats détaillés'!E17)=0,FALSE,NOT(IF(ISNUMBER('Résultats détaillés'!E17),AND('Résultats détaillés'!E17>=0,'Résultats détaillés'!E17<=3,MOD('Résultats détaillés'!E17,1)=0),FALSE))),IF(LEN('Résultats détaillés'!F17)=0,FALSE,NOT(IF(ISNUMBER('Résultats détaillés'!F17),AND('Résultats détaillés'!F17>=1,'Résultats détaillés'!F17<=4,MOD('Résultats détaillés'!F17,1)=0),FALSE))),IF(LEN('Résultats détaillés'!H17)=0,FALSE,NOT(IF(ISNUMBER('Résultats détaillés'!H17),AND('Résultats détaillés'!H17>=1,'Résultats détaillés'!H17<=4,MOD('Résultats détaillés'!H17,1)=0),FALSE)))),1,0) -> 0 | AM17: =IF(AND(ISNUMBER(AB17),AB17>0,AK17=0),1,0) -> 0 | AN17: 17 | AO17: =IF(AND(ISNUMBER(AB17),AB17>0),1,0) -> 0 | AP17: =IF(AND(AC17>0,AH17=0),1,0) -> 0 | AQ17: =IF(AND(AC17>0,AJ17=0),1,0) -> 0 | AR17: =IF(ISNUMBER(AB17),1,0) -> 0
B18: Part prioritaire = urgentes + prioritaires / applicables évaluées. « Avec action » = une proposition écrite pour ces priorités. | AA18: 2 | AB18: =IF(ISNUMBER('Résultats détaillés'!T18),'Résultats détaillés'!T18,"") | AC18: =IF(AND(ISNUMBER(AB18),AB18>=5),AB18*100+20,0) -> 0 | AD18: =IF(ISBLANK('Résultats détaillés'!B18),"",'Résultats détaillés'!B18) -> 2.5 | AE18: =IF(ISBLANK('Résultats détaillés'!C18),"",'Résultats détaillés'!C18) -> Vérifier que l’intelligence artificielle ne discrimine personne et que ses services peuvent être utilisés par toutes et tous. | AF18: =IF(ISBLANK('Résultats détaillés'!E18),"",'Résultats détaillés'!E18) | AG18: =IF(ISBLANK('Résultats détaillés'!F18),"",'Résultats détaillés'!F18) | AH18: =IF(ISNUMBER('Résultats détaillés'!H18),IF(AND('Résultats détaillés'!H18>=1,'Résultats détaillés'!H18<=4,MOD('Résultats détaillés'!H18,1)=0),'Résultats détaillés'!H18,0),0) -> 0 | AI18: =IF(ISBLANK('Résultats détaillés'!W18),"",'Résultats détaillés'!W18) | AJ18: =IF(LEN(TRIM(AI18))>0,1,0) -> 0 | AK18: =IF(LEN(TRIM('Résultats détaillés'!G18))>0,1,0) -> 0 | AL18: =IF(OR(IF(LEN('Résultats détaillés'!E18)=0,FALSE,NOT(IF(ISNUMBER('Résultats détaillés'!E18),AND('Résultats détaillés'!E18>=0,'Résultats détaillés'!E18<=3,MOD('Résultats détaillés'!E18,1)=0),FALSE))),IF(LEN('Résultats détaillés'!F18)=0,FALSE,NOT(IF(ISNUMBER('Résultats détaillés'!F18),AND('Résultats détaillés'!F18>=1,'Résultats détaillés'!F18<=4,MOD('Résultats détaillés'!F18,1)=0),FALSE))),IF(LEN('Résultats détaillés'!H18)=0,FALSE,NOT(IF(ISNUMBER('Résultats détaillés'!H18),AND('Résultats détaillés'!H18>=1,'Résultats détaillés'!H18<=4,MOD('Résultats détaillés'!H18,1)=0),FALSE)))),1,0) -> 0 | AM18: =IF(AND(ISNUMBER(AB18),AB18>0,AK18=0),1,0) -> 0 | AN18: 18 | AO18: =IF(AND(ISNUMBER(AB18),AB18>0),1,0) -> 0 | AP18: =IF(AND(AC18>0,AH18=0),1,0) -> 0 | AQ18: =IF(AND(AC18>0,AJ18=0),1,0) -> 0 | AR18: =IF(ISNUMBER(AB18),1,0) -> 0
B19: =IF(D16=0,"Commencer par renseigner les notes dans les onglets ONR.",E16&" cibles restent à évaluer. "&(D16-G16)&" sont non applicables. Les résultats portent sur "&G16&" cibles applicables évaluées.") -> 27 cibles restent à évaluer. 0 sont non applicables. Les résultats portent sur 5 cibles applicables évaluées. | AA19: 3 | AB19: =IF(ISNUMBER('Résultats détaillés'!T20),'Résultats détaillés'!T20,"") | AC19: =IF(AND(ISNUMBER(AB19),AB19>=5),AB19*100+19,0) -> 0 | AD19: =IF(ISBLANK('Résultats détaillés'!B20),"",'Résultats détaillés'!B20) -> 3.1 | AE19: =IF(ISBLANK('Résultats détaillés'!C20),"",'Résultats détaillés'!C20) -> Utiliser les données et les services numériques avec mesure, en respectant les personnes et l’environnement. | AF19: =IF(ISBLANK('Résultats détaillés'!E20),"",'Résultats détaillés'!E20) | AG19: =IF(ISBLANK('Résultats détaillés'!F20),"",'Résultats détaillés'!F20) | AH19: =IF(ISNUMBER('Résultats détaillés'!H20),IF(AND('Résultats détaillés'!H20>=1,'Résultats détaillés'!H20<=4,MOD('Résultats détaillés'!H20,1)=0),'Résultats détaillés'!H20,0),0) -> 0 | AI19: =IF(ISBLANK('Résultats détaillés'!W20),"",'Résultats détaillés'!W20) | AJ19: =IF(LEN(TRIM(AI19))>0,1,0) -> 0 | AK19: =IF(LEN(TRIM('Résultats détaillés'!G20))>0,1,0) -> 0 | AL19: =IF(OR(IF(LEN('Résultats détaillés'!E20)=0,FALSE,NOT(IF(ISNUMBER('Résultats détaillés'!E20),AND('Résultats détaillés'!E20>=0,'Résultats détaillés'!E20<=3,MOD('Résultats détaillés'!E20,1)=0),FALSE))),IF(LEN('Résultats détaillés'!F20)=0,FALSE,NOT(IF(ISNUMBER('Résultats détaillés'!F20),AND('Résultats détaillés'!F20>=1,'Résultats détaillés'!F20<=4,MOD('Résultats détaillés'!F20,1)=0),FALSE))),IF(LEN('Résultats détaillés'!H20)=0,FALSE,NOT(IF(ISNUMBER('Résultats détaillés'!H20),AND('Résultats détaillés'!H20>=1,'Résultats détaillés'!H20<=4,MOD('Résultats détaillés'!H20,1)=0),FALSE)))),1,0) -> 0 | AM19: =IF(AND(ISNUMBER(AB19),AB19>0,AK19=0),1,0) -> 0 | AN19: 20 | AO19: =IF(AND(ISNUMBER(AB19),AB19>0),1,0) -> 0 | AP19: =IF(AND(AC19>0,AH19=0),1,0) -> 0 | AQ19: =IF(AND(AC19>0,AJ19=0),1,0) -> 0 | AR19: =IF(ISNUMBER(AB19),1,0) -> 0
AA20: 3 | AB20: =IF(ISNUMBER('Résultats détaillés'!T21),'Résultats détaillés'!T21,"") | AC20: =IF(AND(ISNUMBER(AB20),AB20>=5),AB20*100+18,0) -> 0 | AD20: =IF(ISBLANK('Résultats détaillés'!B21),"",'Résultats détaillés'!B21) -> 3.2 | AE20: =IF(ISBLANK('Résultats détaillés'!C21),"",'Résultats détaillés'!C21) -> Supprimer les pratiques et les interfaces qui trompent les utilisateurs sur les sites web, aussi appelées « dark patterns ». Respecter la réglementation. | AF20: =IF(ISBLANK('Résultats détaillés'!E21),"",'Résultats détaillés'!E21) | AG20: =IF(ISBLANK('Résultats détaillés'!F21),"",'Résultats détaillés'!F21) | AH20: =IF(ISNUMBER('Résultats détaillés'!H21),IF(AND('Résultats détaillés'!H21>=1,'Résultats détaillés'!H21<=4,MOD('Résultats détaillés'!H21,1)=0),'Résultats détaillés'!H21,0),0) -> 0 | AI20: =IF(ISBLANK('Résultats détaillés'!W21),"",'Résultats détaillés'!W21) | AJ20: =IF(LEN(TRIM(AI20))>0,1,0) -> 0 | AK20: =IF(LEN(TRIM('Résultats détaillés'!G21))>0,1,0) -> 0 | AL20: =IF(OR(IF(LEN('Résultats détaillés'!E21)=0,FALSE,NOT(IF(ISNUMBER('Résultats détaillés'!E21),AND('Résultats détaillés'!E21>=0,'Résultats détaillés'!E21<=3,MOD('Résultats détaillés'!E21,1)=0),FALSE))),IF(LEN('Résultats détaillés'!F21)=0,FALSE,NOT(IF(ISNUMBER('Résultats détaillés'!F21),AND('Résultats détaillés'!F21>=1,'Résultats détaillés'!F21<=4,MOD('Résultats détaillés'!F21,1)=0),FALSE))),IF(LEN('Résultats détaillés'!H21)=0,FALSE,NOT(IF(ISNUMBER('Résultats détaillés'!H21),AND('Résultats détaillés'!H21>=1,'Résultats détaillés'!H21<=4,MOD('Résultats détaillés'!H21,1)=0),FALSE)))),1,0) -> 0 | AM20: =IF(AND(ISNUMBER(AB20),AB20>0,AK20=0),1,0) -> 0 | AN20: 21 | AO20: =IF(AND(ISNUMBER(AB20),AB20>0),1,0) -> 0 | AP20: =IF(AND(AC20>0,AH20=0),1,0) -> 0 | AQ20: =IF(AND(AC20>0,AJ20=0),1,0) -> 0 | AR20: =IF(ISNUMBER(AB20),1,0) -> 0
B21: Où concentrer les efforts ? | AA21: 3 | AB21: =IF(ISNUMBER('Résultats détaillés'!T22),'Résultats détaillés'!T22,"") | AC21: =IF(AND(ISNUMBER(AB21),AB21>=5),AB21*100+17,0) -> 0 | AD21: =IF(ISBLANK('Résultats détaillés'!B22),"",'Résultats détaillés'!B22) -> 3.3 | AE21: =IF(ISBLANK('Résultats détaillés'!C22),"",'Résultats détaillés'!C22) -> Collecter seulement les données nécessaires au service rendu. Protéger la vie privée, réduire les effets sur l’environnement et respecter le RGPD, le règlement sur la protection des données personnelles. | AF21: =IF(ISBLANK('Résultats détaillés'!E22),"",'Résultats détaillés'!E22) | AG21: =IF(ISBLANK('Résultats détaillés'!F22),"",'Résultats détaillés'!F22) | AH21: =IF(ISNUMBER('Résultats détaillés'!H22),IF(AND('Résultats détaillés'!H22>=1,'Résultats détaillés'!H22<=4,MOD('Résultats détaillés'!H22,1)=0),'Résultats détaillés'!H22,0),0) -> 0 | AI21: =IF(ISBLANK('Résultats détaillés'!W22),"",'Résultats détaillés'!W22) | AJ21: =IF(LEN(TRIM(AI21))>0,1,0) -> 0 | AK21: =IF(LEN(TRIM('Résultats détaillés'!G22))>0,1,0) -> 0 | AL21: =IF(OR(IF(LEN('Résultats détaillés'!E22)=0,FALSE,NOT(IF(ISNUMBER('Résultats détaillés'!E22),AND('Résultats détaillés'!E22>=0,'Résultats détaillés'!E22<=3,MOD('Résultats détaillés'!E22,1)=0),FALSE))),IF(LEN('Résultats détaillés'!F22)=0,FALSE,NOT(IF(ISNUMBER('Résultats détaillés'!F22),AND('Résultats détaillés'!F22>=1,'Résultats détaillés'!F22<=4,MOD('Résultats détaillés'!F22,1)=0),FALSE))),IF(LEN('Résultats détaillés'!H22)=0,FALSE,NOT(IF(ISNUMBER('Résultats détaillés'!H22),AND('Résultats détaillés'!H22>=1,'Résultats détaillés'!H22<=4,MOD('Résultats détaillés'!H22,1)=0),FALSE)))),1,0) -> 0 | AM21: =IF(AND(ISNUMBER(AB21),AB21>0,AK21=0),1,0) -> 0 | AN21: 22 | AO21: =IF(AND(ISNUMBER(AB21),AB21>0),1,0) -> 0 | AP21: =IF(AND(AC21>0,AH21=0),1,0) -> 0 | AQ21: =IF(AND(AC21>0,AJ21=0),1,0) -> 0 | AR21: =IF(ISNUMBER(AB21),1,0) -> 0
AA22: 3 | AB22: =IF(ISNUMBER('Résultats détaillés'!T23),'Résultats détaillés'!T23,"") | AC22: =IF(AND(ISNUMBER(AB22),AB22>=5),AB22*100+16,0) -> 0 | AD22: =IF(ISBLANK('Résultats détaillés'!B23),"",'Résultats détaillés'!B23) -> 3.4 | AE22: =IF(ISBLANK('Résultats détaillés'!C23),"",'Résultats détaillés'!C23) -> Recruter des personnes aux profils variés dans les métiers du numérique. | AF22: =IF(ISBLANK('Résultats détaillés'!E23),"",'Résultats détaillés'!E23) | AG22: =IF(ISBLANK('Résultats détaillés'!F23),"",'Résultats détaillés'!F23) | AH22: =IF(ISNUMBER('Résultats détaillés'!H23),IF(AND('Résultats détaillés'!H23>=1,'Résultats détaillés'!H23<=4,MOD('Résultats détaillés'!H23,1)=0),'Résultats détaillés'!H23,0),0) -> 0 | AI22: =IF(ISBLANK('Résultats détaillés'!W23),"",'Résultats détaillés'!W23) | AJ22: =IF(LEN(TRIM(AI22))>0,1,0) -> 0 | AK22: =IF(LEN(TRIM('Résultats détaillés'!G23))>0,1,0) -> 0 | AL22: =IF(OR(IF(LEN('Résultats détaillés'!E23)=0,FALSE,NOT(IF(ISNUMBER('Résultats détaillés'!E23),AND('Résultats détaillés'!E23>=0,'Résultats détaillés'!E23<=3,MOD('Résultats détaillés'!E23,1)=0),FALSE))),IF(LEN('Résultats détaillés'!F23)=0,FALSE,NOT(IF(ISNUMBER('Résultats détaillés'!F23),AND('Résultats détaillés'!F23>=1,'Résultats détaillés'!F23<=4,MOD('Résultats détaillés'!F23,1)=0),FALSE))),IF(LEN('Résultats détaillés'!H23)=0,FALSE,NOT(IF(ISNUMBER('Résultats détaillés'!H23),AND('Résultats détaillés'!H23>=1,'Résultats détaillés'!H23<=4,MOD('Résultats détaillés'!H23,1)=0),FALSE)))),1,0) -> 0 | AM22: =IF(AND(ISNUMBER(AB22),AB22>0,AK22=0),1,0) -> 0 | AN22: 23 | AO22: =IF(AND(ISNUMBER(AB22),AB22>0),1,0) -> 0 | AP22: =IF(AND(AC22>0,AH22=0),1,0) -> 0 | AQ22: =IF(AND(AC22>0,AJ22=0),1,0) -> 0 | AR22: =IF(ISNUMBER(AB22),1,0) -> 0
AA23: 3 | AB23: =IF(ISNUMBER('Résultats détaillés'!T24),'Résultats détaillés'!T24,"") | AC23: =IF(AND(ISNUMBER(AB23),AB23>=5),AB23*100+15,0) -> 0 | AD23: =IF(ISBLANK('Résultats détaillés'!B24),"",'Résultats détaillés'!B24) -> 3.5 | AE23: =IF(ISBLANK('Résultats détaillés'!C24),"",'Résultats détaillés'!C24) -> Améliorer les conditions de travail des personnes qui travaillent dans le numérique. | AF23: =IF(ISBLANK('Résultats détaillés'!E24),"",'Résultats détaillés'!E24) | AG23: =IF(ISBLANK('Résultats détaillés'!F24),"",'Résultats détaillés'!F24) | AH23: =IF(ISNUMBER('Résultats détaillés'!H24),IF(AND('Résultats détaillés'!H24>=1,'Résultats détaillés'!H24<=4,MOD('Résultats détaillés'!H24,1)=0),'Résultats détaillés'!H24,0),0) -> 0 | AI23: =IF(ISBLANK('Résultats détaillés'!W24),"",'Résultats détaillés'!W24) | AJ23: =IF(LEN(TRIM(AI23))>0,1,0) -> 0 | AK23: =IF(LEN(TRIM('Résultats détaillés'!G24))>0,1,0) -> 0 | AL23: =IF(OR(IF(LEN('Résultats détaillés'!E24)=0,FALSE,NOT(IF(ISNUMBER('Résultats détaillés'!E24),AND('Résultats détaillés'!E24>=0,'Résultats détaillés'!E24<=3,MOD('Résultats détaillés'!E24,1)=0),FALSE))),IF(LEN('Résultats détaillés'!F24)=0,FALSE,NOT(IF(ISNUMBER('Résultats détaillés'!F24),AND('Résultats détaillés'!F24>=1,'Résultats détaillés'!F24<=4,MOD('Résultats détaillés'!F24,1)=0),FALSE))),IF(LEN('Résultats détaillés'!H24)=0,FALSE,NOT(IF(ISNUMBER('Résultats détaillés'!H24),AND('Résultats détaillés'!H24>=1,'Résultats détaillés'!H24<=4,MOD('Résultats détaillés'!H24,1)=0),FALSE)))),1,0) -> 0 | AM23: =IF(AND(ISNUMBER(AB23),AB23>0,AK23=0),1,0) -> 0 | AN23: 24 | AO23: =IF(AND(ISNUMBER(AB23),AB23>0),1,0) -> 0 | AP23: =IF(AND(AC23>0,AH23=0),1,0) -> 0 | AQ23: =IF(AND(AC23>0,AJ23=0),1,0) -> 0 | AR23: =IF(ISNUMBER(AB23),1,0) -> 0
AA24: 3 | AB24: =IF(ISNUMBER('Résultats détaillés'!T25),'Résultats détaillés'!T25,"") | AC24: =IF(AND(ISNUMBER(AB24),AB24>=5),AB24*100+14,0) -> 0 | AD24: =IF(ISBLANK('Résultats détaillés'!B25),"",'Résultats détaillés'!B25) -> 3.6 | AE24: =IF(ISBLANK('Résultats détaillés'!C25),"",'Résultats détaillés'!C25) -> Fixer et appliquer des règles éthiques pour utiliser les algorithmes, en particulier l’intelligence artificielle. Encadrer l’utilisation des données et assurer leur protection. | AF24: =IF(ISBLANK('Résultats détaillés'!E25),"",'Résultats détaillés'!E25) | AG24: =IF(ISBLANK('Résultats détaillés'!F25),"",'Résultats détaillés'!F25) | AH24: =IF(ISNUMBER('Résultats détaillés'!H25),IF(AND('Résultats détaillés'!H25>=1,'Résultats détaillés'!H25<=4,MOD('Résultats détaillés'!H25,1)=0),'Résultats détaillés'!H25,0),0) -> 0 | AI24: =IF(ISBLANK('Résultats détaillés'!W25),"",'Résultats détaillés'!W25) | AJ24: =IF(LEN(TRIM(AI24))>0,1,0) -> 0 | AK24: =IF(LEN(TRIM('Résultats détaillés'!G25))>0,1,0) -> 0 | AL24: =IF(OR(IF(LEN('Résultats détaillés'!E25)=0,FALSE,NOT(IF(ISNUMBER('Résultats détaillés'!E25),AND('Résultats détaillés'!E25>=0,'Résultats détaillés'!E25<=3,MOD('Résultats détaillés'!E25,1)=0),FALSE))),IF(LEN('Résultats détaillés'!F25)=0,FALSE,NOT(IF(ISNUMBER('Résultats détaillés'!F25),AND('Résultats détaillés'!F25>=1,'Résultats détaillés'!F25<=4,MOD('Résultats détaillés'!F25,1)=0),FALSE))),IF(LEN('Résultats détaillés'!H25)=0,FALSE,NOT(IF(ISNUMBER('Résultats détaillés'!H25),AND('Résultats détaillés'!H25>=1,'Résultats détaillés'!H25<=4,MOD('Résultats détaillés'!H25,1)=0),FALSE)))),1,0) -> 0 | AM24: =IF(AND(ISNUMBER(AB24),AB24>0,AK24=0),1,0) -> 0 | AN24: 25 | AO24: =IF(AND(ISNUMBER(AB24),AB24>0),1,0) -> 0 | AP24: =IF(AND(AC24>0,AH24=0),1,0) -> 0 | AQ24: =IF(AND(AC24>0,AJ24=0),1,0) -> 0 | AR24: =IF(ISNUMBER(AB24),1,0) -> 0
AA25: 3 | AB25: =IF(ISNUMBER('Résultats détaillés'!T26),'Résultats détaillés'!T26,"") | AC25: =IF(AND(ISNUMBER(AB25),AB25>=5),AB25*100+13,0) -> 0 | AD25: =IF(ISBLANK('Résultats détaillés'!B26),"",'Résultats détaillés'!B26) -> 3.7 | AE25: =IF(ISBLANK('Résultats détaillés'!C26),"",'Résultats détaillés'!C26) -> Mettre en place et faire connaître les actions de responsabilité sociétale (RSE), qui prennent en compte les effets de l’organisation sur la société et l’environnement. | AF25: =IF(ISBLANK('Résultats détaillés'!E26),"",'Résultats détaillés'!E26) | AG25: =IF(ISBLANK('Résultats détaillés'!F26),"",'Résultats détaillés'!F26) | AH25: =IF(ISNUMBER('Résultats détaillés'!H26),IF(AND('Résultats détaillés'!H26>=1,'Résultats détaillés'!H26<=4,MOD('Résultats détaillés'!H26,1)=0),'Résultats détaillés'!H26,0),0) -> 0 | AI25: =IF(ISBLANK('Résultats détaillés'!W26),"",'Résultats détaillés'!W26) | AJ25: =IF(LEN(TRIM(AI25))>0,1,0) -> 0 | AK25: =IF(LEN(TRIM('Résultats détaillés'!G26))>0,1,0) -> 0 | AL25: =IF(OR(IF(LEN('Résultats détaillés'!E26)=0,FALSE,NOT(IF(ISNUMBER('Résultats détaillés'!E26),AND('Résultats détaillés'!E26>=0,'Résultats détaillés'!E26<=3,MOD('Résultats détaillés'!E26,1)=0),FALSE))),IF(LEN('Résultats détaillés'!F26)=0,FALSE,NOT(IF(ISNUMBER('Résultats détaillés'!F26),AND('Résultats détaillés'!F26>=1,'Résultats détaillés'!F26<=4,MOD('Résultats détaillés'!F26,1)=0),FALSE))),IF(LEN('Résultats détaillés'!H26)=0,FALSE,NOT(IF(ISNUMBER('Résultats détaillés'!H26),AND('Résultats détaillés'!H26>=1,'Résultats détaillés'!H26<=4,MOD('Résultats détaillés'!H26,1)=0),FALSE)))),1,0) -> 0 | AM25: =IF(AND(ISNUMBER(AB25),AB25>0,AK25=0),1,0) -> 0 | AN25: 26 | AO25: =IF(AND(ISNUMBER(AB25),AB25>0),1,0) -> 0 | AP25: =IF(AND(AC25>0,AH25=0),1,0) -> 0 | AQ25: =IF(AND(AC25>0,AJ25=0),1,0) -> 0 | AR25: =IF(ISNUMBER(AB25),1,0) -> 0
AA26: 3 | AB26: =IF(ISNUMBER('Résultats détaillés'!T27),'Résultats détaillés'!T27,"") | AC26: =IF(AND(ISNUMBER(AB26),AB26>=5),AB26*100+12,0) -> 0 | AD26: =IF(ISBLANK('Résultats détaillés'!B27),"",'Résultats détaillés'!B27) -> 3.8 | AE26: =IF(ISBLANK('Résultats détaillés'!C27),"",'Résultats détaillés'!C27) -> Indiquer quand une intelligence artificielle répond et expliquer comment elle prend ses décisions. Garder un contrôle humain sur les sujets sensibles. | AF26: =IF(ISBLANK('Résultats détaillés'!E27),"",'Résultats détaillés'!E27) | AG26: =IF(ISBLANK('Résultats détaillés'!F27),"",'Résultats détaillés'!F27) | AH26: =IF(ISNUMBER('Résultats détaillés'!H27),IF(AND('Résultats détaillés'!H27>=1,'Résultats détaillés'!H27<=4,MOD('Résultats détaillés'!H27,1)=0),'Résultats détaillés'!H27,0),0) -> 0 | AI26: =IF(ISBLANK('Résultats détaillés'!W27),"",'Résultats détaillés'!W27) | AJ26: =IF(LEN(TRIM(AI26))>0,1,0) -> 0 | AK26: =IF(LEN(TRIM('Résultats détaillés'!G27))>0,1,0) -> 0 | AL26: =IF(OR(IF(LEN('Résultats détaillés'!E27)=0,FALSE,NOT(IF(ISNUMBER('Résultats détaillés'!E27),AND('Résultats détaillés'!E27>=0,'Résultats détaillés'!E27<=3,MOD('Résultats détaillés'!E27,1)=0),FALSE))),IF(LEN('Résultats détaillés'!F27)=0,FALSE,NOT(IF(ISNUMBER('Résultats détaillés'!F27),AND('Résultats détaillés'!F27>=1,'Résultats détaillés'!F27<=4,MOD('Résultats détaillés'!F27,1)=0),FALSE))),IF(LEN('Résultats détaillés'!H27)=0,FALSE,NOT(IF(ISNUMBER('Résultats détaillés'!H27),AND('Résultats détaillés'!H27>=1,'Résultats détaillés'!H27<=4,MOD('Résultats détaillés'!H27,1)=0),FALSE)))),1,0) -> 0 | AM26: =IF(AND(ISNUMBER(AB26),AB26>0,AK26=0),1,0) -> 0 | AN26: 27 | AO26: =IF(AND(ISNUMBER(AB26),AB26>0),1,0) -> 0 | AP26: =IF(AND(AC26>0,AH26=0),1,0) -> 0 | AQ26: =IF(AND(AC26>0,AJ26=0),1,0) -> 0 | AR26: =IF(ISNUMBER(AB26),1,0) -> 0
AA27: 4 | AB27: =IF(ISNUMBER('Résultats détaillés'!T29),'Résultats détaillés'!T29,"") | AC27: =IF(AND(ISNUMBER(AB27),AB27>=5),AB27*100+11,0) -> 0 | AD27: =IF(ISBLANK('Résultats détaillés'!B29),"",'Résultats détaillés'!B29) -> 4.1 | AE27: =IF(ISBLANK('Résultats détaillés'!C29),"",'Résultats détaillés'!C29) -> Suivre des normes communes pour recueillir, regrouper, analyser et partager les données sur les effets des technologies de l’information et de la communication (TIC). | AF27: =IF(ISBLANK('Résultats détaillés'!E29),"",'Résultats détaillés'!E29) | AG27: =IF(ISBLANK('Résultats détaillés'!F29),"",'Résultats détaillés'!F29) | AH27: =IF(ISNUMBER('Résultats détaillés'!H29),IF(AND('Résultats détaillés'!H29>=1,'Résultats détaillés'!H29<=4,MOD('Résultats détaillés'!H29,1)=0),'Résultats détaillés'!H29,0),0) -> 0 | AI27: =IF(ISBLANK('Résultats détaillés'!W29),"",'Résultats détaillés'!W29) | AJ27: =IF(LEN(TRIM(AI27))>0,1,0) -> 0 | AK27: =IF(LEN(TRIM('Résultats détaillés'!G29))>0,1,0) -> 0 | AL27: =IF(OR(IF(LEN('Résultats détaillés'!E29)=0,FALSE,NOT(IF(ISNUMBER('Résultats détaillés'!E29),AND('Résultats détaillés'!E29>=0,'Résultats détaillés'!E29<=3,MOD('Résultats détaillés'!E29,1)=0),FALSE))),IF(LEN('Résultats détaillés'!F29)=0,FALSE,NOT(IF(ISNUMBER('Résultats détaillés'!F29),AND('Résultats détaillés'!F29>=1,'Résultats détaillés'!F29<=4,MOD('Résultats détaillés'!F29,1)=0),FALSE))),IF(LEN('Résultats détaillés'!H29)=0,FALSE,NOT(IF(ISNUMBER('Résultats détaillés'!H29),AND('Résultats détaillés'!H29>=1,'Résultats détaillés'!H29<=4,MOD('Résultats détaillés'!H29,1)=0),FALSE)))),1,0) -> 0 | AM27: =IF(AND(ISNUMBER(AB27),AB27>0,AK27=0),1,0) -> 0 | AN27: 29 | AO27: =IF(AND(ISNUMBER(AB27),AB27>0),1,0) -> 0 | AP27: =IF(AND(AC27>0,AH27=0),1,0) -> 0 | AQ27: =IF(AND(AC27>0,AJ27=0),1,0) -> 0 | AR27: =IF(ISNUMBER(AB27),1,0) -> 0
AA28: 4 | AB28: =IF(ISNUMBER('Résultats détaillés'!T30),'Résultats détaillés'!T30,"") | AC28: =IF(AND(ISNUMBER(AB28),AB28>=5),AB28*100+10,0) -> 0 | AD28: =IF(ISBLANK('Résultats détaillés'!B30),"",'Résultats détaillés'!B30) -> 4.2 | AE28: =IF(ISBLANK('Résultats détaillés'!C30),"",'Résultats détaillés'!C30) -> Évaluer les services numériques au fil du temps et partager les résultats. | AF28: =IF(ISBLANK('Résultats détaillés'!E30),"",'Résultats détaillés'!E30) | AG28: =IF(ISBLANK('Résultats détaillés'!F30),"",'Résultats détaillés'!F30) | AH28: =IF(ISNUMBER('Résultats détaillés'!H30),IF(AND('Résultats détaillés'!H30>=1,'Résultats détaillés'!H30<=4,MOD('Résultats détaillés'!H30,1)=0),'Résultats détaillés'!H30,0),0) -> 0 | AI28: =IF(ISBLANK('Résultats détaillés'!W30),"",'Résultats détaillés'!W30) | AJ28: =IF(LEN(TRIM(AI28))>0,1,0) -> 0 | AK28: =IF(LEN(TRIM('Résultats détaillés'!G30))>0,1,0) -> 0 | AL28: =IF(OR(IF(LEN('Résultats détaillés'!E30)=0,FALSE,NOT(IF(ISNUMBER('Résultats détaillés'!E30),AND('Résultats détaillés'!E30>=0,'Résultats détaillés'!E30<=3,MOD('Résultats détaillés'!E30,1)=0),FALSE))),IF(LEN('Résultats détaillés'!F30)=0,FALSE,NOT(IF(ISNUMBER('Résultats détaillés'!F30),AND('Résultats détaillés'!F30>=1,'Résultats détaillés'!F30<=4,MOD('Résultats détaillés'!F30,1)=0),FALSE))),IF(LEN('Résultats détaillés'!H30)=0,FALSE,NOT(IF(ISNUMBER('Résultats détaillés'!H30),AND('Résultats détaillés'!H30>=1,'Résultats détaillés'!H30<=4,MOD('Résultats détaillés'!H30,1)=0),FALSE)))),1,0) -> 0 | AM28: =IF(AND(ISNUMBER(AB28),AB28>0,AK28=0),1,0) -> 0 | AN28: 30 | AO28: =IF(AND(ISNUMBER(AB28),AB28>0),1,0) -> 0 | AP28: =IF(AND(AC28>0,AH28=0),1,0) -> 0 | AQ28: =IF(AND(AC28>0,AJ28=0),1,0) -> 0 | AR28: =IF(ISNUMBER(AB28),1,0) -> 0
AA29: 4 | AB29: =IF(ISNUMBER('Résultats détaillés'!T31),'Résultats détaillés'!T31,"") | AC29: =IF(AND(ISNUMBER(AB29),AB29>=5),AB29*100+9,0) -> 0 | AD29: =IF(ISBLANK('Résultats détaillés'!B31),"",'Résultats détaillés'!B31) -> 4.3 | AE29: =IF(ISBLANK('Résultats détaillés'!C31),"",'Résultats détaillés'!C31) -> Innover en utilisant de nouveaux outils numériques. Évaluer leurs effets et expliquer les résultats aux personnes qui les utilisent. | AF29: =IF(ISBLANK('Résultats détaillés'!E31),"",'Résultats détaillés'!E31) | AG29: =IF(ISBLANK('Résultats détaillés'!F31),"",'Résultats détaillés'!F31) | AH29: =IF(ISNUMBER('Résultats détaillés'!H31),IF(AND('Résultats détaillés'!H31>=1,'Résultats détaillés'!H31<=4,MOD('Résultats détaillés'!H31,1)=0),'Résultats détaillés'!H31,0),0) -> 0 | AI29: =IF(ISBLANK('Résultats détaillés'!W31),"",'Résultats détaillés'!W31) | AJ29: =IF(LEN(TRIM(AI29))>0,1,0) -> 0 | AK29: =IF(LEN(TRIM('Résultats détaillés'!G31))>0,1,0) -> 0 | AL29: =IF(OR(IF(LEN('Résultats détaillés'!E31)=0,FALSE,NOT(IF(ISNUMBER('Résultats détaillés'!E31),AND('Résultats détaillés'!E31>=0,'Résultats détaillés'!E31<=3,MOD('Résultats détaillés'!E31,1)=0),FALSE))),IF(LEN('Résultats détaillés'!F31)=0,FALSE,NOT(IF(ISNUMBER('Résultats détaillés'!F31),AND('Résultats détaillés'!F31>=1,'Résultats détaillés'!F31<=4,MOD('Résultats détaillés'!F31,1)=0),FALSE))),IF(LEN('Résultats détaillés'!H31)=0,FALSE,NOT(IF(ISNUMBER('Résultats détaillés'!H31),AND('Résultats détaillés'!H31>=1,'Résultats détaillés'!H31<=4,MOD('Résultats détaillés'!H31,1)=0),FALSE)))),1,0) -> 0 | AM29: =IF(AND(ISNUMBER(AB29),AB29>0,AK29=0),1,0) -> 0 | AN29: 31 | AO29: =IF(AND(ISNUMBER(AB29),AB29>0),1,0) -> 0 | AP29: =IF(AND(AC29>0,AH29=0),1,0) -> 0 | AQ29: =IF(AND(AC29>0,AJ29=0),1,0) -> 0 | AR29: =IF(ISNUMBER(AB29),1,0) -> 0
AA30: 4 | AB30: =IF(ISNUMBER('Résultats détaillés'!T32),'Résultats détaillés'!T32,"") | AC30: =IF(AND(ISNUMBER(AB30),AB30>=5),AB30*100+8,0) -> 0 | AD30: =IF(ISBLANK('Résultats détaillés'!B32),"",'Résultats détaillés'!B32) -> 4.4 | AE30: =IF(ISBLANK('Résultats détaillés'!C32),"",'Résultats détaillés'!C32) -> Renforcer la souveraineté numérique : garder la maîtrise de nos choix, de nos outils et de nos données. | AF30: =IF(ISBLANK('Résultats détaillés'!E32),"",'Résultats détaillés'!E32) | AG30: =IF(ISBLANK('Résultats détaillés'!F32),"",'Résultats détaillés'!F32) | AH30: =IF(ISNUMBER('Résultats détaillés'!H32),IF(AND('Résultats détaillés'!H32>=1,'Résultats détaillés'!H32<=4,MOD('Résultats détaillés'!H32,1)=0),'Résultats détaillés'!H32,0),0) -> 0 | AI30: =IF(ISBLANK('Résultats détaillés'!W32),"",'Résultats détaillés'!W32) | AJ30: =IF(LEN(TRIM(AI30))>0,1,0) -> 0 | AK30: =IF(LEN(TRIM('Résultats détaillés'!G32))>0,1,0) -> 0 | AL30: =IF(OR(IF(LEN('Résultats détaillés'!E32)=0,FALSE,NOT(IF(ISNUMBER('Résultats détaillés'!E32),AND('Résultats détaillés'!E32>=0,'Résultats détaillés'!E32<=3,MOD('Résultats détaillés'!E32,1)=0),FALSE))),IF(LEN('Résultats détaillés'!F32)=0,FALSE,NOT(IF(ISNUMBER('Résultats détaillés'!F32),AND('Résultats détaillés'!F32>=1,'Résultats détaillés'!F32<=4,MOD('Résultats détaillés'!F32,1)=0),FALSE))),IF(LEN('Résultats détaillés'!H32)=0,FALSE,NOT(IF(ISNUMBER('Résultats détaillés'!H32),AND('Résultats détaillés'!H32>=1,'Résultats détaillés'!H32<=4,MOD('Résultats détaillés'!H32,1)=0),FALSE)))),1,0) -> 0 | AM30: =IF(AND(ISNUMBER(AB30),AB30>0,AK30=0),1,0) -> 0 | AN30: 32 | AO30: =IF(AND(ISNUMBER(AB30),AB30>0),1,0) -> 0 | AP30: =IF(AND(AC30>0,AH30=0),1,0) -> 0 | AQ30: =IF(AND(AC30>0,AJ30=0),1,0) -> 0 | AR30: =IF(ISNUMBER(AB30),1,0) -> 0
AA31: 5 | AB31: =IF(ISNUMBER('Résultats détaillés'!T34),'Résultats détaillés'!T34,"") | AC31: =IF(AND(ISNUMBER(AB31),AB31>=5),AB31*100+7,0) -> 0 | AD31: =IF(ISBLANK('Résultats détaillés'!B34),"",'Résultats détaillés'!B34) -> 5.1 | AE31: =IF(ISBLANK('Résultats détaillés'!C34),"",'Résultats détaillés'!C34) -> Concevoir les systèmes et les services numériques en intégrant de nouvelles façons de répondre aux besoins sociaux. | AF31: =IF(ISBLANK('Résultats détaillés'!E34),"",'Résultats détaillés'!E34) | AG31: =IF(ISBLANK('Résultats détaillés'!F34),"",'Résultats détaillés'!F34) | AH31: =IF(ISNUMBER('Résultats détaillés'!H34),IF(AND('Résultats détaillés'!H34>=1,'Résultats détaillés'!H34<=4,MOD('Résultats détaillés'!H34,1)=0),'Résultats détaillés'!H34,0),0) -> 0 | AI31: =IF(ISBLANK('Résultats détaillés'!W34),"",'Résultats détaillés'!W34) | AJ31: =IF(LEN(TRIM(AI31))>0,1,0) -> 0 | AK31: =IF(LEN(TRIM('Résultats détaillés'!G34))>0,1,0) -> 0 | AL31: =IF(OR(IF(LEN('Résultats détaillés'!E34)=0,FALSE,NOT(IF(ISNUMBER('Résultats détaillés'!E34),AND('Résultats détaillés'!E34>=0,'Résultats détaillés'!E34<=3,MOD('Résultats détaillés'!E34,1)=0),FALSE))),IF(LEN('Résultats détaillés'!F34)=0,FALSE,NOT(IF(ISNUMBER('Résultats détaillés'!F34),AND('Résultats détaillés'!F34>=1,'Résultats détaillés'!F34<=4,MOD('Résultats détaillés'!F34,1)=0),FALSE))),IF(LEN('Résultats détaillés'!H34)=0,FALSE,NOT(IF(ISNUMBER('Résultats détaillés'!H34),AND('Résultats détaillés'!H34>=1,'Résultats détaillés'!H34<=4,MOD('Résultats détaillés'!H34,1)=0),FALSE)))),1,0) -> 0 | AM31: =IF(AND(ISNUMBER(AB31),AB31>0,AK31=0),1,0) -> 0 | AN31: 34 | AO31: =IF(AND(ISNUMBER(AB31),AB31>0),1,0) -> 0 | AP31: =IF(AND(AC31>0,AH31=0),1,0) -> 0 | AQ31: =IF(AND(AC31>0,AJ31=0),1,0) -> 0 | AR31: =IF(ISNUMBER(AB31),1,0) -> 0
AA32: 5 | AB32: =IF(ISNUMBER('Résultats détaillés'!T35),'Résultats détaillés'!T35,"") | AC32: =IF(AND(ISNUMBER(AB32),AB32>=5),AB32*100+6,0) -> 0 | AD32: =IF(ISBLANK('Résultats détaillés'!B35),"",'Résultats détaillés'!B35) -> 5.2 | AE32: =IF(ISBLANK('Résultats détaillés'!C35),"",'Résultats détaillés'!C35) -> Faire connaître et soutenir les initiatives des équipes qui encouragent l’engagement, la coopération entre services et le bien-être au travail. | AF32: =IF(ISBLANK('Résultats détaillés'!E35),"",'Résultats détaillés'!E35) | AG32: =IF(ISBLANK('Résultats détaillés'!F35),"",'Résultats détaillés'!F35) | AH32: =IF(ISNUMBER('Résultats détaillés'!H35),IF(AND('Résultats détaillés'!H35>=1,'Résultats détaillés'!H35<=4,MOD('Résultats détaillés'!H35,1)=0),'Résultats détaillés'!H35,0),0) -> 0 | AI32: =IF(ISBLANK('Résultats détaillés'!W35),"",'Résultats détaillés'!W35) | AJ32: =IF(LEN(TRIM(AI32))>0,1,0) -> 0 | AK32: =IF(LEN(TRIM('Résultats détaillés'!G35))>0,1,0) -> 0 | AL32: =IF(OR(IF(LEN('Résultats détaillés'!E35)=0,FALSE,NOT(IF(ISNUMBER('Résultats détaillés'!E35),AND('Résultats détaillés'!E35>=0,'Résultats détaillés'!E35<=3,MOD('Résultats détaillés'!E35,1)=0),FALSE))),IF(LEN('Résultats détaillés'!F35)=0,FALSE,NOT(IF(ISNUMBER('Résultats détaillés'!F35),AND('Résultats détaillés'!F35>=1,'Résultats détaillés'!F35<=4,MOD('Résultats détaillés'!F35,1)=0),FALSE))),IF(LEN('Résultats détaillés'!H35)=0,FALSE,NOT(IF(ISNUMBER('Résultats détaillés'!H35),AND('Résultats détaillés'!H35>=1,'Résultats détaillés'!H35<=4,MOD('Résultats détaillés'!H35,1)=0),FALSE)))),1,0) -> 0 | AM32: =IF(AND(ISNUMBER(AB32),AB32>0,AK32=0),1,0) -> 0 | AN32: 35 | AO32: =IF(AND(ISNUMBER(AB32),AB32>0),1,0) -> 0 | AP32: =IF(AND(AC32>0,AH32=0),1,0) -> 0 | AQ32: =IF(AND(AC32>0,AJ32=0),1,0) -> 0 | AR32: =IF(ISNUMBER(AB32),1,0) -> 0
AA33: 5 | AB33: =IF(ISNUMBER('Résultats détaillés'!T36),'Résultats détaillés'!T36,"") | AC33: =IF(AND(ISNUMBER(AB33),AB33>=5),AB33*100+5,0) -> 0 | AD33: =IF(ISBLANK('Résultats détaillés'!B36),"",'Résultats détaillés'!B36) -> 5.3 | AE33: =IF(ISBLANK('Résultats détaillés'!C36),"",'Résultats détaillés'!C36) -> Faire participer les personnes et les organisations concernées. S’appuyer sur leurs connaissances des questions d’environnement, de conditions de vie et de société. | AF33: =IF(ISBLANK('Résultats détaillés'!E36),"",'Résultats détaillés'!E36) | AG33: =IF(ISBLANK('Résultats détaillés'!F36),"",'Résultats détaillés'!F36) | AH33: =IF(ISNUMBER('Résultats détaillés'!H36),IF(AND('Résultats détaillés'!H36>=1,'Résultats détaillés'!H36<=4,MOD('Résultats détaillés'!H36,1)=0),'Résultats détaillés'!H36,0),0) -> 0 | AI33: =IF(ISBLANK('Résultats détaillés'!W36),"",'Résultats détaillés'!W36) | AJ33: =IF(LEN(TRIM(AI33))>0,1,0) -> 0 | AK33: =IF(LEN(TRIM('Résultats détaillés'!G36))>0,1,0) -> 0 | AL33: =IF(OR(IF(LEN('Résultats détaillés'!E36)=0,FALSE,NOT(IF(ISNUMBER('Résultats détaillés'!E36),AND('Résultats détaillés'!E36>=0,'Résultats détaillés'!E36<=3,MOD('Résultats détaillés'!E36,1)=0),FALSE))),IF(LEN('Résultats détaillés'!F36)=0,FALSE,NOT(IF(ISNUMBER('Résultats détaillés'!F36),AND('Résultats détaillés'!F36>=1,'Résultats détaillés'!F36<=4,MOD('Résultats détaillés'!F36,1)=0),FALSE))),IF(LEN('Résultats détaillés'!H36)=0,FALSE,NOT(IF(ISNUMBER('Résultats détaillés'!H36),AND('Résultats détaillés'!H36>=1,'Résultats détaillés'!H36<=4,MOD('Résultats détaillés'!H36,1)=0),FALSE)))),1,0) -> 0 | AM33: =IF(AND(ISNUMBER(AB33),AB33>0,AK33=0),1,0) -> 0 | AN33: 36 | AO33: =IF(AND(ISNUMBER(AB33),AB33>0),1,0) -> 0 | AP33: =IF(AND(AC33>0,AH33=0),1,0) -> 0 | AQ33: =IF(AND(AC33>0,AJ33=0),1,0) -> 0 | AR33: =IF(ISNUMBER(AB33),1,0) -> 0
AA34: 5 | AB34: =IF(ISNUMBER('Résultats détaillés'!T37),'Résultats détaillés'!T37,"") | AC34: =IF(AND(ISNUMBER(AB34),AB34>=5),AB34*100+4,0) -> 0 | AD34: =IF(ISBLANK('Résultats détaillés'!B37),"",'Résultats détaillés'!B37) -> 5.4 | AE34: =IF(ISBLANK('Résultats détaillés'!C37),"",'Résultats détaillés'!C37) -> Permettre aux générations futures d’innover pour mieux vivre ensemble, s’ouvrir aux autres et préserver l’équilibre de la nature. | AF34: =IF(ISBLANK('Résultats détaillés'!E37),"",'Résultats détaillés'!E37) | AG34: =IF(ISBLANK('Résultats détaillés'!F37),"",'Résultats détaillés'!F37) | AH34: =IF(ISNUMBER('Résultats détaillés'!H37),IF(AND('Résultats détaillés'!H37>=1,'Résultats détaillés'!H37<=4,MOD('Résultats détaillés'!H37,1)=0),'Résultats détaillés'!H37,0),0) -> 0 | AI34: =IF(ISBLANK('Résultats détaillés'!W37),"",'Résultats détaillés'!W37) | AJ34: =IF(LEN(TRIM(AI34))>0,1,0) -> 0 | AK34: =IF(LEN(TRIM('Résultats détaillés'!G37))>0,1,0) -> 0 | AL34: =IF(OR(IF(LEN('Résultats détaillés'!E37)=0,FALSE,NOT(IF(ISNUMBER('Résultats détaillés'!E37),AND('Résultats détaillés'!E37>=0,'Résultats détaillés'!E37<=3,MOD('Résultats détaillés'!E37,1)=0),FALSE))),IF(LEN('Résultats détaillés'!F37)=0,FALSE,NOT(IF(ISNUMBER('Résultats détaillés'!F37),AND('Résultats détaillés'!F37>=1,'Résultats détaillés'!F37<=4,MOD('Résultats détaillés'!F37,1)=0),FALSE))),IF(LEN('Résultats détaillés'!H37)=0,FALSE,NOT(IF(ISNUMBER('Résultats détaillés'!H37),AND('Résultats détaillés'!H37>=1,'Résultats détaillés'!H37<=4,MOD('Résultats détaillés'!H37,1)=0),FALSE)))),1,0) -> 0 | AM34: =IF(AND(ISNUMBER(AB34),AB34>0,AK34=0),1,0) -> 0 | AN34: 37 | AO34: =IF(AND(ISNUMBER(AB34),AB34>0),1,0) -> 0 | AP34: =IF(AND(AC34>0,AH34=0),1,0) -> 0 | AQ34: =IF(AND(AC34>0,AJ34=0),1,0) -> 0 | AR34: =IF(ISNUMBER(AB34),1,0) -> 0
AA35: 5 | AB35: =IF(ISNUMBER('Résultats détaillés'!T38),'Résultats détaillés'!T38,"") | AC35: =IF(AND(ISNUMBER(AB35),AB35>=5),AB35*100+3,0) -> 0 | AD35: =IF(ISBLANK('Résultats détaillés'!B38),"",'Résultats détaillés'!B38) -> 5.5 | AE35: =IF(ISBLANK('Résultats détaillés'!C38),"",'Résultats détaillés'!C38) -> Suivre les résultats obtenus et le respect des règles à l’aide d’indicateurs. | AF35: =IF(ISBLANK('Résultats détaillés'!E38),"",'Résultats détaillés'!E38) | AG35: =IF(ISBLANK('Résultats détaillés'!F38),"",'Résultats détaillés'!F38) | AH35: =IF(ISNUMBER('Résultats détaillés'!H38),IF(AND('Résultats détaillés'!H38>=1,'Résultats détaillés'!H38<=4,MOD('Résultats détaillés'!H38,1)=0),'Résultats détaillés'!H38,0),0) -> 0 | AI35: =IF(ISBLANK('Résultats détaillés'!W38),"",'Résultats détaillés'!W38) | AJ35: =IF(LEN(TRIM(AI35))>0,1,0) -> 0 | AK35: =IF(LEN(TRIM('Résultats détaillés'!G38))>0,1,0) -> 0 | AL35: =IF(OR(IF(LEN('Résultats détaillés'!E38)=0,FALSE,NOT(IF(ISNUMBER('Résultats détaillés'!E38),AND('Résultats détaillés'!E38>=0,'Résultats détaillés'!E38<=3,MOD('Résultats détaillés'!E38,1)=0),FALSE))),IF(LEN('Résultats détaillés'!F38)=0,FALSE,NOT(IF(ISNUMBER('Résultats détaillés'!F38),AND('Résultats détaillés'!F38>=1,'Résultats détaillés'!F38<=4,MOD('Résultats détaillés'!F38,1)=0),FALSE))),IF(LEN('Résultats détaillés'!H38)=0,FALSE,NOT(IF(ISNUMBER('Résultats détaillés'!H38),AND('Résultats détaillés'!H38>=1,'Résultats détaillés'!H38<=4,MOD('Résultats détaillés'!H38,1)=0),FALSE)))),1,0) -> 0 | AM35: =IF(AND(ISNUMBER(AB35),AB35>0,AK35=0),1,0) -> 0 | AN35: 38 | AO35: =IF(AND(ISNUMBER(AB35),AB35>0),1,0) -> 0 | AP35: =IF(AND(AC35>0,AH35=0),1,0) -> 0 | AQ35: =IF(AND(AC35>0,AJ35=0),1,0) -> 0 | AR35: =IF(ISNUMBER(AB35),1,0) -> 0
AA36: 5 | AB36: =IF(ISNUMBER('Résultats détaillés'!T39),'Résultats détaillés'!T39,"") | AC36: =IF(AND(ISNUMBER(AB36),AB36>=5),AB36*100+2,0) -> 0 | AD36: =IF(ISBLANK('Résultats détaillés'!B39),"",'Résultats détaillés'!B39) -> 5.6 | AE36: =IF(ISBLANK('Résultats détaillés'!C39),"",'Résultats détaillés'!C39) -> Proposer des améliorations et de nouvelles idées pour un numérique responsable, y compris des solutions sans outils numériques. | AF36: =IF(ISBLANK('Résultats détaillés'!E39),"",'Résultats détaillés'!E39) | AG36: =IF(ISBLANK('Résultats détaillés'!F39),"",'Résultats détaillés'!F39) | AH36: =IF(ISNUMBER('Résultats détaillés'!H39),IF(AND('Résultats détaillés'!H39>=1,'Résultats détaillés'!H39<=4,MOD('Résultats détaillés'!H39,1)=0),'Résultats détaillés'!H39,0),0) -> 0 | AI36: =IF(ISBLANK('Résultats détaillés'!W39),"",'Résultats détaillés'!W39) | AJ36: =IF(LEN(TRIM(AI36))>0,1,0) -> 0 | AK36: =IF(LEN(TRIM('Résultats détaillés'!G39))>0,1,0) -> 0 | AL36: =IF(OR(IF(LEN('Résultats détaillés'!E39)=0,FALSE,NOT(IF(ISNUMBER('Résultats détaillés'!E39),AND('Résultats détaillés'!E39>=0,'Résultats détaillés'!E39<=3,MOD('Résultats détaillés'!E39,1)=0),FALSE))),IF(LEN('Résultats détaillés'!F39)=0,FALSE,NOT(IF(ISNUMBER('Résultats détaillés'!F39),AND('Résultats détaillés'!F39>=1,'Résultats détaillés'!F39<=4,MOD('Résultats détaillés'!F39,1)=0),FALSE))),IF(LEN('Résultats détaillés'!H39)=0,FALSE,NOT(IF(ISNUMBER('Résultats détaillés'!H39),AND('Résultats détaillés'!H39>=1,'Résultats détaillés'!H39<=4,MOD('Résultats détaillés'!H39,1)=0),FALSE)))),1,0) -> 0 | AM36: =IF(AND(ISNUMBER(AB36),AB36>0,AK36=0),1,0) -> 0 | AN36: 39 | AO36: =IF(AND(ISNUMBER(AB36),AB36>0),1,0) -> 0 | AP36: =IF(AND(AC36>0,AH36=0),1,0) -> 0 | AQ36: =IF(AND(AC36>0,AJ36=0),1,0) -> 0 | AR36: =IF(ISNUMBER(AB36),1,0) -> 0
B37: Comprendre les notes et les besoins | AA37: 5 | AB37: =IF(ISNUMBER('Résultats détaillés'!T40),'Résultats détaillés'!T40,"") | AC37: =IF(AND(ISNUMBER(AB37),AB37>=5),AB37*100+1,0) -> 0 | AD37: =IF(ISBLANK('Résultats détaillés'!B40),"",'Résultats détaillés'!B40) -> 5.7 | AE37: =IF(ISBLANK('Résultats détaillés'!C40),"",'Résultats détaillés'!C40) -> Décider avec les équipes comment utiliser l’intelligence artificielle. Les former à ses limites et préserver le sens de leur travail. | AF37: =IF(ISBLANK('Résultats détaillés'!E40),"",'Résultats détaillés'!E40) | AG37: =IF(ISBLANK('Résultats détaillés'!F40),"",'Résultats détaillés'!F40) | AH37: =IF(ISNUMBER('Résultats détaillés'!H40),IF(AND('Résultats détaillés'!H40>=1,'Résultats détaillés'!H40<=4,MOD('Résultats détaillés'!H40,1)=0),'Résultats détaillés'!H40,0),0) -> 0 | AI37: =IF(ISBLANK('Résultats détaillés'!W40),"",'Résultats détaillés'!W40) | AJ37: =IF(LEN(TRIM(AI37))>0,1,0) -> 0 | AK37: =IF(LEN(TRIM('Résultats détaillés'!G40))>0,1,0) -> 0 | AL37: =IF(OR(IF(LEN('Résultats détaillés'!E40)=0,FALSE,NOT(IF(ISNUMBER('Résultats détaillés'!E40),AND('Résultats détaillés'!E40>=0,'Résultats détaillés'!E40<=3,MOD('Résultats détaillés'!E40,1)=0),FALSE))),IF(LEN('Résultats détaillés'!F40)=0,FALSE,NOT(IF(ISNUMBER('Résultats détaillés'!F40),AND('Résultats détaillés'!F40>=1,'Résultats détaillés'!F40<=4,MOD('Résultats détaillés'!F40,1)=0),FALSE))),IF(LEN('Résultats détaillés'!H40)=0,FALSE,NOT(IF(ISNUMBER('Résultats détaillés'!H40),AND('Résultats détaillés'!H40>=1,'Résultats détaillés'!H40<=4,MOD('Résultats détaillés'!H40,1)=0),FALSE)))),1,0) -> 0 | AM37: =IF(AND(ISNUMBER(AB37),AB37>0,AK37=0),1,0) -> 0 | AN37: 40 | AO37: =IF(AND(ISNUMBER(AB37),AB37>0),1,0) -> 0 | AP37: =IF(AND(AC37>0,AH37=0),1,0) -> 0 | AQ37: =IF(AND(AC37>0,AJ37=0),1,0) -> 0 | AR37: =IF(ISNUMBER(AB37),1,0) -> 0
B38: Importance et niveau atteint | I38: Compétences nécessaires pour les priorités
B39: Importance | C39: 1. Pas du tout | D39: 2. En partie | E39: 3. En bonne voie | F39: 4. Atteinte | G39: Total | I39: Équipe à mobiliser | M39: Cibles
B40: 3. Très importante | C40: =COUNTIFS($AO$6:$AO$37,1,$AF$6:$AF$37,3,$AG$6:$AG$37,1) -> 3 | D40: =COUNTIFS($AO$6:$AO$37,1,$AF$6:$AF$37,3,$AG$6:$AG$37,2) -> 1 | E40: =COUNTIFS($AO$6:$AO$37,1,$AF$6:$AF$37,3,$AG$6:$AG$37,3) -> 1 | F40: =COUNTIFS($AO$6:$AO$37,1,$AF$6:$AF$37,3,$AG$6:$AG$37,4) -> 0 | G40: =SUM(C40:F40) -> 5 | I40: Équipe NR / RSE | M40: =COUNTIFS($AC$6:$AC$37,">0",$AH$6:$AH$37,1) -> 0
B41: 2. Importante | C41: =COUNTIFS($AO$6:$AO$37,1,$AF$6:$AF$37,2,$AG$6:$AG$37,1) -> 0 | D41: =COUNTIFS($AO$6:$AO$37,1,$AF$6:$AF$37,2,$AG$6:$AG$37,2) -> 0 | E41: =COUNTIFS($AO$6:$AO$37,1,$AF$6:$AF$37,2,$AG$6:$AG$37,3) -> 0 | F41: =COUNTIFS($AO$6:$AO$37,1,$AF$6:$AF$37,2,$AG$6:$AG$37,4) -> 0 | G41: =SUM(C41:F41) -> 0 | I41: NR / RSE et informatique (DSI) | M41: =COUNTIFS($AC$6:$AC$37,">0",$AH$6:$AH$37,2) -> 3
B42: 1. Peu importante | C42: =COUNTIFS($AO$6:$AO$37,1,$AF$6:$AF$37,1,$AG$6:$AG$37,1) -> 0 | D42: =COUNTIFS($AO$6:$AO$37,1,$AF$6:$AF$37,1,$AG$6:$AG$37,2) -> 0 | E42: =COUNTIFS($AO$6:$AO$37,1,$AF$6:$AF$37,1,$AG$6:$AG$37,3) -> 0 | F42: =COUNTIFS($AO$6:$AO$37,1,$AF$6:$AF$37,1,$AG$6:$AG$37,4) -> 0 | G42: =SUM(C42:F42) -> 0 | I42: NR / RSE et équipe hors DSI | M42: =COUNTIFS($AC$6:$AC$37,">0",$AH$6:$AH$37,3) -> 1
B43: Total | C43: =SUM(C40:C42) -> 3 | D43: =SUM(D40:D42) -> 1 | E43: =SUM(E40:E42) -> 1 | F43: =SUM(F40:F42) -> 0 | G43: =SUM(G40:G42) -> 5 | I43: Intervention extérieure | M43: =COUNTIFS($AC$6:$AC$37,">0",$AH$6:$AH$37,4) -> 0
I44: À préciser | M44: =COUNTIFS($AC$6:$AC$37,">0",$AH$6:$AH$37,0) -> 0
B45: La matrice compte les cibles applicables évaluées. Les couleurs suivent les niveaux de priorité du document. | I45: NR : numérique responsable. RSE : responsabilité sociétale. Ce tableau concerne les urgentes et les prioritaires.
B48: Informations à compléter
B49: Point à vérifier | G49: Cibles | H49: Comment lire ce nombre
B50: Évaluation à compléter | G50: =E16 -> 27 | H50: Une priorité ne peut pas encore être calculée.
B51: Notes hors échelle | G51: =SUM($AL$6:$AL$37) -> 0 | H51: Au moins une note saisie ne respecte pas les choix proposés.
B52: Justification du niveau actuel absente | G52: =SUM($AM$6:$AM$37) -> 0 | H52: Cibles applicables évaluées sans explication de la note.
B53: Compétences à préciser sur les priorités | G53: =SUM($AP$6:$AP$37) -> 0 | H53: Cibles urgentes ou prioritaires sans choix de compétences valide.
B54: Action à proposer sur les priorités | G54: =SUM($AQ$6:$AQ$37) -> 0 | H54: Cibles urgentes ou prioritaires sans proposition écrite.
B56: Une cellule de taux vide signifie qu’aucune cible ne permet encore de calculer ce taux. Une importance de 0 indique une cible non applicable.
B58: Cibles à traiter en premier
B59: =IF(H16+I16=0,IF(D16=0,"La liste apparaîtra après la saisie des notes.","Aucune cible urgente ou prioritaire parmi les cibles évaluées."),"Les "&MIN(10,H16+I16)&" premières cibles sur "&(H16+I16)&" urgentes ou prioritaires. Ordre : urgence, puis numéro de cible.") -> Les 4 premières cibles sur 4 urgentes ou prioritaires. Ordre : urgence, puis numéro de cible.
B60: Cible | C60: Ce que l’on cherche à faire | G60: Priorité | H60: Niveau / 4 | I60: Compétences | J60: Action proposée (extrait)
B61: =IF(ISNUMBER($AS61),INDEX($AD$6:$AD$37,$AS61),"") -> 1.1 | C61: =IF(ISNUMBER($AS61),INDEX($AE$6:$AE$37,$AS61),"") -> Prendre en compte toutes les étapes de la vie des équipements et des logiciels, de leur création à leur fin de vie, pour contribuer à la transition énergétique. | G61: =IF(ISNUMBER($AS61),IF(INDEX($AB$6:$AB$37,$AS61)=6,"Urgente","Prioritaire"),"") -> Urgente | H61: =IF(ISNUMBER($AS61),INDEX($AG$6:$AG$37,$AS61),"") -> 1 | I61: =IF(ISNUMBER($AS61),IF(INDEX($AH$6:$AH$37,$AS61)=0,"À préciser",CHOOSE(INDEX($AH$6:$AH$37,$AS61),"NR / RSE","Avec DSI","Hors DSI","Externe")),"") -> Hors DSI | J61: =IF(ISNUMBER($AS61),IF(INDEX($AJ$6:$AJ$37,$AS61)=0,"À proposer",LEFT(INDEX($AI$6:$AI$37,$AS61),180)&IF(LEN(INDEX($AI$6:$AI$37,$AS61))>180,"…","")),"") -> Former l’équipe Achats aux critères du numérique responsable et aux labels TCO et EPEAT. Dans les prochains appels d’offres pour remplacer les serveurs, faire compter les critères … | AS61: =IF(1>$H$16+$I$16,"",MATCH(LARGE($AC$6:$AC$37,1),$AC$6:$AC$37,0)) -> 1
B62: =IF(ISNUMBER($AS62),INDEX($AD$6:$AD$37,$AS62),"") -> 1.7 | C62: =IF(ISNUMBER($AS62),INDEX($AE$6:$AE$37,$AS62),"") -> Réserver l’intelligence artificielle aux besoins qui la justifient et privilégier des solutions sobres en ressources. | G62: =IF(ISNUMBER($AS62),IF(INDEX($AB$6:$AB$37,$AS62)=6,"Urgente","Prioritaire"),"") -> Urgente | H62: =IF(ISNUMBER($AS62),INDEX($AG$6:$AG$37,$AS62),"") -> 1 | I62: =IF(ISNUMBER($AS62),IF(INDEX($AH$6:$AH$37,$AS62)=0,"À préciser",CHOOSE(INDEX($AH$6:$AH$37,$AS62),"NR / RSE","Avec DSI","Hors DSI","Externe")),"") -> Avec DSI | J62: =IF(ISNUMBER($AS62),IF(INDEX($AJ$6:$AJ$37,$AS62)=0,"À proposer",LEFT(INDEX($AI$6:$AI$37,$AS62),180)&IF(LEN(INDEX($AI$6:$AI$37,$AS62))>180,"…","")),"") -> 1. Vérifier le besoin avant chaque projet : faut-il de l’IA ou un outil informatique classique suffit-il ? 2. Choisir de petits modèles spécialisés quand ils répondent au besoin. 3… | AS62: =IF(2>$H$16+$I$16,"",MATCH(LARGE($AC$6:$AC$37,2),$AC$6:$AC$37,0)) -> 7
B63: =IF(ISNUMBER($AS63),INDEX($AD$6:$AD$37,$AS63),"") -> 1.8 | C63: =IF(ISNUMBER($AS63),INDEX($AE$6:$AE$37,$AS63),"") -> Mesurer et réduire ce que consomme l’intelligence artificielle, pendant son entraînement comme pendant son utilisation. | G63: =IF(ISNUMBER($AS63),IF(INDEX($AB$6:$AB$37,$AS63)=6,"Urgente","Prioritaire"),"") -> Urgente | H63: =IF(ISNUMBER($AS63),INDEX($AG$6:$AG$37,$AS63),"") -> 1 | I63: =IF(ISNUMBER($AS63),IF(INDEX($AH$6:$AH$37,$AS63)=0,"À préciser",CHOOSE(INDEX($AH$6:$AH$37,$AS63),"NR / RSE","Avec DSI","Hors DSI","Externe")),"") -> Avec DSI | J63: =IF(ISNUMBER($AS63),IF(INDEX($AJ$6:$AJ$37,$AS63)=0,"À proposer",LEFT(INDEX($AI$6:$AI$37,$AS63),180)&IF(LEN(INDEX($AI$6:$AI$37,$AS63))>180,"…","")),"") -> 1. Vérifier le besoin avant chaque projet : faut-il de l’IA ou un outil informatique classique suffit-il ? 2. Choisir de petits modèles spécialisés quand ils répondent au besoin. 3… | AS63: =IF(3>$H$16+$I$16,"",MATCH(LARGE($AC$6:$AC$37,3),$AC$6:$AC$37,0)) -> 8
B64: =IF(ISNUMBER($AS64),INDEX($AD$6:$AD$37,$AS64),"") -> 1.3 | C64: =IF(ISNUMBER($AS64),INDEX($AE$6:$AE$37,$AS64),"") -> Concevoir des services numériques qui limitent leurs effets sur l’environnement. Choisir des technologies qui contribuent aux Objectifs de développement durable (ODD). | G64: =IF(ISNUMBER($AS64),IF(INDEX($AB$6:$AB$37,$AS64)=6,"Urgente","Prioritaire"),"") -> Prioritaire | H64: =IF(ISNUMBER($AS64),INDEX($AG$6:$AG$37,$AS64),"") -> 2 | I64: =IF(ISNUMBER($AS64),IF(INDEX($AH$6:$AH$37,$AS64)=0,"À préciser",CHOOSE(INDEX($AH$6:$AH$37,$AS64),"NR / RSE","Avec DSI","Hors DSI","Externe")),"") -> Avec DSI | J64: =IF(ISNUMBER($AS64),IF(INDEX($AJ$6:$AJ$37,$AS64)=0,"À proposer",LEFT(INDEX($AI$6:$AI$37,$AS64),180)&IF(LEN(INDEX($AI$6:$AI$37,$AS64))>180,"…","")),"") -> 1. Former les équipes de conception, de développement et de gestion de projet à créer des services numériques qui limitent leurs effets sur l’environnement. 2. Ajouter des exigence… | AS64: =IF(4>$H$16+$I$16,"",MATCH(LARGE($AC$6:$AC$37,4),$AC$6:$AC$37,0)) -> 3
B65: =IF(ISNUMBER($AS65),INDEX($AD$6:$AD$37,$AS65),"") | C65: =IF(ISNUMBER($AS65),INDEX($AE$6:$AE$37,$AS65),"") | G65: =IF(ISNUMBER($AS65),IF(INDEX($AB$6:$AB$37,$AS65)=6,"Urgente","Prioritaire"),"") | H65: =IF(ISNUMBER($AS65),INDEX($AG$6:$AG$37,$AS65),"") | I65: =IF(ISNUMBER($AS65),IF(INDEX($AH$6:$AH$37,$AS65)=0,"À préciser",CHOOSE(INDEX($AH$6:$AH$37,$AS65),"NR / RSE","Avec DSI","Hors DSI","Externe")),"") | J65: =IF(ISNUMBER($AS65),IF(INDEX($AJ$6:$AJ$37,$AS65)=0,"À proposer",LEFT(INDEX($AI$6:$AI$37,$AS65),180)&IF(LEN(INDEX($AI$6:$AI$37,$AS65))>180,"…","")),"") | AS65: =IF(5>$H$16+$I$16,"",MATCH(LARGE($AC$6:$AC$37,5),$AC$6:$AC$37,0))
B66: =IF(ISNUMBER($AS66),INDEX($AD$6:$AD$37,$AS66),"") | C66: =IF(ISNUMBER($AS66),INDEX($AE$6:$AE$37,$AS66),"") | G66: =IF(ISNUMBER($AS66),IF(INDEX($AB$6:$AB$37,$AS66)=6,"Urgente","Prioritaire"),"") | H66: =IF(ISNUMBER($AS66),INDEX($AG$6:$AG$37,$AS66),"") | I66: =IF(ISNUMBER($AS66),IF(INDEX($AH$6:$AH$37,$AS66)=0,"À préciser",CHOOSE(INDEX($AH$6:$AH$37,$AS66),"NR / RSE","Avec DSI","Hors DSI","Externe")),"") | J66: =IF(ISNUMBER($AS66),IF(INDEX($AJ$6:$AJ$37,$AS66)=0,"À proposer",LEFT(INDEX($AI$6:$AI$37,$AS66),180)&IF(LEN(INDEX($AI$6:$AI$37,$AS66))>180,"…","")),"") | AS66: =IF(6>$H$16+$I$16,"",MATCH(LARGE($AC$6:$AC$37,6),$AC$6:$AC$37,0))
B67: =IF(ISNUMBER($AS67),INDEX($AD$6:$AD$37,$AS67),"") | C67: =IF(ISNUMBER($AS67),INDEX($AE$6:$AE$37,$AS67),"") | G67: =IF(ISNUMBER($AS67),IF(INDEX($AB$6:$AB$37,$AS67)=6,"Urgente","Prioritaire"),"") | H67: =IF(ISNUMBER($AS67),INDEX($AG$6:$AG$37,$AS67),"") | I67: =IF(ISNUMBER($AS67),IF(INDEX($AH$6:$AH$37,$AS67)=0,"À préciser",CHOOSE(INDEX($AH$6:$AH$37,$AS67),"NR / RSE","Avec DSI","Hors DSI","Externe")),"") | J67: =IF(ISNUMBER($AS67),IF(INDEX($AJ$6:$AJ$37,$AS67)=0,"À proposer",LEFT(INDEX($AI$6:$AI$37,$AS67),180)&IF(LEN(INDEX($AI$6:$AI$37,$AS67))>180,"…","")),"") | AS67: =IF(7>$H$16+$I$16,"",MATCH(LARGE($AC$6:$AC$37,7),$AC$6:$AC$37,0))
B68: =IF(ISNUMBER($AS68),INDEX($AD$6:$AD$37,$AS68),"") | C68: =IF(ISNUMBER($AS68),INDEX($AE$6:$AE$37,$AS68),"") | G68: =IF(ISNUMBER($AS68),IF(INDEX($AB$6:$AB$37,$AS68)=6,"Urgente","Prioritaire"),"") | H68: =IF(ISNUMBER($AS68),INDEX($AG$6:$AG$37,$AS68),"") | I68: =IF(ISNUMBER($AS68),IF(INDEX($AH$6:$AH$37,$AS68)=0,"À préciser",CHOOSE(INDEX($AH$6:$AH$37,$AS68),"NR / RSE","Avec DSI","Hors DSI","Externe")),"") | J68: =IF(ISNUMBER($AS68),IF(INDEX($AJ$6:$AJ$37,$AS68)=0,"À proposer",LEFT(INDEX($AI$6:$AI$37,$AS68),180)&IF(LEN(INDEX($AI$6:$AI$37,$AS68))>180,"…","")),"") | AS68: =IF(8>$H$16+$I$16,"",MATCH(LARGE($AC$6:$AC$37,8),$AC$6:$AC$37,0))
B69: =IF(ISNUMBER($AS69),INDEX($AD$6:$AD$37,$AS69),"") | C69: =IF(ISNUMBER($AS69),INDEX($AE$6:$AE$37,$AS69),"") | G69: =IF(ISNUMBER($AS69),IF(INDEX($AB$6:$AB$37,$AS69)=6,"Urgente","Prioritaire"),"") | H69: =IF(ISNUMBER($AS69),INDEX($AG$6:$AG$37,$AS69),"") | I69: =IF(ISNUMBER($AS69),IF(INDEX($AH$6:$AH$37,$AS69)=0,"À préciser",CHOOSE(INDEX($AH$6:$AH$37,$AS69),"NR / RSE","Avec DSI","Hors DSI","Externe")),"") | J69: =IF(ISNUMBER($AS69),IF(INDEX($AJ$6:$AJ$37,$AS69)=0,"À proposer",LEFT(INDEX($AI$6:$AI$37,$AS69),180)&IF(LEN(INDEX($AI$6:$AI$37,$AS69))>180,"…","")),"") | AS69: =IF(9>$H$16+$I$16,"",MATCH(LARGE($AC$6:$AC$37,9),$AC$6:$AC$37,0))
B70: =IF(ISNUMBER($AS70),INDEX($AD$6:$AD$37,$AS70),"") | C70: =IF(ISNUMBER($AS70),INDEX($AE$6:$AE$37,$AS70),"") | G70: =IF(ISNUMBER($AS70),IF(INDEX($AB$6:$AB$37,$AS70)=6,"Urgente","Prioritaire"),"") | H70: =IF(ISNUMBER($AS70),INDEX($AG$6:$AG$37,$AS70),"") | I70: =IF(ISNUMBER($AS70),IF(INDEX($AH$6:$AH$37,$AS70)=0,"À préciser",CHOOSE(INDEX($AH$6:$AH$37,$AS70),"NR / RSE","Avec DSI","Hors DSI","Externe")),"") | J70: =IF(ISNUMBER($AS70),IF(INDEX($AJ$6:$AJ$37,$AS70)=0,"À proposer",LEFT(INDEX($AI$6:$AI$37,$AS70),180)&IF(LEN(INDEX($AI$6:$AI$37,$AS70))>180,"…","")),"") | AS70: =IF(10>$H$16+$I$16,"",MATCH(LARGE($AC$6:$AC$37,10),$AC$6:$AC$37,0))
B72: Les actions sont abrégées ici. Consulter l’onglet ONR de la cible pour lire le texte complet et préparer la mise en œuvre.
B73: Au-delà de dix priorités, consulter « Résultats détaillés ». Les égalités de priorité sont classées par numéro, sans différence d’importance.

Sheet Liste ONR
A1: 1.1 | B1: Prendre en compte toutes les étapes de la vie des équipements et des logiciels, de leur création à leur fin de vie, pour contribuer à la transition énergétique.
A2: 1.2 | B2: Utiliser les équipements plus longtemps, même après la fin de leur amortissement, c’est-à-dire la période sur laquelle leur coût est réparti dans les comptes.
A3: 1.3 | B3: Concevoir des services numériques qui limitent leurs effets sur l’environnement. Choisir des technologies qui contribuent aux Objectifs de développement durable (ODD).
A4: 1.4 | B4: Adopter des pratiques qui consomment moins de matériel, de ressources, d’énergie et de consommables, comme le papier ou l’encre.
A5: 1.5 | B5: Réutiliser ou recycler les déchets pour en faire de nouvelles ressources. Soutenir les emplois liés à leur traitement et à l’économie circulaire.
A6: 1.6 | B6: Choisir des énergies renouvelables et encourager leur utilisation.
A7: 1.7 | B7: Réserver l’intelligence artificielle aux besoins qui la justifient et privilégier des solutions sobres en ressources.
A8: 1.8 | B8: Mesurer et réduire ce que consomme l’intelligence artificielle, pendant son entraînement comme pendant son utilisation.
A9: 2.1 | B9: Intégrer dans tous les achats des exigences qui tiennent compte de leurs effets sur la société et l’environnement.
A10: 2.2 | B10: Rendre les services numériques accessibles à toutes et tous. Mesurer leur respect du RGAA, le référentiel français sur l’accessibilité numérique.
A11: 2.3 | B11: Créer des applications utiles, faciles à utiliser et réellement utilisées : les « 3 U ». Les rendre accessibles pour permettre à chacun d’utiliser le numérique.
A12: 2.4 | B12: Concevoir les services avec leurs utilisateurs et utilisatrices, en se concentrant sur leurs besoins réels.
... A32: 5.7 | B32: Décider avec les équipes comment utiliser l’intelligence artificielle. Les former à ses limites et préserver le sens de leur travail.
